Workbook
Name Tile_Level_Carpet: 'Tile Product Lists'!$K$2:$K$30
Name Tile_Level_Curb: 'Tile Product Lists'!$J$2:$J$30
Name Tile_Level_Floor_Tile: 'Tile Product Lists'!$D$2:$D$30
Name Tile_Level_Kitchen_Backsplash: 'Tile Product Lists'!$C$2:$C$30
Name Tile_Level_Knee_Wall_Cap: 'Tile Product Lists'!$I$2:$I$30
Name Tile_Level_List: 'Tile Product Lists'!$B$2:$B$30
Name Tile_Level_Listel: 'Tile Product Lists'!$E$2:$E$30
Name Tile_Level_LVP: 'Tile Product Lists'!$L$2:$L$30
Name Tile_Level_Shower_Pan_Tile: 'Tile Product Lists'!$F$2:$F$30
Name Tile_Level_Shower_Tub_Wall_Tile: 'Tile Product Lists'!$G$2:$G$30
Name Tile_Level_Sill: 'Tile Product Lists'!$H$2:$H$30
Name Tile_Level_Wood: 'Tile Product Lists'!$M$2:$M$30
Name Tile_Product_Carpet_Level_1: 'Tile Product Lists'!$BD$2:$BD$30
Name Tile_Product_Curb_Level_1: 'Tile Product Lists'!$BC$2:$BC$30
Name Tile_Product_Floor_Tile_Level_1: 'Tile Product Lists'!$Y$2:$Y$30
Name Tile_Product_Floor_Tile_Level_2: 'Tile Product Lists'!$Z$2:$Z$30
Name Tile_Product_Floor_Tile_Level_3: 'Tile Product Lists'!$AA$2:$AA$30
Name Tile_Product_Floor_Tile_Level_4: 'Tile Product Lists'!$AB$2:$AB$30
Name Tile_Product_Floor_Tile_Level_5: 'Tile Product Lists'!$AC$2:$AC$30
Name Tile_Product_Floor_Tile_Level_6: 'Tile Product Lists'!$AD$2:$AD$30
Name Tile_Product_Floor_Tile_Level_7: 'Tile Product Lists'!$AE$2:$AE$30
Name Tile_Product_Floor_Tile_Level_8: 'Tile Product Lists'!$AF$2:$AF$30
Name Tile_Product_Floor_Tile_Level_9: 'Tile Product Lists'!$AG$2:$AG$30
Name Tile_Product_Kitchen_Backsplash_Level_1: 'Tile Product Lists'!$P$2:$P$30
Name Tile_Product_Kitchen_Backsplash_Level_2: 'Tile Product Lists'!$Q$2:$Q$30
Name Tile_Product_Kitchen_Backsplash_Level_3: 'Tile Product Lists'!$R$2:$R$30
Name Tile_Product_Kitchen_Backsplash_Level_4: 'Tile Product Lists'!$S$2:$S$30
Name Tile_Product_Kitchen_Backsplash_Level_5: 'Tile Product Lists'!$T$2:$T$30
Name Tile_Product_Kitchen_Backsplash_Level_6: 'Tile Product Lists'!$U$2:$U$30
Name Tile_Product_Kitchen_Backsplash_Level_7: 'Tile Product Lists'!$V$2:$V$30
Name Tile_Product_Kitchen_Backsplash_Level_8: 'Tile Product Lists'!$W$2:$W$30
Name Tile_Product_Kitchen_Backsplash_Level_9: 'Tile Product Lists'!$X$2:$X$30
Name Tile_Product_Knee_Wall_Cap_Level_1: 'Tile Product Lists'!$BB$2:$BB$30
Name Tile_Product_Listel_Level_1: 'Tile Product Lists'!$AH$2:$AH$30
Name Tile_Product_Listel_Level_2: 'Tile Product Lists'!$AI$2:$AI$30
Name Tile_Product_Listel_Level_3: 'Tile Product Lists'!$AJ$2:$AJ29
Name Tile_Product_Listel_Level_4: 'Tile Product Lists'!$AK$2:$AK$30
Name Tile_Product_Listel_Level_5: 'Tile Product Lists'!$AL$2:$AL$30
Name Tile_Product_LVP_Level_1: 'Tile Product Lists'!$BE$2:$BE$30
Name Tile_Product_Shower_Pan_Tile_Level_1: 'Tile Product Lists'!$AM$2:$AM$30
Name Tile_Product_Shower_Pan_Tile_Level_2: 'Tile Product Lists'!$AN$2:$AN$30
Name Tile_Product_Shower_Pan_Tile_Level_3: 'Tile Product Lists'!$AO$2:$AO$30
Name Tile_Product_Shower_Pan_Tile_Level_4: 'Tile Product Lists'!$AP$2:$AP$30
Name Tile_Product_Shower_Pan_Tile_Level_5: 'Tile Product Lists'!$AQ$2:$AQ$30
Name Tile_Product_Shower_Tub_Wall_Tile_Level_1: 'Tile Product Lists'!$AR$2:$AR$30
Name Tile_Product_Shower_Tub_Wall_Tile_Level_2: 'Tile Product Lists'!$AS$2:$AS$30
Name Tile_Product_Shower_Tub_Wall_Tile_Level_3: 'Tile Product Lists'!$AT$2:$AT$30
Name Tile_Product_Shower_Tub_Wall_Tile_Level_4: 'Tile Product Lists'!$AU$2:$AU$30
Name Tile_Product_Shower_Tub_Wall_Tile_Level_5: 'Tile Product Lists'!$AV$2:$AV$30
Name Tile_Product_Shower_Tub_Wall_Tile_Level_6: 'Tile Product Lists'!$AW$2:$AW$30
Name Tile_Product_Shower_Tub_Wall_Tile_Level_7: 'Tile Product Lists'!$AX$2:$AX$30
Name Tile_Product_Shower_Tub_Wall_Tile_Level_8: 'Tile Product Lists'!$AY$2:$AY$30
Name Tile_Product_Shower_Tub_Wall_Tile_Level_9: 'Tile Product Lists'!$AZ$2:$AZ$30
Name Tile_Product_Sill_Level_1: 'Tile Product Lists'!$BA$2:$BA$30
Name Tile_Product_Wood_Level_1: 'Tile Product Lists'!$BF$2:$BF$30
Name Tile_Section_List: 'Tile Product Lists'!$A$2:$A$30

Sheet Customer Option Cover Page
D2: Once selections have been reviewed and signed by both parties, they are considered final. We understand that adjustments may occasionally be requested; however, changes made after approval and/or after construction has begun may result in additional costs and are subject to the Builder’s review and approval. To ensure clarity and accuracy, any changes must be documented and signed by both parties prior to implementation. This Customer Option Form agreement is non-refundable. However, if any selected option is not installed, a full refund for the individual option(s) will be credited at closing
C3: CUSTOMER OPTION FORM #1
B5: DATE: | C5: =TODAY() -> 46259
B6: CUSTOMER: | C6: John Doe | E6: Allowance Estimated Pricing Subject to change, based on final installed price
B7: JOB ADDRESS: | C7: 123 avenue
B8: ALLOWANCES
B9: PRICE REQUEST ITEMS BY HOMEOWNER | D9: Please Note: Pricing may fluctuate on items that are priced out for the Homeowners from the time of price request to time of homeowner approval. A charge or credit will apply at the time of ordering.
B10: "Ballpark" Prelim. Estimate
B11: CLARIFICATIONS (NO PRICE CHANGE)
B12: PRICING READY TO SHOW HOMEOWNER
B13: HOMEOWNER REVIEWING
B14: PRICING APPROVED BY HOMEOWNER
B15: Eric Olsen
B16: Sarah Brown
B17: Stephanie Throop
B18: Ashley Birmingham
B19: Monique Lumsley
B20: TOP PRIORITY
B21: (Select Status)
B22: Category | C22: Description | D22: Date | E22: Revised by: | F22: Allowance | G22: Final price | H22: Difference | I22: Status
B23: Allowance | C23: Designer Time
B24: Allowance | C24: Appliance Allowance | H24: Overage To be paid directly to the Appliance Co. | I24: ALLOWANCES
B25: Allowance | C25: Cabinetry Allowance: This is allowance for base cabinetry throughout the home. Added items or options will be priced separately below. | I25: ALLOWANCES
B26: Allowance | C26: Cabinetry Hardware Standard: | H26: Placeholder | I26: ALLOWANCES
B27: Allowance | C27: Drywall/Duro/Densglass Material Allowance: | I27: ALLOWANCES
B28: Allowance | C28: Electrical Allowance: This allowance is for base electrical for the home. Upgraded or added items will be priced separately below. | I28: ALLOWANCES
B29: Allowance | C29: Exterior Doors Allowance: | I29: ALLOWANCES
B30: Allowance | C30: Exterior Railing Allowance: | I30: ALLOWANCES
B31: Allowance | C31: Garage Door Allowance: | I31: ALLOWANCES
B32: Allowance | C32: Granite Countertop Allowance: | I32: ALLOWANCES
B33: Allowance | C33: Impact Fees Allowance: | I33: ALLOWANCES
B34: Allowance | C34: Interior Railing Allowance: | I34: ALLOWANCES
B35: Allowance | C35: Landscaping Allowance: | H35: Overage To be paid directly to the Landscaping Co. | I35: ALLOWANCES
B36: Allowance | C36: Light Fixture Allowance | H36: Overage To be paid directly to the Lighting Co. | I36: ALLOWANCES
B37: Allowance | C37: Lumber Allowance: | I37: ALLOWANCES
B38: Allowance | C38: Paver Allowance: More may be needed once survey is finalized and approved. | I38: ALLOWANCES
B39: Allowance | C39: Plumbing Allowance: This allowance is for base plumbing for the home. Upgraded or added items will be priced separately below. | I39: ALLOWANCES
B40: Allowance | C40: Pool Allowance: | H40: Overage To be paid directly to the Pool Co. | I40: ALLOWANCES
B41: Allowance | C41: Roofing Allowance: | I41: ALLOWANCES
B42: Allowance | C42: Sitework Allowance: THERE MAY BE ADDITONAL WORK ON TH LOT AT THE END OF THE PROJECT AS WELL AS POTENTIAL DEGRASS OF AREAS WE LEAVE UNITL THE END. | I42: ALLOWANCES
B43: Allowance | C43: Truss Allowance | I43: ALLOWANCES
B44: Allowance | C44: Windows Allowance: | I44: ALLOWANCES
C45: Changes made during plan design stage: | I45: (Select Status)
I46: (Select Status)
I47: (Select Status)
I48: (Select Status)
I49: (Select Status)
I50: (Select Status)
I51: (Select Status)
I52: (Select Status)
I53: (Select Status)
I54: (Select Status)
C55: Plan Changes made during Exterior Color Selection Meeting with Designer | I55: (Select Status)
I56: (Select Status)
I57: (Select Status)
I58: (Select Status)
I59: (Select Status)
I60: (Select Status)
I61: (Select Status)
I62: (Select Status)
I63: (Select Status)
I64: (Select Status)
I65: (Select Status)
I66: (Select Status)
C67: Changes made during color selection stage: | I67: (Select Status)
I68: (Select Status)
I69: (Select Status)
I70: (Select Status)
I71: (Select Status)
I72: (Select Status)
I73: (Select Status)
I74: (Select Status)
I75: (Select Status)
I76: (Select Status)
I77: (Select Status)
I78: (Select Status)
I79: (Select Status)
G81: TOTAL: | H81: =SUM(H24:H79) -> 0
B82: Customer Signature | C82: Date of Approval:
B84: Builder Signature | C84: Date of Approval:
B86: Date Paid

Sheet Allowances
A1: ='Customer Option Cover Page'!C6 -> John Doe
A2: ='Customer Option Cover Page'!C7 -> 123 avenue
B3: DATE: | C3: =TODAY() -> 46259
B4: CUSTOMER: | C4: ='Customer Option Cover Page'!C6 -> John Doe
B5: JOB ADDRESS: | C5: ='Customer Option Cover Page'!C7 -> 123 avenue
B7: Category | C7: Description | D7: Date | E7: Allowance | F7: Actuals | G7: Difference
B8: Allowance | C8: Drywall/Duro/Densglass Material Allowance:
B9: Allowance | C9: Electrical Allowance: This allowance is for base electrical for the home. Upgraded or added items will be priced separately below.
B10: Allowance | C10: Impact Fees Allowance:
B11: Allowance | C11: Lumber Allowance:
B12: Allowance | C12: Plumbing Allowance: This allowance is for base plumbing for the home. Upgraded or added items will be priced separately below.
B13: Allowance | C13: Roofing Allowance:
B14: Allowance | C14: Sitework Allowance: THERE MAY BE ADDITONAL WORK ON TH LOT AT THE END OF THE PROJECT AS WELL AS POTENTIAL DEGRASS OF AREAS WE LEAVE UNITL THE END.
B15: Allowance | C15: Truss Allowance
B16: Allowance | C16: Windows Allowance:

Sheet Options
A1: ='Customer Option Cover Page'!C6 -> John Doe
A2: ='Customer Option Cover Page'!C7 -> 123 avenue
B3: DATE: | C3: =TODAY() -> 46259
B4: CUSTOMER: | C4: =A1 -> John Doe
B5: JOB ADDRESS: | C5: =A2 -> 123 avenue
B7: Category | C7: Description | D7: Date | E7: Revised by: | F7: Contract Pricing Page | G7: Final price | H7: Difference

Sheet Countertops
B2: Countertop Quick Pricing Sheet | L2: ='Customer Option Cover Page'!C6 -> John Doe
B3: =U18 -> *All pricing displayed on this page is subject to change at the sole discression of Olsen Custom Homes. Pricing will be finalized via a customer option form.* | L3: ='Customer Option Cover Page'!C7 -> 123 avenue
B4: Designer Information | K4: Estimator | U4: Summary | X4: Instructions
B5: Area | C5: Type | D5: Detail | E5: Product Name | F5: Level | G5: Included? | H5: Edge Style | I5: Cutouts? | J5: Notes | K5: Qty_Est | L5: Qty_Pad | M5: Units | N5: $ / Unit | O5: Olsen Total | P5: Included | Q5: Difference | R5: Charge HO | U5: Allowance Total: | V5: 30000 | X5: **Please read this and follow the process EXACTLY**
L6: 0.1 | R6: 0.65 | X6: Instructions for ESTIMATOR
B7: Kitchen | U7: Area | V7: Charge to HO | X7: Instructions for ESTIMATOR (BEFORE-HO meeting)
B8: Countertop #1 | C8: Countertop Surface | D8: Surface Type | E8: Dallas White | F8: =VLOOKUP(E8,Counter_Pricing[[Material_Name]:[Level]],5,0) -> Level 1 | K8: 92 | L8: =K8*(1+$L$6) -> 101.2 | M8: SF | N8: =INDEX(Counter_Pricing[Olsen_Cost],MATCH(F8,Counter_Pricing[Level])) -> 38 | O8: =L8*N8 -> 3845.6 | P8: =(L8/SUM($L$8:$L$137))*$V$5 -> 255.3664 | Q8: =O8-P8 -> 3590.2336 | R8: =IF(Q8>0,Q8/$R$6,Q8) -> 5523.4363 | U8: =B7 -> Kitchen | V8: =R25 -> 45055.758 | X8: Step #1: Input correct allowance total in cell V5
B9: Countertop #1 | C9: Edge Type | D9: Eased Edge | E9: Eased Edge | F9: =VLOOKUP(E9,Counter_Pricing[[Material_Name]:[Level]],5,0) -> Labor | K9: 93 | L9: =K9*(1+$L$6) -> 102.3 | M9: LF | N9: =INDEX(Counter_Pricing[Olsen_Cost],MATCH(F9,Counter_Pricing[Level])) -> 0 | O9: =L9*N9 -> 0 | P9: =(L9/SUM($L$8:$L$137))*$V$5 -> 258.14212 | Q9: =O9-P9 -> -258.14212 | R9: =IF(Q9>0,Q9/$R$6,Q9) -> -258.14212 | U9: =B26 -> Master Bathroom | V9: =R41 -> 45055.758 | X9: Step #2: Assign all Rooms in BLACK Rows (7, 31,44, 57,70,83,96,109,122)
B10: Countertop #1 | C10: Cutout | D10: Sink (Undermount) | E10: Sink Cutout | F10: =VLOOKUP(E10,Counter_Pricing[[Material_Name]:[Level]],5,0) -> Labor | K10: 94 | L10: =K10*(1+$L$6) -> 103.4 | M10: SF | N10: =INDEX(Counter_Pricing[Olsen_Cost],MATCH(F10,Counter_Pricing[Level])) -> 0 | O10: =L10*N10 -> 0 | P10: =(L10/SUM($L$8:$L$137))*$V$5 -> 260.91784 | Q10: =O10-P10 -> -260.91784 | R10: =IF(Q10>0,Q10/$R$6,Q10) -> -260.91784 | U10: =B42 -> Bathroom #2 | V10: =R57 -> 45055.758 | X10: Step #3: Assign all areas receiving tile Column B
B11: Countertop #2 | C11: Countertop Surface | D11: Surface Type | E11: Dallas White | F11: =VLOOKUP(E11,Counter_Pricing[[Material_Name]:[Level]],5,0) -> Level 1 | K11: 95 | L11: =K11*(1+$L$6) -> 104.5 | M11: SF | N11: =INDEX(Counter_Pricing[Olsen_Cost],MATCH(F11,Counter_Pricing[Level])) -> 38 | O11: =L11*N11 -> 3971 | P11: =(L11/SUM($L$8:$L$137))*$V$5 -> 263.69356 | Q11: =O11-P11 -> 3707.3064 | R11: =IF(Q11>0,Q11/$R$6,Q11) -> 5703.5484 | U11: =B58 -> Bathroom #3 | V11: =R73 -> 45055.758 | X11: Step #4: Input each square footage estimate in Column L
B12: Countertop #2 | C12: Edge Type | D12: Mitered Edge | E12: Mitered Edge | F12: =VLOOKUP(E12,Counter_Pricing[[Material_Name]:[Level]],5,0) -> Labor | K12: 96 | L12: =K12*(1+$L$6) -> 105.6 | M12: SF | N12: =INDEX(Counter_Pricing[Olsen_Cost],MATCH(F12,Counter_Pricing[Level])) -> 0 | O12: =L12*N12 -> 0 | P12: =(L12/SUM($L$8:$L$137))*$V$5 -> 266.46928 | Q12: =O12-P12 -> -266.46928 | R12: =IF(Q12>0,Q12/$R$6,Q12) -> -266.46928 | U12: =B74 -> Bathroom #4 | V12: =R89 -> 45055.758 | X12: Step #5: Hide Columns L, Q, and R (highlighted in red)
B13: Countertop #2 | C13: Cutout | D13: Cooktop | E13: Sink Cutout | F13: =VLOOKUP(E13,Counter_Pricing[[Material_Name]:[Level]],5,0) -> Labor | K13: 97 | L13: =K13*(1+$L$6) -> 106.7 | M13: SF | N13: =INDEX(Counter_Pricing[Olsen_Cost],MATCH(F13,Counter_Pricing[Level])) -> 0 | O13: =L13*N13 -> 0 | P13: =(L13/SUM($L$8:$L$137))*$V$5 -> 269.245 | Q13: =O13-P13 -> -269.245 | R13: =IF(Q13>0,Q13/$R$6,Q13) -> -269.245 | U13: =B86 -> Countertop | V13: =R105 -> #N/A | X13: Step #6: Verify Pricing is correct at bottom of sheet
B14: Countertop #2 | C14: Cutout | D14: Sink (Undermount) | E14: Sink Cutout | F14: =VLOOKUP(E14,Counter_Pricing[[Material_Name]:[Level]],5,0) -> Labor | K14: 98 | L14: =K14*(1+$L$6) -> 107.8 | M14: SF | N14: =INDEX(Counter_Pricing[Olsen_Cost],MATCH(F14,Counter_Pricing[Level])) -> 0 | O14: =L14*N14 -> 0 | P14: =(L14/SUM($L$8:$L$137))*$V$5 -> 272.02073 | Q14: =O14-P14 -> -272.02073 | R14: =IF(Q14>0,Q14/$R$6,Q14) -> -272.02073 | U14: =B90 -> Pantry | V14: =R105 -> #N/A | X14: Instructions for DESIGNER (BEFORE HO Meeting)
B15: Island Countertop | C15: Countertop Surface | D15: Surface Type | E15: Dallas White | F15: =VLOOKUP(E15,Counter_Pricing[[Material_Name]:[Level]],5,0) -> Level 1 | K15: 95 | L15: =K15*(1+$L$6) -> 104.5 | M15: SF | N15: =INDEX(Counter_Pricing[Olsen_Cost],MATCH(F15,Counter_Pricing[Level])) -> 38 | O15: =L15*N15 -> 3971 | P15: =(L15/SUM($L$8:$L$137))*$V$5 -> 263.69356 | Q15: =O15-P15 -> 3707.3064 | R15: =IF(Q15>0,Q15/$R$6,Q15) -> 5703.5484 | U15: =B106 -> 0 | V15: =R121 -> #N/A | X15: Step #1: Input any selections from BT if client has already made them
B16: Island Countertop | C16: Edge Type | D16: Eased Edge | E16: Eased Edge | F16: =VLOOKUP(E16,Counter_Pricing[[Material_Name]:[Level]],5,0) -> Labor | K16: 96 | L16: =K16*(1+$L$6) -> 105.6 | M16: SF | N16: =INDEX(Counter_Pricing[Olsen_Cost],MATCH(F16,Counter_Pricing[Level])) -> 0 | O16: =L16*N16 -> 0 | P16: =(L16/SUM($L$8:$L$137))*$V$5 -> 266.46928 | Q16: =O16-P16 -> -266.46928 | R16: =IF(Q16>0,Q16/$R$6,Q16) -> -266.46928 | U16: =B122 -> 0 | V16: =R137 -> #N/A | X16: Step #2: Verify Estimator has input ALL area information in Column L
B17: Island Countertop | C17: Waterfall Surface | D17: Surface Type | E17: Dallas White | F17: =VLOOKUP(E17,Counter_Pricing[[Material_Name]:[Level]],5,0) -> Level 1 | H17: Left Waterfall | K17: 97 | L17: =K17*(1+$L$6) -> 106.7 | M17: SF | N17: =INDEX(Counter_Pricing[Olsen_Cost],MATCH(F17,Counter_Pricing[Level])) -> 38 | O17: =L17*N17 -> 4054.6 | P17: =(L17/SUM($L$8:$L$137))*$V$5 -> 269.245 | Q17: =O17-P17 -> 3785.355 | R17: =IF(Q17>0,Q17/$R$6,Q17) -> 5823.6231 | U17: Total Charge to HO: | V17: =SUM(V8:V16) -> #N/A
B18: Island Countertop | C18: Surface Type | D18: Surface Type | E18: Dallas White | F18: =VLOOKUP(E18,Counter_Pricing[[Material_Name]:[Level]],5,0) -> Level 1 | K18: 98 | L18: =K18*(1+$L$6) -> 107.8 | M18: SF | N18: =INDEX(Counter_Pricing[Olsen_Cost],MATCH(F18,Counter_Pricing[Level])) -> 38 | O18: =L18*N18 -> 4096.4 | P18: =(L18/SUM($L$8:$L$137))*$V$5 -> 272.02073 | Q18: =O18-P18 -> 3824.3793 | R18: =IF(Q18>0,Q18/$R$6,Q18) -> 5883.6604 | U18: *All pricing displayed on this page is subject to change at the sole discression of Olsen Custom Homes. Pricing will be finalized via a customer option form.* | X18: Instructions for DESIGNER (During HO Meeting)
B19: Countertop | C19: Surface Type | D19: Surface Type | E19: Dallas White | F19: =VLOOKUP(E19,Counter_Pricing[[Material_Name]:[Level]],5,0) -> Level 1 | K19: 99 | L19: =K19*(1+$L$6) -> 108.9 | M19: SF | N19: =INDEX(Counter_Pricing[Olsen_Cost],MATCH(F19,Counter_Pricing[Level])) -> 38 | O19: =L19*N19 -> 4138.2 | P19: =(L19/SUM($L$8:$L$137))*$V$5 -> 274.79645 | Q19: =O19-P19 -> 3863.4036 | R19: =IF(Q19>0,Q19/$R$6,Q19) -> 5943.6978 | X19: Step #1: Select Type of Tile in Column C
B20: Countertop | C20: Surface Type | D20: Surface Type | E20: Dallas White | F20: =VLOOKUP(E20,Counter_Pricing[[Material_Name]:[Level]],5,0) -> Level 1 | K20: 100 | L20: =K20*(1+$L$6) -> 110 | M20: SF | N20: =INDEX(Counter_Pricing[Olsen_Cost],MATCH(F20,Counter_Pricing[Level])) -> 38 | O20: =L20*N20 -> 4180 | P20: =(L20/SUM($L$8:$L$137))*$V$5 -> 277.57217 | Q20: =O20-P20 -> 3902.4278 | R20: =IF(Q20>0,Q20/$R$6,Q20) -> 6003.7351 | X20: Step #2: Select Level of Tile in Column D
B21: Countertop | C21: Surface Type | D21: Surface Type | E21: Dallas White | F21: =VLOOKUP(E21,Counter_Pricing[[Material_Name]:[Level]],5,0) -> Level 1 | K21: 101 | L21: =K21*(1+$L$6) -> 111.1 | M21: SF | N21: =INDEX(Counter_Pricing[Olsen_Cost],MATCH(F21,Counter_Pricing[Level])) -> 38 | O21: =L21*N21 -> 4221.8 | P21: =(L21/SUM($L$8:$L$137))*$V$5 -> 280.34789 | Q21: =O21-P21 -> 3941.4521 | R21: =IF(Q21>0,Q21/$R$6,Q21) -> 6063.7725 | X21: Step #3: Select Product Name in Column E
X22: Step $4: Select Finish, Pattern, Direction, Grout and Joint
X23: Step #5: Input Niche width and height (=0 if no niche)
X24: Step #6: Add special instructions and notes
O25: *HO Pays: | R25: =SUM(R8:R24) -> 45055.758 | X25: Step #7: Explain to client this pricing is a ballpark price
B26: Master Bathroom | X26: Step #8: Verify ALL lines with SF value also have selection before pricing!!
B27: Countertop #1 | C27: Countertop Surface | D27: Surface Type | E27: Dallas White | F27: =VLOOKUP(E27,Counter_Pricing[[Material_Name]:[Level]],5,0) -> Level 1 | K27: 92 | L27: =K27*(1+$L$6) -> 101.2 | M27: SF | N27: =INDEX(Counter_Pricing[Olsen_Cost],MATCH(F27,Counter_Pricing[Level])) -> 38 | O27: =L27*N27 -> 3845.6 | P27: =(L27/SUM($L$8:$L$136))*$V$5 -> 255.3664 | Q27: =O27-P27 -> 3590.2336 | R27: =IF(Q27>0,Q27/$R$6,Q27) -> 5523.4363 | X27: Step #9: Add thin info and pricing to buildertrend and get a signoff
B28: Countertop #1 | C28: Edge Type | D28: Eased Edge | E28: Eased Edge | F28: =VLOOKUP(E28,Counter_Pricing[[Material_Name]:[Level]],5,0) -> Labor | K28: 93 | L28: =K28*(1+$L$6) -> 102.3 | M28: LF | N28: =INDEX(Counter_Pricing[Olsen_Cost],MATCH(F28,Counter_Pricing[Level])) -> 0 | O28: =L28*N28 -> 0 | P28: =(L28/SUM($L$8:$L$136))*$V$5 -> 258.14212 | Q28: =O28-P28 -> -258.14212 | R28: =IF(Q28>0,Q28/$R$6,Q28) -> -258.14212 | X28: Step #10: Add correct language to the COF and total charge to HO (Cell V17)
B29: Countertop #1 | C29: Cutout | D29: Sink (Undermount) | E29: Sink Cutout | F29: =VLOOKUP(E29,Counter_Pricing[[Material_Name]:[Level]],5,0) -> Labor | K29: 94 | L29: =K29*(1+$L$6) -> 103.4 | M29: SF | N29: =INDEX(Counter_Pricing[Olsen_Cost],MATCH(F29,Counter_Pricing[Level])) -> 0 | O29: =L29*N29 -> 0 | P29: =(L29/SUM($L$8:$L$136))*$V$5 -> 260.91784 | Q29: =O29-P29 -> -260.91784 | R29: =IF(Q29>0,Q29/$R$6,Q29) -> -260.91784
B30: Countertop #2 | C30: Countertop Surface | D30: Surface Type | E30: Dallas White | F30: =VLOOKUP(E30,Counter_Pricing[[Material_Name]:[Level]],5,0) -> Level 1 | K30: 95 | L30: =K30*(1+$L$6) -> 104.5 | M30: SF | N30: =INDEX(Counter_Pricing[Olsen_Cost],MATCH(F30,Counter_Pricing[Level])) -> 38 | O30: =L30*N30 -> 3971 | P30: =(L30/SUM($L$8:$L$136))*$V$5 -> 263.69356 | Q30: =O30-P30 -> 3707.3064 | R30: =IF(Q30>0,Q30/$R$6,Q30) -> 5703.5484
B31: Countertop #2 | C31: Edge Type | D31: Mitered Edge | E31: Mitered Edge | F31: =VLOOKUP(E31,Counter_Pricing[[Material_Name]:[Level]],5,0) -> Labor | K31: 96 | L31: =K31*(1+$L$6) -> 105.6 | M31: SF | N31: =INDEX(Counter_Pricing[Olsen_Cost],MATCH(F31,Counter_Pricing[Level])) -> 0 | O31: =L31*N31 -> 0 | P31: =(L31/SUM($L$8:$L$136))*$V$5 -> 266.46928 | Q31: =O31-P31 -> -266.46928 | R31: =IF(Q31>0,Q31/$R$6,Q31) -> -266.46928
B32: Countertop #2 | C32: Cutout | D32: Cooktop | E32: Sink Cutout | F32: =VLOOKUP(E32,Counter_Pricing[[Material_Name]:[Level]],5,0) -> Labor | K32: 97 | L32: =K32*(1+$L$6) -> 106.7 | M32: SF | N32: =INDEX(Counter_Pricing[Olsen_Cost],MATCH(F32,Counter_Pricing[Level])) -> 0 | O32: =L32*N32 -> 0 | P32: =(L32/SUM($L$8:$L$136))*$V$5 -> 269.245 | Q32: =O32-P32 -> -269.245 | R32: =IF(Q32>0,Q32/$R$6,Q32) -> -269.245
B33: Countertop #2 | C33: Cutout | D33: Sink (Undermount) | E33: Sink Cutout | F33: =VLOOKUP(E33,Counter_Pricing[[Material_Name]:[Level]],5,0) -> Labor | K33: 98 | L33: =K33*(1+$L$6) -> 107.8 | M33: SF | N33: =INDEX(Counter_Pricing[Olsen_Cost],MATCH(F33,Counter_Pricing[Level])) -> 0 | O33: =L33*N33 -> 0 | P33: =(L33/SUM($L$8:$L$136))*$V$5 -> 272.02073 | Q33: =O33-P33 -> -272.02073 | R33: =IF(Q33>0,Q33/$R$6,Q33) -> -272.02073 | X33: Instructions for ESTIMATOR (After-HO meeting)
B34: Island Countertop | C34: Countertop Surface | D34: Surface Type | E34: Dallas White | F34: =VLOOKUP(E34,Counter_Pricing[[Material_Name]:[Level]],5,0) -> Level 1 | K34: 95 | L34: =K34*(1+$L$6) -> 104.5 | M34: SF | N34: =INDEX(Counter_Pricing[Olsen_Cost],MATCH(F34,Counter_Pricing[Level])) -> 38 | O34: =L34*N34 -> 3971 | P34: =(L34/SUM($L$8:$L$136))*$V$5 -> 263.69356 | Q34: =O34-P34 -> 3707.3064 | R34: =IF(Q34>0,Q34/$R$6,Q34) -> 5703.5484 | X34: Step #1: Verify Pricing
B35: Island Countertop | C35: Edge Type | D35: Eased Edge | E35: Eased Edge | F35: =VLOOKUP(E35,Counter_Pricing[[Material_Name]:[Level]],5,0) -> Labor | K35: 96 | L35: =K35*(1+$L$6) -> 105.6 | M35: SF | N35: =INDEX(Counter_Pricing[Olsen_Cost],MATCH(F35,Counter_Pricing[Level])) -> 0 | O35: =L35*N35 -> 0 | P35: =(L35/SUM($L$8:$L$136))*$V$5 -> 266.46928 | Q35: =O35-P35 -> -266.46928 | R35: =IF(Q35>0,Q35/$R$6,Q35) -> -266.46928 | X35: Step #2: Assign all Rooms in Rows 8, 29,42, 55,68,81,94,107,120
B36: Island Countertop | C36: Waterfall Surface | D36: Surface Type | E36: Dallas White | F36: =VLOOKUP(E36,Counter_Pricing[[Material_Name]:[Level]],5,0) -> Level 1 | H36: Left Waterfall | K36: 97 | L36: =K36*(1+$L$6) -> 106.7 | M36: SF | N36: =INDEX(Counter_Pricing[Olsen_Cost],MATCH(F36,Counter_Pricing[Level])) -> 38 | O36: =L36*N36 -> 4054.6 | P36: =(L36/SUM($L$8:$L$136))*$V$5 -> 269.245 | Q36: =O36-P36 -> 3785.355 | R36: =IF(Q36>0,Q36/$R$6,Q36) -> 5823.6231 | X36: Step #3: Assign all areas receiving tile Column B
B37: Island Countertop | C37: Surface Type | D37: Surface Type | E37: Dallas White | F37: =VLOOKUP(E37,Counter_Pricing[[Material_Name]:[Level]],5,0) -> Level 1 | K37: 98 | L37: =K37*(1+$L$6) -> 107.8 | M37: SF | N37: =INDEX(Counter_Pricing[Olsen_Cost],MATCH(F37,Counter_Pricing[Level])) -> 38 | O37: =L37*N37 -> 4096.4 | P37: =(L37/SUM($L$8:$L$136))*$V$5 -> 272.02073 | Q37: =O37-P37 -> 3824.3793 | R37: =IF(Q37>0,Q37/$R$6,Q37) -> 5883.6604
B38: Countertop | C38: Surface Type | D38: Surface Type | E38: Dallas White | F38: =VLOOKUP(E38,Counter_Pricing[[Material_Name]:[Level]],5,0) -> Level 1 | K38: 99 | L38: =K38*(1+$L$6) -> 108.9 | M38: SF | N38: =INDEX(Counter_Pricing[Olsen_Cost],MATCH(F38,Counter_Pricing[Level])) -> 38 | O38: =L38*N38 -> 4138.2 | P38: =(L38/SUM($L$8:$L$136))*$V$5 -> 274.79645 | Q38: =O38-P38 -> 3863.4036 | R38: =IF(Q38>0,Q38/$R$6,Q38) -> 5943.6978
B39: Countertop | C39: Surface Type | D39: Surface Type | E39: Dallas White | F39: =VLOOKUP(E39,Counter_Pricing[[Material_Name]:[Level]],5,0) -> Level 1 | K39: 100 | L39: =K39*(1+$L$6) -> 110 | M39: SF | N39: =INDEX(Counter_Pricing[Olsen_Cost],MATCH(F39,Counter_Pricing[Level])) -> 38 | O39: =L39*N39 -> 4180 | P39: =(L39/SUM($L$8:$L$136))*$V$5 -> 277.57217 | Q39: =O39-P39 -> 3902.4278 | R39: =IF(Q39>0,Q39/$R$6,Q39) -> 6003.7351
C40: Surface Type | D40: Surface Type | E40: Dallas White | F40: =VLOOKUP(E40,Counter_Pricing[[Material_Name]:[Level]],5,0) -> Level 1 | K40: 101 | L40: =K40*(1+$L$6) -> 111.1 | M40: SF | N40: =INDEX(Counter_Pricing[Olsen_Cost],MATCH(F40,Counter_Pricing[Level])) -> 38 | O40: =L40*N40 -> 4221.8 | P40: =(L40/SUM($L$8:$L$136))*$V$5 -> 280.34789 | Q40: =O40-P40 -> 3941.4521 | R40: =IF(Q40>0,Q40/$R$6,Q40) -> 6063.7725
O41: *HO Pays: | R41: =SUM(R27:R40) -> 45055.758
B42: Bathroom #2
B43: Countertop #1 | C43: Countertop Surface | D43: Surface Type | E43: Dallas White | F43: =VLOOKUP(E43,Counter_Pricing[[Material_Name]:[Level]],5,0) -> Level 1 | K43: 92 | L43: =K43*(1+$L$6) -> 101.2 | M43: SF | N43: =INDEX(Counter_Pricing[Olsen_Cost],MATCH(F43,Counter_Pricing[Level])) -> 38 | O43: =L43*N43 -> 3845.6 | P43: =(L43/SUM($L$8:$L$136))*$V$5 -> 255.3664 | Q43: =O43-P43 -> 3590.2336 | R43: =IF(Q43>0,Q43/$R$6,Q43) -> 5523.4363
B44: Countertop #1 | C44: Edge Type | D44: Eased Edge | E44: Eased Edge | F44: =VLOOKUP(E44,Counter_Pricing[[Material_Name]:[Level]],5,0) -> Labor | K44: 93 | L44: =K44*(1+$L$6) -> 102.3 | M44: LF | N44: =INDEX(Counter_Pricing[Olsen_Cost],MATCH(F44,Counter_Pricing[Level])) -> 0 | O44: =L44*N44 -> 0 | P44: =(L44/SUM($L$8:$L$136))*$V$5 -> 258.14212 | Q44: =O44-P44 -> -258.14212 | R44: =IF(Q44>0,Q44/$R$6,Q44) -> -258.14212
B45: Countertop #1 | C45: Cutout | D45: Sink (Undermount) | E45: Sink Cutout | F45: =VLOOKUP(E45,Counter_Pricing[[Material_Name]:[Level]],5,0) -> Labor | K45: 94 | L45: =K45*(1+$L$6) -> 103.4 | M45: SF | N45: =INDEX(Counter_Pricing[Olsen_Cost],MATCH(F45,Counter_Pricing[Level])) -> 0 | O45: =L45*N45 -> 0 | P45: =(L45/SUM($L$8:$L$136))*$V$5 -> 260.91784 | Q45: =O45-P45 -> -260.91784 | R45: =IF(Q45>0,Q45/$R$6,Q45) -> -260.91784
B46: Countertop #2 | C46: Countertop Surface | D46: Surface Type | E46: Dallas White | F46: =VLOOKUP(E46,Counter_Pricing[[Material_Name]:[Level]],5,0) -> Level 1 | K46: 95 | L46: =K46*(1+$L$6) -> 104.5 | M46: SF | N46: =INDEX(Counter_Pricing[Olsen_Cost],MATCH(F46,Counter_Pricing[Level])) -> 38 | O46: =L46*N46 -> 3971 | P46: =(L46/SUM($L$8:$L$136))*$V$5 -> 263.69356 | Q46: =O46-P46 -> 3707.3064 | R46: =IF(Q46>0,Q46/$R$6,Q46) -> 5703.5484
B47: Countertop #2 | C47: Edge Type | D47: Mitered Edge | E47: Mitered Edge | F47: =VLOOKUP(E47,Counter_Pricing[[Material_Name]:[Level]],5,0) -> Labor | K47: 96 | L47: =K47*(1+$L$6) -> 105.6 | M47: SF | N47: =INDEX(Counter_Pricing[Olsen_Cost],MATCH(F47,Counter_Pricing[Level])) -> 0 | O47: =L47*N47 -> 0 | P47: =(L47/SUM($L$8:$L$136))*$V$5 -> 266.46928 | Q47: =O47-P47 -> -266.46928 | R47: =IF(Q47>0,Q47/$R$6,Q47) -> -266.46928
B48: Countertop #2 | C48: Cutout | D48: Cooktop | E48: Sink Cutout | F48: =VLOOKUP(E48,Counter_Pricing[[Material_Name]:[Level]],5,0) -> Labor | K48: 97 | L48: =K48*(1+$L$6) -> 106.7 | M48: SF | N48: =INDEX(Counter_Pricing[Olsen_Cost],MATCH(F48,Counter_Pricing[Level])) -> 0 | O48: =L48*N48 -> 0 | P48: =(L48/SUM($L$8:$L$136))*$V$5 -> 269.245 | Q48: =O48-P48 -> -269.245 | R48: =IF(Q48>0,Q48/$R$6,Q48) -> -269.245
B49: Countertop #2 | C49: Cutout | D49: Sink (Undermount) | E49: Sink Cutout | F49: =VLOOKUP(E49,Counter_Pricing[[Material_Name]:[Level]],5,0) -> Labor | K49: 98 | L49: =K49*(1+$L$6) -> 107.8 | M49: SF | N49: =INDEX(Counter_Pricing[Olsen_Cost],MATCH(F49,Counter_Pricing[Level])) -> 0 | O49: =L49*N49 -> 0 | P49: =(L49/SUM($L$8:$L$136))*$V$5 -> 272.02073 | Q49: =O49-P49 -> -272.02073 | R49: =IF(Q49>0,Q49/$R$6,Q49) -> -272.02073
B50: Island Countertop | C50: Countertop Surface | D50: Surface Type | E50: Dallas White | F50: =VLOOKUP(E50,Counter_Pricing[[Material_Name]:[Level]],5,0) -> Level 1 | K50: 95 | L50: =K50*(1+$L$6) -> 104.5 | M50: SF | N50: =INDEX(Counter_Pricing[Olsen_Cost],MATCH(F50,Counter_Pricing[Level])) -> 38 | O50: =L50*N50 -> 3971 | P50: =(L50/SUM($L$8:$L$136))*$V$5 -> 263.69356 | Q50: =O50-P50 -> 3707.3064 | R50: =IF(Q50>0,Q50/$R$6,Q50) -> 5703.5484
B51: Island Countertop | C51: Edge Type | D51: Eased Edge | E51: Eased Edge | F51: =VLOOKUP(E51,Counter_Pricing[[Material_Name]:[Level]],5,0) -> Labor | K51: 96 | L51: =K51*(1+$L$6) -> 105.6 | M51: SF | N51: =INDEX(Counter_Pricing[Olsen_Cost],MATCH(F51,Counter_Pricing[Level])) -> 0 | O51: =L51*N51 -> 0 | P51: =(L51/SUM($L$8:$L$136))*$V$5 -> 266.46928 | Q51: =O51-P51 -> -266.46928 | R51: =IF(Q51>0,Q51/$R$6,Q51) -> -266.46928
B52: Island Countertop | C52: Waterfall Surface | D52: Surface Type | E52: Dallas White | F52: =VLOOKUP(E52,Counter_Pricing[[Material_Name]:[Level]],5,0) -> Level 1 | H52: Left Waterfall | K52: 97 | L52: =K52*(1+$L$6) -> 106.7 | M52: SF | N52: =INDEX(Counter_Pricing[Olsen_Cost],MATCH(F52,Counter_Pricing[Level])) -> 38 | O52: =L52*N52 -> 4054.6 | P52: =(L52/SUM($L$8:$L$136))*$V$5 -> 269.245 | Q52: =O52-P52 -> 3785.355 | R52: =IF(Q52>0,Q52/$R$6,Q52) -> 5823.6231
B53: Island Countertop | C53: Surface Type | D53: Surface Type | E53: Dallas White | F53: =VLOOKUP(E53,Counter_Pricing[[Material_Name]:[Level]],5,0) -> Level 1 | K53: 98 | L53: =K53*(1+$L$6) -> 107.8 | M53: SF | N53: =INDEX(Counter_Pricing[Olsen_Cost],MATCH(F53,Counter_Pricing[Level])) -> 38 | O53: =L53*N53 -> 4096.4 | P53: =(L53/SUM($L$8:$L$136))*$V$5 -> 272.02073 | Q53: =O53-P53 -> 3824.3793 | R53: =IF(Q53>0,Q53/$R$6,Q53) -> 5883.6604
B54: Countertop | C54: Surface Type | D54: Surface Type | E54: Dallas White | F54: =VLOOKUP(E54,Counter_Pricing[[Material_Name]:[Level]],5,0) -> Level 1 | K54: 99 | L54: =K54*(1+$L$6) -> 108.9 | M54: SF | N54: =INDEX(Counter_Pricing[Olsen_Cost],MATCH(F54,Counter_Pricing[Level])) -> 38 | O54: =L54*N54 -> 4138.2 | P54: =(L54/SUM($L$8:$L$136))*$V$5 -> 274.79645 | Q54: =O54-P54 -> 3863.4036 | R54: =IF(Q54>0,Q54/$R$6,Q54) -> 5943.6978
B55: Countertop | C55: Surface Type | D55: Surface Type | E55: Dallas White | F55: =VLOOKUP(E55,Counter_Pricing[[Material_Name]:[Level]],5,0) -> Level 1 | K55: 100 | L55: =K55*(1+$L$6) -> 110 | M55: SF | N55: =INDEX(Counter_Pricing[Olsen_Cost],MATCH(F55,Counter_Pricing[Level])) -> 38 | O55: =L55*N55 -> 4180 | P55: =(L55/SUM($L$8:$L$136))*$V$5 -> 277.57217 | Q55: =O55-P55 -> 3902.4278 | R55: =IF(Q55>0,Q55/$R$6,Q55) -> 6003.7351
B56: Countertop | C56: Surface Type | D56: Surface Type | E56: Dallas White | F56: =VLOOKUP(E56,Counter_Pricing[[Material_Name]:[Level]],5,0) -> Level 1 | K56: 101 | L56: =K56*(1+$L$6) -> 111.1 | M56: SF | N56: =INDEX(Counter_Pricing[Olsen_Cost],MATCH(F56,Counter_Pricing[Level])) -> 38 | O56: =L56*N56 -> 4221.8 | P56: =(L56/SUM($L$8:$L$136))*$V$5 -> 280.34789 | Q56: =O56-P56 -> 3941.4521 | R56: =IF(Q56>0,Q56/$R$6,Q56) -> 6063.7725
O57: *HO Pays: | R57: =SUM(R43:R56) -> 45055.758
B58: Bathroom #3
B59: Countertop #1 | C59: Countertop Surface | D59: Surface Type | E59: Dallas White | F59: =VLOOKUP(E59,Counter_Pricing[[Material_Name]:[Level]],5,0) -> Level 1 | K59: 92 | L59: =K59*(1+$L$6) -> 101.2 | M59: SF | N59: =INDEX(Counter_Pricing[Olsen_Cost],MATCH(F59,Counter_Pricing[Level])) -> 38 | O59: =L59*N59 -> 3845.6 | P59: =(L59/SUM($L$8:$L$136))*$V$5 -> 255.3664 | Q59: =O59-P59 -> 3590.2336 | R59: =IF(Q59>0,Q59/$R$6,Q59) -> 5523.4363
B60: Countertop #1 | C60: Edge Type | D60: Eased Edge | E60: Eased Edge | F60: =VLOOKUP(E60,Counter_Pricing[[Material_Name]:[Level]],5,0) -> Labor | K60: 93 | L60: =K60*(1+$L$6) -> 102.3 | M60: LF | N60: =INDEX(Counter_Pricing[Olsen_Cost],MATCH(F60,Counter_Pricing[Level])) -> 0 | O60: =L60*N60 -> 0 | P60: =(L60/SUM($L$8:$L$136))*$V$5 -> 258.14212 | Q60: =O60-P60 -> -258.14212 | R60: =IF(Q60>0,Q60/$R$6,Q60) -> -258.14212
B61: Countertop #1 | C61: Cutout | D61: Sink (Undermount) | E61: Sink Cutout | F61: =VLOOKUP(E61,Counter_Pricing[[Material_Name]:[Level]],5,0) -> Labor | K61: 94 | L61: =K61*(1+$L$6) -> 103.4 | M61: SF | N61: =INDEX(Counter_Pricing[Olsen_Cost],MATCH(F61,Counter_Pricing[Level])) -> 0 | O61: =L61*N61 -> 0 | P61: =(L61/SUM($L$8:$L$136))*$V$5 -> 260.91784 | Q61: =O61-P61 -> -260.91784 | R61: =IF(Q61>0,Q61/$R$6,Q61) -> -260.91784
B62: Countertop #2 | C62: Countertop Surface | D62: Surface Type | E62: Dallas White | F62: =VLOOKUP(E62,Counter_Pricing[[Material_Name]:[Level]],5,0) -> Level 1 | K62: 95 | L62: =K62*(1+$L$6) -> 104.5 | M62: SF | N62: =INDEX(Counter_Pricing[Olsen_Cost],MATCH(F62,Counter_Pricing[Level])) -> 38 | O62: =L62*N62 -> 3971 | P62: =(L62/SUM($L$8:$L$136))*$V$5 -> 263.69356 | Q62: =O62-P62 -> 3707.3064 | R62: =IF(Q62>0,Q62/$R$6,Q62) -> 5703.5484
B63: Countertop #2 | C63: Edge Type | D63: Mitered Edge | E63: Mitered Edge | F63: =VLOOKUP(E63,Counter_Pricing[[Material_Name]:[Level]],5,0) -> Labor | K63: 96 | L63: =K63*(1+$L$6) -> 105.6 | M63: SF | N63: =INDEX(Counter_Pricing[Olsen_Cost],MATCH(F63,Counter_Pricing[Level])) -> 0 | O63: =L63*N63 -> 0 | P63: =(L63/SUM($L$8:$L$136))*$V$5 -> 266.46928 | Q63: =O63-P63 -> -266.46928 | R63: =IF(Q63>0,Q63/$R$6,Q63) -> -266.46928
B64: Countertop #2 | C64: Cutout | D64: Cooktop | E64: Sink Cutout | F64: =VLOOKUP(E64,Counter_Pricing[[Material_Name]:[Level]],5,0) -> Labor | K64: 97 | L64: =K64*(1+$L$6) -> 106.7 | M64: SF | N64: =INDEX(Counter_Pricing[Olsen_Cost],MATCH(F64,Counter_Pricing[Level])) -> 0 | O64: =L64*N64 -> 0 | P64: =(L64/SUM($L$8:$L$136))*$V$5 -> 269.245 | Q64: =O64-P64 -> -269.245 | R64: =IF(Q64>0,Q64/$R$6,Q64) -> -269.245
B65: Countertop #2 | C65: Cutout | D65: Sink (Undermount) | E65: Sink Cutout | F65: =VLOOKUP(E65,Counter_Pricing[[Material_Name]:[Level]],5,0) -> Labor | K65: 98 | L65: =K65*(1+$L$6) -> 107.8 | M65: SF | N65: =INDEX(Counter_Pricing[Olsen_Cost],MATCH(F65,Counter_Pricing[Level])) -> 0 | O65: =L65*N65 -> 0 | P65: =(L65/SUM($L$8:$L$136))*$V$5 -> 272.02073 | Q65: =O65-P65 -> -272.02073 | R65: =IF(Q65>0,Q65/$R$6,Q65) -> -272.02073
B66: Island Countertop | C66: Countertop Surface | D66: Surface Type | E66: Dallas White | F66: =VLOOKUP(E66,Counter_Pricing[[Material_Name]:[Level]],5,0) -> Level 1 | K66: 95 | L66: =K66*(1+$L$6) -> 104.5 | M66: SF | N66: =INDEX(Counter_Pricing[Olsen_Cost],MATCH(F66,Counter_Pricing[Level])) -> 38 | O66: =L66*N66 -> 3971 | P66: =(L66/SUM($L$8:$L$136))*$V$5 -> 263.69356 | Q66: =O66-P66 -> 3707.3064 | R66: =IF(Q66>0,Q66/$R$6,Q66) -> 5703.5484
B67: Island Countertop | C67: Edge Type | D67: Eased Edge | E67: Eased Edge | F67: =VLOOKUP(E67,Counter_Pricing[[Material_Name]:[Level]],5,0) -> Labor | K67: 96 | L67: =K67*(1+$L$6) -> 105.6 | M67: SF | N67: =INDEX(Counter_Pricing[Olsen_Cost],MATCH(F67,Counter_Pricing[Level])) -> 0 | O67: =L67*N67 -> 0 | P67: =(L67/SUM($L$8:$L$136))*$V$5 -> 266.46928 | Q67: =O67-P67 -> -266.46928 | R67: =IF(Q67>0,Q67/$R$6,Q67) -> -266.46928
B68: Island Countertop | C68: Waterfall Surface | D68: Surface Type | E68: Dallas White | F68: =VLOOKUP(E68,Counter_Pricing[[Material_Name]:[Level]],5,0) -> Level 1 | H68: Left Waterfall | K68: 97 | L68: =K68*(1+$L$6) -> 106.7 | M68: SF | N68: =INDEX(Counter_Pricing[Olsen_Cost],MATCH(F68,Counter_Pricing[Level])) -> 38 | O68: =L68*N68 -> 4054.6 | P68: =(L68/SUM($L$8:$L$136))*$V$5 -> 269.245 | Q68: =O68-P68 -> 3785.355 | R68: =IF(Q68>0,Q68/$R$6,Q68) -> 5823.6231
B69: Island Countertop | C69: Surface Type | D69: Surface Type | E69: Dallas White | F69: =VLOOKUP(E69,Counter_Pricing[[Material_Name]:[Level]],5,0) -> Level 1 | K69: 98 | L69: =K69*(1+$L$6) -> 107.8 | M69: SF | N69: =INDEX(Counter_Pricing[Olsen_Cost],MATCH(F69,Counter_Pricing[Level])) -> 38 | O69: =L69*N69 -> 4096.4 | P69: =(L69/SUM($L$8:$L$136))*$V$5 -> 272.02073 | Q69: =O69-P69 -> 3824.3793 | R69: =IF(Q69>0,Q69/$R$6,Q69) -> 5883.6604
B70: Countertop | C70: Surface Type | D70: Surface Type | E70: Dallas White | F70: =VLOOKUP(E70,Counter_Pricing[[Material_Name]:[Level]],5,0) -> Level 1 | K70: 99 | L70: =K70*(1+$L$6) -> 108.9 | M70: SF | N70: =INDEX(Counter_Pricing[Olsen_Cost],MATCH(F70,Counter_Pricing[Level])) -> 38 | O70: =L70*N70 -> 4138.2 | P70: =(L70/SUM($L$8:$L$136))*$V$5 -> 274.79645 | Q70: =O70-P70 -> 3863.4036 | R70: =IF(Q70>0,Q70/$R$6,Q70) -> 5943.6978
B71: Countertop | C71: Surface Type | D71: Surface Type | E71: Dallas White | F71: =VLOOKUP(E71,Counter_Pricing[[Material_Name]:[Level]],5,0) -> Level 1 | K71: 100 | L71: =K71*(1+$L$6) -> 110 | M71: SF | N71: =INDEX(Counter_Pricing[Olsen_Cost],MATCH(F71,Counter_Pricing[Level])) -> 38 | O71: =L71*N71 -> 4180 | P71: =(L71/SUM($L$8:$L$136))*$V$5 -> 277.57217 | Q71: =O71-P71 -> 3902.4278 | R71: =IF(Q71>0,Q71/$R$6,Q71) -> 6003.7351
B72: Countertop | C72: Surface Type | D72: Surface Type | E72: Dallas White | F72: =VLOOKUP(E72,Counter_Pricing[[Material_Name]:[Level]],5,0) -> Level 1 | K72: 101 | L72: =K72*(1+$L$6) -> 111.1 | M72: SF | N72: =INDEX(Counter_Pricing[Olsen_Cost],MATCH(F72,Counter_Pricing[Level])) -> 38 | O72: =L72*N72 -> 4221.8 | P72: =(L72/SUM($L$8:$L$136))*$V$5 -> 280.34789 | Q72: =O72-P72 -> 3941.4521 | R72: =IF(Q72>0,Q72/$R$6,Q72) -> 6063.7725
O73: *HO Pays: | R73: =SUM(R59:R72) -> 45055.758
B74: Bathroom #4
B75: Countertop #1 | C75: Countertop Surface | D75: Surface Type | E75: Dallas White | F75: =VLOOKUP(E75,Counter_Pricing[[Material_Name]:[Level]],5,0) -> Level 1 | K75: 92 | L75: =K75*(1+$L$6) -> 101.2 | M75: SF | N75: =INDEX(Counter_Pricing[Olsen_Cost],MATCH(F75,Counter_Pricing[Level])) -> 38 | O75: =L75*N75 -> 3845.6 | P75: =(L75/SUM($L$8:$L$136))*$V$5 -> 255.3664 | Q75: =O75-P75 -> 3590.2336 | R75: =IF(Q75>0,Q75/$R$6,Q75) -> 5523.4363
B76: Countertop #1 | C76: Edge Type | D76: Eased Edge | E76: Eased Edge | F76: =VLOOKUP(E76,Counter_Pricing[[Material_Name]:[Level]],5,0) -> Labor | K76: 93 | L76: =K76*(1+$L$6) -> 102.3 | M76: LF | N76: =INDEX(Counter_Pricing[Olsen_Cost],MATCH(F76,Counter_Pricing[Level])) -> 0 | O76: =L76*N76 -> 0 | P76: =(L76/SUM($L$8:$L$136))*$V$5 -> 258.14212 | Q76: =O76-P76 -> -258.14212 | R76: =IF(Q76>0,Q76/$R$6,Q76) -> -258.14212
B77: Countertop #1 | C77: Cutout | D77: Sink (Undermount) | E77: Sink Cutout | F77: =VLOOKUP(E77,Counter_Pricing[[Material_Name]:[Level]],5,0) -> Labor | K77: 94 | L77: =K77*(1+$L$6) -> 103.4 | M77: SF | N77: =INDEX(Counter_Pricing[Olsen_Cost],MATCH(F77,Counter_Pricing[Level])) -> 0 | O77: =L77*N77 -> 0 | P77: =(L77/SUM($L$8:$L$136))*$V$5 -> 260.91784 | Q77: =O77-P77 -> -260.91784 | R77: =IF(Q77>0,Q77/$R$6,Q77) -> -260.91784
B78: Countertop #2 | C78: Countertop Surface | D78: Surface Type | E78: Dallas White | F78: =VLOOKUP(E78,Counter_Pricing[[Material_Name]:[Level]],5,0) -> Level 1 | K78: 95 | L78: =K78*(1+$L$6) -> 104.5 | M78: SF | N78: =INDEX(Counter_Pricing[Olsen_Cost],MATCH(F78,Counter_Pricing[Level])) -> 38 | O78: =L78*N78 -> 3971 | P78: =(L78/SUM($L$8:$L$136))*$V$5 -> 263.69356 | Q78: =O78-P78 -> 3707.3064 | R78: =IF(Q78>0,Q78/$R$6,Q78) -> 5703.5484
B79: Countertop #2 | C79: Edge Type | D79: Mitered Edge | E79: Mitered Edge | F79: =VLOOKUP(E79,Counter_Pricing[[Material_Name]:[Level]],5,0) -> Labor | K79: 96 | L79: =K79*(1+$L$6) -> 105.6 | M79: SF | N79: =INDEX(Counter_Pricing[Olsen_Cost],MATCH(F79,Counter_Pricing[Level])) -> 0 | O79: =L79*N79 -> 0 | P79: =(L79/SUM($L$8:$L$136))*$V$5 -> 266.46928 | Q79: =O79-P79 -> -266.46928 | R79: =IF(Q79>0,Q79/$R$6,Q79) -> -266.46928
B80: Countertop #2 | C80: Cutout | D80: Cooktop | E80: Sink Cutout | F80: =VLOOKUP(E80,Counter_Pricing[[Material_Name]:[Level]],5,0) -> Labor | K80: 97 | L80: =K80*(1+$L$6) -> 106.7 | M80: SF | N80: =INDEX(Counter_Pricing[Olsen_Cost],MATCH(F80,Counter_Pricing[Level])) -> 0 | O80: =L80*N80 -> 0 | P80: =(L80/SUM($L$8:$L$136))*$V$5 -> 269.245 | Q80: =O80-P80 -> -269.245 | R80: =IF(Q80>0,Q80/$R$6,Q80) -> -269.245
B81: Countertop #2 | C81: Cutout | D81: Sink (Undermount) | E81: Sink Cutout | F81: =VLOOKUP(E81,Counter_Pricing[[Material_Name]:[Level]],5,0) -> Labor | K81: 98 | L81: =K81*(1+$L$6) -> 107.8 | M81: SF | N81: =INDEX(Counter_Pricing[Olsen_Cost],MATCH(F81,Counter_Pricing[Level])) -> 0 | O81: =L81*N81 -> 0 | P81: =(L81/SUM($L$8:$L$136))*$V$5 -> 272.02073 | Q81: =O81-P81 -> -272.02073 | R81: =IF(Q81>0,Q81/$R$6,Q81) -> -272.02073
B82: Island Countertop | C82: Countertop Surface | D82: Surface Type | E82: Dallas White | F82: =VLOOKUP(E82,Counter_Pricing[[Material_Name]:[Level]],5,0) -> Level 1 | K82: 95 | L82: =K82*(1+$L$6) -> 104.5 | M82: SF | N82: =INDEX(Counter_Pricing[Olsen_Cost],MATCH(F82,Counter_Pricing[Level])) -> 38 | O82: =L82*N82 -> 3971 | P82: =(L82/SUM($L$8:$L$136))*$V$5 -> 263.69356 | Q82: =O82-P82 -> 3707.3064 | R82: =IF(Q82>0,Q82/$R$6,Q82) -> 5703.5484
B83: Island Countertop | C83: Edge Type | D83: Eased Edge | E83: Eased Edge | F83: =VLOOKUP(E83,Counter_Pricing[[Material_Name]:[Level]],5,0) -> Labor | K83: 96 | L83: =K83*(1+$L$6) -> 105.6 | M83: SF | N83: =INDEX(Counter_Pricing[Olsen_Cost],MATCH(F83,Counter_Pricing[Level])) -> 0 | O83: =L83*N83 -> 0 | P83: =(L83/SUM($L$8:$L$136))*$V$5 -> 266.46928 | Q83: =O83-P83 -> -266.46928 | R83: =IF(Q83>0,Q83/$R$6,Q83) -> -266.46928
B84: Island Countertop | C84: Waterfall Surface | D84: Surface Type | E84: Dallas White | F84: =VLOOKUP(E84,Counter_Pricing[[Material_Name]:[Level]],5,0) -> Level 1 | K84: 97 | L84: =K84*(1+$L$6) -> 106.7 | M84: SF | N84: =INDEX(Counter_Pricing[Olsen_Cost],MATCH(F84,Counter_Pricing[Level])) -> 38 | O84: =L84*N84 -> 4054.6 | P84: =(L84/SUM($L$8:$L$136))*$V$5 -> 269.245 | Q84: =O84-P84 -> 3785.355 | R84: =IF(Q84>0,Q84/$R$6,Q84) -> 5823.6231
B85: Island Countertop | C85: Surface Type | D85: Surface Type | E85: Dallas White | F85: =VLOOKUP(E85,Counter_Pricing[[Material_Name]:[Level]],5,0) -> Level 1 | K85: 98 | L85: =K85*(1+$L$6) -> 107.8 | M85: SF | N85: =INDEX(Counter_Pricing[Olsen_Cost],MATCH(F85,Counter_Pricing[Level])) -> 38 | O85: =L85*N85 -> 4096.4 | P85: =(L85/SUM($L$8:$L$136))*$V$5 -> 272.02073 | Q85: =O85-P85 -> 3824.3793 | R85: =IF(Q85>0,Q85/$R$6,Q85) -> 5883.6604
B86: Countertop | C86: Surface Type | D86: Surface Type | E86: Dallas White | F86: =VLOOKUP(E86,Counter_Pricing[[Material_Name]:[Level]],5,0) -> Level 1 | K86: 99 | L86: =K86*(1+$L$6) -> 108.9 | M86: SF | N86: =INDEX(Counter_Pricing[Olsen_Cost],MATCH(F86,Counter_Pricing[Level])) -> 38 | O86: =L86*N86 -> 4138.2 | P86: =(L86/SUM($L$8:$L$136))*$V$5 -> 274.79645 | Q86: =O86-P86 -> 3863.4036 | R86: =IF(Q86>0,Q86/$R$6,Q86) -> 5943.6978
... B88: Countertop | C88: Surface Type | D88: Surface Type | E88: Dallas White | F88: =VLOOKUP(E88,Counter_Pricing[[Material_Name]:[Level]],5,0) -> Level 1 | K88: 101 | L88: =K88*(1+$L$6) -> 111.1 | M88: SF | N88: =INDEX(Counter_Pricing[Olsen_Cost],MATCH(F88,Counter_Pricing[Level])) -> 38 | O88: =L88*N88 -> 4221.8 | P88: =(L88/SUM($L$8:$L$136))*$V$5 -> 280.34789 | Q88: =O88-P88 -> 3941.4521 | R88: =IF(Q88>0,Q88/$R$6,Q88) -> 6063.7725
O89: *HO Pays: | R89: =SUM(R75:R88) -> 45055.758
B90: Pantry
B91: Countertop #1 | C91: Countertop Surface | D91: Surface Type | E91: Mitered Edge | F91: =VLOOKUP(E91,Counter_Pricing[[Material_Name]:[Level]],5,0) -> Labor | K91: 92 | L91: =K91*(1+$L$6) -> 101.2 | M91: SF | N91: =INDEX(Counter_Pricing[Olsen_Cost],MATCH(F91,Counter_Pricing[Level])) -> 0 | O91: =L91*N91 -> 0 | P91: =(L91/SUM($L$8:$L$136))*$V$5 -> 255.3664 | Q91: =O91-P91 -> -255.3664 | R91: =IF(Q91>0,Q91/$R$6,Q91) -> -255.3664
F92: =VLOOKUP(E92,Counter_Pricing[[Material_Name]:[Level]],5,0) -> #N/A | K92: 93 | L92: =K92*(1+$L$6) -> 102.3 | M92: LF | N92: =INDEX(Counter_Pricing[Olsen_Cost],MATCH(F92,Counter_Pricing[Level])) -> #N/A | O92: =L92*N92 -> #N/A | P92: =(L92/SUM($L$8:$L$136))*$V$5 -> 258.14212 | Q92: =O92-P92 -> #N/A | R92: =IF(Q92>0,Q92/$R$6,Q92) -> #N/A
F93: =VLOOKUP(E93,Counter_Pricing[[Material_Name]:[Level]],5,0) -> #N/A | K93: 94 | L93: =K93*(1+$L$6) -> 103.4 | M93: SF | N93: =INDEX(Counter_Pricing[Olsen_Cost],MATCH(F93,Counter_Pricing[Level])) -> #N/A | O93: =L93*N93 -> #N/A | P93: =(L93/SUM($L$8:$L$136))*$V$5 -> 260.91784 | Q93: =O93-P93 -> #N/A | R93: =IF(Q93>0,Q93/$R$6,Q93) -> #N/A
F94: =VLOOKUP(E94,Counter_Pricing[[Material_Name]:[Level]],5,0) -> #N/A | K94: 95 | L94: =K94*(1+$L$6) -> 104.5 | M94: SF | N94: =INDEX(Counter_Pricing[Olsen_Cost],MATCH(F94,Counter_Pricing[Level])) -> #N/A | O94: =L94*N94 -> #N/A | P94: =(L94/SUM($L$8:$L$136))*$V$5 -> 263.69356 | Q94: =O94-P94 -> #N/A | R94: =IF(Q94>0,Q94/$R$6,Q94) -> #N/A
F95: =VLOOKUP(E95,Counter_Pricing[[Material_Name]:[Level]],5,0) -> #N/A | K95: 96 | L95: =K95*(1+$L$6) -> 105.6 | M95: SF | N95: =INDEX(Counter_Pricing[Olsen_Cost],MATCH(F95,Counter_Pricing[Level])) -> #N/A | O95: =L95*N95 -> #N/A | P95: =(L95/SUM($L$8:$L$136))*$V$5 -> 266.46928 | Q95: =O95-P95 -> #N/A | R95: =IF(Q95>0,Q95/$R$6,Q95) -> #N/A
F96: =VLOOKUP(E96,Counter_Pricing[[Material_Name]:[Level]],5,0) -> #N/A | K96: 97 | L96: =K96*(1+$L$6) -> 106.7 | M96: SF | N96: =INDEX(Counter_Pricing[Olsen_Cost],MATCH(F96,Counter_Pricing[Level])) -> #N/A | O96: =L96*N96 -> #N/A | P96: =(L96/SUM($L$8:$L$136))*$V$5 -> 269.245 | Q96: =O96-P96 -> #N/A | R96: =IF(Q96>0,Q96/$R$6,Q96) -> #N/A
F97: =VLOOKUP(E97,Counter_Pricing[[Material_Name]:[Level]],5,0) -> #N/A | K97: 98 | L97: =K97*(1+$L$6) -> 107.8 | M97: SF | N97: =INDEX(Counter_Pricing[Olsen_Cost],MATCH(F97,Counter_Pricing[Level])) -> #N/A | O97: =L97*N97 -> #N/A | P97: =(L97/SUM($L$8:$L$136))*$V$5 -> 272.02073 | Q97: =O97-P97 -> #N/A | R97: =IF(Q97>0,Q97/$R$6,Q97) -> #N/A
F98: =VLOOKUP(E98,Counter_Pricing[[Material_Name]:[Level]],5,0) -> #N/A | K98: 95 | L98: =K98*(1+$L$6) -> 104.5 | M98: SF | N98: =INDEX(Counter_Pricing[Olsen_Cost],MATCH(F98,Counter_Pricing[Level])) -> #N/A | O98: =L98*N98 -> #N/A | P98: =(L98/SUM($L$8:$L$136))*$V$5 -> 263.69356 | Q98: =O98-P98 -> #N/A | R98: =IF(Q98>0,Q98/$R$6,Q98) -> #N/A
F99: =VLOOKUP(E99,Counter_Pricing[[Material_Name]:[Level]],5,0) -> #N/A | K99: 96 | L99: =K99*(1+$L$6) -> 105.6 | M99: SF | N99: =INDEX(Counter_Pricing[Olsen_Cost],MATCH(F99,Counter_Pricing[Level])) -> #N/A | O99: =L99*N99 -> #N/A | P99: =(L99/SUM($L$8:$L$136))*$V$5 -> 266.46928 | Q99: =O99-P99 -> #N/A | R99: =IF(Q99>0,Q99/$R$6,Q99) -> #N/A
F100: =VLOOKUP(E100,Counter_Pricing[[Material_Name]:[Level]],5,0) -> #N/A | K100: 97 | L100: =K100*(1+$L$6) -> 106.7 | M100: SF | N100: =INDEX(Counter_Pricing[Olsen_Cost],MATCH(F100,Counter_Pricing[Level])) -> #N/A | O100: =L100*N100 -> #N/A | P100: =(L100/SUM($L$8:$L$136))*$V$5 -> 269.245 | Q100: =O100-P100 -> #N/A | R100: =IF(Q100>0,Q100/$R$6,Q100) -> #N/A
F101: =VLOOKUP(E101,Counter_Pricing[[Material_Name]:[Level]],5,0) -> #N/A | K101: 98 | L101: =K101*(1+$L$6) -> 107.8 | M101: SF | N101: =INDEX(Counter_Pricing[Olsen_Cost],MATCH(F101,Counter_Pricing[Level])) -> #N/A | O101: =L101*N101 -> #N/A | P101: =(L101/SUM($L$8:$L$136))*$V$5 -> 272.02073 | Q101: =O101-P101 -> #N/A | R101: =IF(Q101>0,Q101/$R$6,Q101) -> #N/A
F102: =VLOOKUP(E102,Counter_Pricing[[Material_Name]:[Level]],5,0) -> #N/A | K102: 99 | L102: =K102*(1+$L$6) -> 108.9 | M102: SF | N102: =INDEX(Counter_Pricing[Olsen_Cost],MATCH(F102,Counter_Pricing[Level])) -> #N/A | O102: =L102*N102 -> #N/A | P102: =(L102/SUM($L$8:$L$136))*$V$5 -> 274.79645 | Q102: =O102-P102 -> #N/A | R102: =IF(Q102>0,Q102/$R$6,Q102) -> #N/A
...

Sheet Tile-Floor
B2: Tile Quick Pricing Sheet | L2: ='Customer Option Cover Page'!C6 -> John Doe
B3: =U18 -> *All pricing displayed on this page is subject to change at the sole discression of Olsen Custom Homes. Pricing will be finalized via a customer option form.* | L3: ='Customer Option Cover Page'!C7 -> 123 avenue
B4: Designer Information | L4: Estimator | U4: Summary | X4: Instructions
B5: Area/Room | C5: Type | D5: Level | E5: Product Name | F5: Notes | G5: Finish | H5: Pattern | I5: Direction | J5: Grout | K5: Joint | L5: Qty_Est | M5: Qty_Pad | N5: Units | O5: $ / Unit | P5: Olsen Total | Q5: Included | R5: Difference | S5: Charge HO | U5: Allowance Total: | V5: 30000 | X5: **Please read this and follow the process EXACTLY**
M6: 0.1 | S6: 0.65 | X6: Instructions for ESTIMATOR
B7: Main Flooring Selections | U7: Area | V7: Charge to HO | X7: Instructions for ESTIMATOR (BEFORE-HO meeting)
B8: Foyer | C8: Floor Tile | D8: Level 4 | E8: Dublin- 13"x13" Straight (no offset) | L8: 1680.7 | M8: =L8*(1+$M$6) -> 1848.77 | N8: SF | O8: =IF(AND($C8<>"",$D8<>"",$E8<>""),IF(COUNTIFS(TileTable[Section],$C8,TileTable[Level],$D8,TileTable[Item_Name],$E8)>0,SUMIFS(TileTable[Olsen_Cost],TileTable[Section],$C8,TileTable[Level],$D8,TileTable[Item_Name],$E8),""),"0") -> 7 | P8: =O8*M8 -> 12941.39 | Q8: =(M8/SUM($M$8:$M$30,$M$32:$M$43,$M$45:$M$56,$M$58:$M$69,$M$71:$M$82,$M$84:$M$95,$M$97:$M$108,$M$110:$M$121,$M$123:$M$134))*$V$5 -> 29773.641 | R8: =P8-Q8 -> -16832.251 | S8: =IF(R8>0,R8/$S$6,R8) -> -16832.251 | U8: =B7 -> Main Flooring Selections | V8: =S30 -> -16849.352 | X8: Step #1: Input correct allowance total in cell V5
B9: Family Room | C9: Listel | D9: Level 2 | E9: Autumn Mist Random Linear Glass Mosaic - 4x12" listel - (1/3 sheet) | M9: =L9*(1+$M$6) -> 0 | N9: SF | O9: =IF(AND($C9<>"",$D9<>"",$E9<>""),IF(COUNTIFS(TileTable[Section],$C9,TileTable[Level],$D9,TileTable[Item_Name],$E9)>0,SUMIFS(TileTable[Olsen_Cost],TileTable[Section],$C9,TileTable[Level],$D9,TileTable[Item_Name],$E9),""),"0") -> 10.47 | P9: =O9*M9 -> 0 | Q9: =(M9/SUM($M$8:$M$30,$M$32:$M$43,$M$45:$M$56,$M$58:$M$69,$M$71:$M$82,$M$84:$M$95,$M$97:$M$108,$M$110:$M$121,$M$123:$M$134))*$V$5 -> 0 | R9: =P9-Q9 -> 0 | S9: =IF(R9>0,R9/$S$6,R9) -> 0 | U9: =B31 -> Master Bathroom | V9: =S43 -> -49.208401 | X9: Step #2: Assign all Rooms in BLACK Rows (7, 31,44, 57,70,83,96,109,122)
B10: Kitchen/Nook | C10: Carpet | D10: Level 1 | M10: =L10*(1+$M$6) -> 0 | N10: SF | O10: =IF(AND($C10<>"",$D10<>"",$E10<>""),IF(COUNTIFS(TileTable[Section],$C10,TileTable[Level],$D10,TileTable[Item_Name],$E10)>0,SUMIFS(TileTable[Olsen_Cost],TileTable[Section],$C10,TileTable[Level],$D10,TileTable[Item_Name],$E10),""),"0") -> 0 | P10: =O10*M10 -> 0 | Q10: =(M10/SUM($M$8:$M$30,$M$32:$M$43,$M$45:$M$56,$M$58:$M$69,$M$71:$M$82,$M$84:$M$95,$M$97:$M$108,$M$110:$M$121,$M$123:$M$134))*$V$5 -> 0 | R10: =P10-Q10 -> 0 | S10: =IF(R10>0,R10/$S$6,R10) -> 0 | U10: =B44 -> Bathroom #2 | V10: =S56 -> 0 | X10: Step #3: Assign all areas receiving tile Column B
B11: Pantry | C11: Shower / Tub Wall Tile | M11: =L11*(1+$M$6) -> 0 | N11: SF | O11: =IF(AND($C11<>"",$D11<>"",$E11<>""),IF(COUNTIFS(TileTable[Section],$C11,TileTable[Level],$D11,TileTable[Item_Name],$E11)>0,SUMIFS(TileTable[Olsen_Cost],TileTable[Section],$C11,TileTable[Level],$D11,TileTable[Item_Name],$E11),""),"0") -> 0 | P11: =O11*M11 -> 0 | Q11: =(M11/SUM($M$8:$M$30,$M$32:$M$43,$M$45:$M$56,$M$58:$M$69,$M$71:$M$82,$M$84:$M$95,$M$97:$M$108,$M$110:$M$121,$M$123:$M$134))*$V$5 -> 0 | R11: =P11-Q11 -> 0 | S11: =IF(R11>0,R11/$S$6,R11) -> 0 | U11: =B57 -> Bathroom #3 | V11: =S69 -> 0 | X11: Step #4: Input each square footage estimate in Column L
B12: Laundry Room | C12: Wood | D12: Level 1 | E12: Essence | L12: 10 | M12: =L12*(1+$M$6) -> 11 | N12: SF | O12: =IF(AND($C12<>"",$D12<>"",$E12<>""),IF(COUNTIFS(TileTable[Section],$C12,TileTable[Level],$D12,TileTable[Item_Name],$E12)>0,SUMIFS(TileTable[Olsen_Cost],TileTable[Section],$C12,TileTable[Level],$D12,TileTable[Item_Name],$E12),""),"0") -> 14.55 | P12: =O12*M12 -> 160.05 | Q12: =(M12/SUM($M$8:$M$30,$M$32:$M$43,$M$45:$M$56,$M$58:$M$69,$M$71:$M$82,$M$84:$M$95,$M$97:$M$108,$M$110:$M$121,$M$123:$M$134))*$V$5 -> 177.15024 | R12: =P12-Q12 -> -17.100243 | S12: =IF(R12>0,R12/$S$6,R12) -> -17.100243 | U12: =B70 -> Bathroom #4 | V12: =S82 -> 0 | X12: Step #5: Hide Columns L, Q, and R (highlighted in red)
B13: Hallways | C13: Floor Tile | M13: =L13*(1+$M$6) -> 0 | N13: SF | O13: =IF(AND($C13<>"",$D13<>"",$E13<>""),IF(COUNTIFS(TileTable[Section],$C13,TileTable[Level],$D13,TileTable[Item_Name],$E13)>0,SUMIFS(TileTable[Olsen_Cost],TileTable[Section],$C13,TileTable[Level],$D13,TileTable[Item_Name],$E13),""),"0") -> 0 | P13: =O13*M13 -> 0 | Q13: =(M13/SUM($M$8:$M$30,$M$32:$M$43,$M$45:$M$56,$M$58:$M$69,$M$71:$M$82,$M$84:$M$95,$M$97:$M$108,$M$110:$M$121,$M$123:$M$134))*$V$5 -> 0 | R13: =P13-Q13 -> 0 | S13: =IF(R13>0,R13/$S$6,R13) -> 0 | U13: =B83 -> Bathroom #5 | V13: =S95 -> 0 | X13: Step #6: Verify Pricing is correct at bottom of sheet
B14: Master Suite | C14: Floor Tile | M14: =L14*(1+$M$6) -> 0 | N14: SF | O14: =IF(AND($C14<>"",$D14<>"",$E14<>""),IF(COUNTIFS(TileTable[Section],$C14,TileTable[Level],$D14,TileTable[Item_Name],$E14)>0,SUMIFS(TileTable[Olsen_Cost],TileTable[Section],$C14,TileTable[Level],$D14,TileTable[Item_Name],$E14),""),"0") -> 0 | P14: =O14*M14 -> 0 | Q14: =(M14/SUM($M$8:$M$30,$M$32:$M$43,$M$45:$M$56,$M$58:$M$69,$M$71:$M$82,$M$84:$M$95,$M$97:$M$108,$M$110:$M$121,$M$123:$M$134))*$V$5 -> 0 | R14: =P14-Q14 -> 0 | S14: =IF(R14>0,R14/$S$6,R14) -> 0 | U14: =B96 -> Bathroom #6 | V14: =S108 -> 0 | X14: Instructions for DESIGNER (BEFORE HO Meeting)
B15: Master Closet | C15: Floor Tile | M15: =L15*(1+$M$6) -> 0 | N15: SF | O15: =IF(AND($C15<>"",$D15<>"",$E15<>""),IF(COUNTIFS(TileTable[Section],$C15,TileTable[Level],$D15,TileTable[Item_Name],$E15)>0,SUMIFS(TileTable[Olsen_Cost],TileTable[Section],$C15,TileTable[Level],$D15,TileTable[Item_Name],$E15),""),"0") -> 0 | P15: =O15*M15 -> 0 | Q15: =(M15/SUM($M$8:$M$30,$M$32:$M$43,$M$45:$M$56,$M$58:$M$69,$M$71:$M$82,$M$84:$M$95,$M$97:$M$108,$M$110:$M$121,$M$123:$M$134))*$V$5 -> 0 | R15: =P15-Q15 -> 0 | S15: =IF(R15>0,R15/$S$6,R15) -> 0 | U15: =B109 -> Backsplash | V15: =S121 -> 0 | X15: Step #1: Input any selections from BT if client has already made them
B16: Master Bathroom | C16: Floor Tile | M16: =L16*(1+$M$6) -> 0 | N16: SF | O16: =IF(AND($C16<>"",$D16<>"",$E16<>""),IF(COUNTIFS(TileTable[Section],$C16,TileTable[Level],$D16,TileTable[Item_Name],$E16)>0,SUMIFS(TileTable[Olsen_Cost],TileTable[Section],$C16,TileTable[Level],$D16,TileTable[Item_Name],$E16),""),"0") -> 0 | P16: =O16*M16 -> 0 | Q16: =(M16/SUM($M$8:$M$30,$M$32:$M$43,$M$45:$M$56,$M$58:$M$69,$M$71:$M$82,$M$84:$M$95,$M$97:$M$108,$M$110:$M$121,$M$123:$M$134))*$V$5 -> 0 | R16: =P16-Q16 -> 0 | S16: =IF(R16>0,R16/$S$6,R16) -> 0 | U16: =B122 -> Fireplace | V16: =S134 -> 0 | X16: Step #2: Verify Estimator has input ALL area information in Column L
B17: Bedroom #2 | C17: Floor Tile | M17: =L17*(1+$M$6) -> 0 | N17: SF | O17: =IF(AND($C17<>"",$D17<>"",$E17<>""),IF(COUNTIFS(TileTable[Section],$C17,TileTable[Level],$D17,TileTable[Item_Name],$E17)>0,SUMIFS(TileTable[Olsen_Cost],TileTable[Section],$C17,TileTable[Level],$D17,TileTable[Item_Name],$E17),""),"0") -> 0 | P17: =O17*M17 -> 0 | Q17: =(M17/SUM($M$8:$M$30,$M$32:$M$43,$M$45:$M$56,$M$58:$M$69,$M$71:$M$82,$M$84:$M$95,$M$97:$M$108,$M$110:$M$121,$M$123:$M$134))*$V$5 -> 0 | R17: =P17-Q17 -> 0 | S17: =IF(R17>0,R17/$S$6,R17) -> 0 | U17: Total Charge to HO: | V17: =SUM(V8:V16) -> -16898.56
B18: Bedroom #3 | C18: Floor Tile | M18: =L18*(1+$M$6) -> 0 | N18: SF | O18: =IF(AND($C18<>"",$D18<>"",$E18<>""),IF(COUNTIFS(TileTable[Section],$C18,TileTable[Level],$D18,TileTable[Item_Name],$E18)>0,SUMIFS(TileTable[Olsen_Cost],TileTable[Section],$C18,TileTable[Level],$D18,TileTable[Item_Name],$E18),""),"0") -> 0 | P18: =O18*M18 -> 0 | Q18: =(M18/SUM($M$8:$M$30,$M$32:$M$43,$M$45:$M$56,$M$58:$M$69,$M$71:$M$82,$M$84:$M$95,$M$97:$M$108,$M$110:$M$121,$M$123:$M$134))*$V$5 -> 0 | R18: =P18-Q18 -> 0 | S18: =IF(R18>0,R18/$S$6,R18) -> 0 | U18: *All pricing displayed on this page is subject to change at the sole discression of Olsen Custom Homes. Pricing will be finalized via a customer option form.* | X18: Instructions for DESIGNER (During HO Meeting)
B19: Bedroom #4 | C19: Floor Tile | M19: =L19*(1+$M$6) -> 0 | N19: SF | O19: =IF(AND($C19<>"",$D19<>"",$E19<>""),IF(COUNTIFS(TileTable[Section],$C19,TileTable[Level],$D19,TileTable[Item_Name],$E19)>0,SUMIFS(TileTable[Olsen_Cost],TileTable[Section],$C19,TileTable[Level],$D19,TileTable[Item_Name],$E19),""),"0") -> 0 | P19: =O19*M19 -> 0 | Q19: =(M19/SUM($M$8:$M$30,$M$32:$M$43,$M$45:$M$56,$M$58:$M$69,$M$71:$M$82,$M$84:$M$95,$M$97:$M$108,$M$110:$M$121,$M$123:$M$134))*$V$5 -> 0 | R19: =P19-Q19 -> 0 | S19: =IF(R19>0,R19/$S$6,R19) -> 0 | X19: Step #1: Select Type of Tile in Column C
B20: Bedroom #5 | C20: Floor Tile | M20: =L20*(1+$M$6) -> 0 | N20: SF | O20: =IF(AND($C20<>"",$D20<>"",$E20<>""),IF(COUNTIFS(TileTable[Section],$C20,TileTable[Level],$D20,TileTable[Item_Name],$E20)>0,SUMIFS(TileTable[Olsen_Cost],TileTable[Section],$C20,TileTable[Level],$D20,TileTable[Item_Name],$E20),""),"0") -> 0 | P20: =O20*M20 -> 0 | Q20: =(M20/SUM($M$8:$M$30,$M$32:$M$43,$M$45:$M$56,$M$58:$M$69,$M$71:$M$82,$M$84:$M$95,$M$97:$M$108,$M$110:$M$121,$M$123:$M$134))*$V$5 -> 0 | R20: =P20-Q20 -> 0 | S20: =IF(R20>0,R20/$S$6,R20) -> 0 | X20: Step #2: Select Level of Tile in Column D
B21: Bedroom #6 | C21: Floor Tile | M21: =L21*(1+$M$6) -> 0 | N21: SF | O21: =IF(AND($C21<>"",$D21<>"",$E21<>""),IF(COUNTIFS(TileTable[Section],$C21,TileTable[Level],$D21,TileTable[Item_Name],$E21)>0,SUMIFS(TileTable[Olsen_Cost],TileTable[Section],$C21,TileTable[Level],$D21,TileTable[Item_Name],$E21),""),"0") -> 0 | P21: =O21*M21 -> 0 | Q21: =(M21/SUM($M$8:$M$30,$M$32:$M$43,$M$45:$M$56,$M$58:$M$69,$M$71:$M$82,$M$84:$M$95,$M$97:$M$108,$M$110:$M$121,$M$123:$M$134))*$V$5 -> 0 | R21: =P21-Q21 -> 0 | S21: =IF(R21>0,R21/$S$6,R21) -> 0 | X21: Step #3: Select Product Name in Column E
B22: Bathroom #2 | C22: Floor Tile | M22: =L22*(1+$M$6) -> 0 | N22: SF | O22: =IF(AND($C22<>"",$D22<>"",$E22<>""),IF(COUNTIFS(TileTable[Section],$C22,TileTable[Level],$D22,TileTable[Item_Name],$E22)>0,SUMIFS(TileTable[Olsen_Cost],TileTable[Section],$C22,TileTable[Level],$D22,TileTable[Item_Name],$E22),""),"0") -> 0 | P22: =O22*M22 -> 0 | Q22: =(M22/SUM($M$8:$M$30,$M$32:$M$43,$M$45:$M$56,$M$58:$M$69,$M$71:$M$82,$M$84:$M$95,$M$97:$M$108,$M$110:$M$121,$M$123:$M$134))*$V$5 -> 0 | R22: =P22-Q22 -> 0 | S22: =IF(R22>0,R22/$S$6,R22) -> 0 | X22: Step $4: Select Finish, Pattern, Direction, Grout and Joint
B23: Bathroom #3 | C23: Floor Tile | M23: =L23*(1+$M$6) -> 0 | N23: SF | O23: =IF(AND($C23<>"",$D23<>"",$E23<>""),IF(COUNTIFS(TileTable[Section],$C23,TileTable[Level],$D23,TileTable[Item_Name],$E23)>0,SUMIFS(TileTable[Olsen_Cost],TileTable[Section],$C23,TileTable[Level],$D23,TileTable[Item_Name],$E23),""),"0") -> 0 | P23: =O23*M23 -> 0 | Q23: =(M23/SUM($M$8:$M$30,$M$32:$M$43,$M$45:$M$56,$M$58:$M$69,$M$71:$M$82,$M$84:$M$95,$M$97:$M$108,$M$110:$M$121,$M$123:$M$134))*$V$5 -> 0 | R23: =P23-Q23 -> 0 | S23: =IF(R23>0,R23/$S$6,R23) -> 0 | X23: Step #5: Input Niche width and height (=0 if no niche)
B24: Bathroom #4 | C24: Floor Tile | M24: =L24*(1+$M$6) -> 0 | N24: SF | O24: =IF(AND($C24<>"",$D24<>"",$E24<>""),IF(COUNTIFS(TileTable[Section],$C24,TileTable[Level],$D24,TileTable[Item_Name],$E24)>0,SUMIFS(TileTable[Olsen_Cost],TileTable[Section],$C24,TileTable[Level],$D24,TileTable[Item_Name],$E24),""),"0") -> 0 | P24: =O24*M24 -> 0 | Q24: =(M24/SUM($M$8:$M$30,$M$32:$M$43,$M$45:$M$56,$M$58:$M$69,$M$71:$M$82,$M$84:$M$95,$M$97:$M$108,$M$110:$M$121,$M$123:$M$134))*$V$5 -> 0 | R24: =P24-Q24 -> 0 | S24: =IF(R24>0,R24/$S$6,R24) -> 0 | X24: Step #6: Add special instructions and notes
B25: Bathroom #5 | C25: Floor Tile | M25: =L25*(1+$M$6) -> 0 | N25: SF | O25: =IF(AND($C25<>"",$D25<>"",$E25<>""),IF(COUNTIFS(TileTable[Section],$C25,TileTable[Level],$D25,TileTable[Item_Name],$E25)>0,SUMIFS(TileTable[Olsen_Cost],TileTable[Section],$C25,TileTable[Level],$D25,TileTable[Item_Name],$E25),""),"0") -> 0 | P25: =O25*M25 -> 0 | Q25: =(M25/SUM($M$8:$M$30,$M$32:$M$43,$M$45:$M$56,$M$58:$M$69,$M$71:$M$82,$M$84:$M$95,$M$97:$M$108,$M$110:$M$121,$M$123:$M$134))*$V$5 -> 0 | R25: =P25-Q25 -> 0 | S25: =IF(R25>0,R25/$S$6,R25) -> 0 | X25: Step #7: Explain to client this pricing is a ballpark price
B26: Bathroom #6 | C26: Floor Tile | M26: =L26*(1+$M$6) -> 0 | N26: SF | O26: =IF(AND($C26<>"",$D26<>"",$E26<>""),IF(COUNTIFS(TileTable[Section],$C26,TileTable[Level],$D26,TileTable[Item_Name],$E26)>0,SUMIFS(TileTable[Olsen_Cost],TileTable[Section],$C26,TileTable[Level],$D26,TileTable[Item_Name],$E26),""),"0") -> 0 | P26: =O26*M26 -> 0 | Q26: =(M26/SUM($M$8:$M$30,$M$32:$M$43,$M$45:$M$56,$M$58:$M$69,$M$71:$M$82,$M$84:$M$95,$M$97:$M$108,$M$110:$M$121,$M$123:$M$134))*$V$5 -> 0 | R26: =P26-Q26 -> 0 | S26: =IF(R26>0,R26/$S$6,R26) -> 0 | X26: Step #8: Verify ALL lines with SF value also have selection before pricing!!
M27: =L27*(1+$M$6) -> 0 | N27: SF | O27: =IF(AND($C27<>"",$D27<>"",$E27<>""),IF(COUNTIFS(TileTable[Section],$C27,TileTable[Level],$D27,TileTable[Item_Name],$E27)>0,SUMIFS(TileTable[Olsen_Cost],TileTable[Section],$C27,TileTable[Level],$D27,TileTable[Item_Name],$E27),""),"0") -> 0 | P27: =O27*M27 -> 0 | Q27: =(M27/SUM($M$8:$M$30,$M$32:$M$43,$M$45:$M$56,$M$58:$M$69,$M$71:$M$82,$M$84:$M$95,$M$97:$M$108,$M$110:$M$121,$M$123:$M$134))*$V$5 -> 0 | R27: =P27-Q27 -> 0 | S27: =IF(R27>0,R27/$S$6,R27) -> 0 | X27: Step #9: Add thin info and pricing to buildertrend and get a signoff
M28: =L28*(1+$M$6) -> 0 | N28: SF | O28: =IF(AND($C28<>"",$D28<>"",$E28<>""),IF(COUNTIFS(TileTable[Section],$C28,TileTable[Level],$D28,TileTable[Item_Name],$E28)>0,SUMIFS(TileTable[Olsen_Cost],TileTable[Section],$C28,TileTable[Level],$D28,TileTable[Item_Name],$E28),""),"0") -> 0 | P28: =O28*M28 -> 0 | Q28: =(M28/SUM($M$8:$M$30,$M$32:$M$43,$M$45:$M$56,$M$58:$M$69,$M$71:$M$82,$M$84:$M$95,$M$97:$M$108,$M$110:$M$121,$M$123:$M$134))*$V$5 -> 0 | R28: =P28-Q28 -> 0 | S28: =IF(R28>0,R28/$S$6,R28) -> 0 | X28: Step #10: Add correct language to the COF and total charge to HO (Cell V17)
M29: =L29*(1+$M$6) -> 0 | N29: SF | O29: =IF(AND($C29<>"",$D29<>"",$E29<>""),IF(COUNTIFS(TileTable[Section],$C29,TileTable[Level],$D29,TileTable[Item_Name],$E29)>0,SUMIFS(TileTable[Olsen_Cost],TileTable[Section],$C29,TileTable[Level],$D29,TileTable[Item_Name],$E29),""),"0") -> 0 | P29: =O29*M29 -> 0 | Q29: =(M29/SUM($M$8:$M$30,$M$32:$M$43,$M$45:$M$56,$M$58:$M$69,$M$71:$M$82,$M$84:$M$95,$M$97:$M$108,$M$110:$M$121,$M$123:$M$134))*$V$5 -> 0 | R29: =P29-Q29 -> 0 | S29: =IF(R29>0,R29/$S$6,R29) -> 0
P30: *HO Pays: | S30: =SUM(S8:S29) -> -16849.352
B31: Master Bathroom
B32: Shower Floor Pan | C32: Shower Pan Tile | M32: =L32*(1+$M$6) -> 0 | N32: SF | O32: =IF(AND($C32<>"",$D32<>"",$E32<>""),IF(COUNTIFS(TileTable[Section],$C32,TileTable[Level],$D32,TileTable[Item_Name],$E32)>0,SUMIFS(TileTable[Olsen_Cost],TileTable[Section],$C32,TileTable[Level],$D32,TileTable[Item_Name],$E32),""),"0") -> 0 | P32: =O32*M32 -> 0 | Q32: =(M32/SUM($M$8:$M$30,$M$32:$M$43,$M$45:$M$56,$M$58:$M$69,$M$71:$M$82,$M$84:$M$95,$M$97:$M$108,$M$110:$M$121,$M$123:$M$134))*$V$5 -> 0 | R32: =P32-Q32 -> 0 | S32: =IF(R32>0,R32/$S$6,R32) -> 0
B33: Shower Walls (8') | C33: Shower / Tub Wall Tile | M33: =L33*(1+$M$6) -> 0 | N33: SF | O33: =IF(AND($C33<>"",$D33<>"",$E33<>""),IF(COUNTIFS(TileTable[Section],$C33,TileTable[Level],$D33,TileTable[Item_Name],$E33)>0,SUMIFS(TileTable[Olsen_Cost],TileTable[Section],$C33,TileTable[Level],$D33,TileTable[Item_Name],$E33),""),"0") -> 0 | P33: =O33*M33 -> 0 | Q33: =(M33/SUM($M$8:$M$30,$M$32:$M$43,$M$45:$M$56,$M$58:$M$69,$M$71:$M$82,$M$84:$M$95,$M$97:$M$108,$M$110:$M$121,$M$123:$M$134))*$V$5 -> 0 | R33: =P33-Q33 -> 0 | S33: =IF(R33>0,R33/$S$6,R33) -> 0 | X33: Instructions for ESTIMATOR (After-HO meeting)
B34: (+) Shower Walls to Ceiling | C34: Shower / Tub Wall Tile | M34: =L34*(1+$M$6) -> 0 | N34: SF | O34: =IF(AND($C34<>"",$D34<>"",$E34<>""),IF(COUNTIFS(TileTable[Section],$C34,TileTable[Level],$D34,TileTable[Item_Name],$E34)>0,SUMIFS(TileTable[Olsen_Cost],TileTable[Section],$C34,TileTable[Level],$D34,TileTable[Item_Name],$E34),""),"0") -> 0 | P34: =O34*M34 -> 0 | Q34: =(M34/SUM($M$8:$M$30,$M$32:$M$43,$M$45:$M$56,$M$58:$M$69,$M$71:$M$82,$M$84:$M$95,$M$97:$M$108,$M$110:$M$121,$M$123:$M$134))*$V$5 -> 0 | R34: =P34-Q34 -> 0 | S34: =IF(R34>0,R34/$S$6,R34) -> 0 | X34: Step #1: Verify Pricing
B35: Shower Niche | C35: Shower Pan Tile | L35: =G43 -> 2.7777778 | M35: =L35*(1+$M$6) -> 3.0555556 | N35: SF | O35: =IF(AND($C35<>"",$D35<>"",$E35<>""),IF(COUNTIFS(TileTable[Section],$C35,TileTable[Level],$D35,TileTable[Item_Name],$E35)>0,SUMIFS(TileTable[Olsen_Cost],TileTable[Section],$C35,TileTable[Level],$D35,TileTable[Item_Name],$E35),""),"0") -> 0 | P35: =O35*M35 -> 0 | Q35: =(M35/SUM($M$8:$M$30,$M$32:$M$43,$M$45:$M$56,$M$58:$M$69,$M$71:$M$82,$M$84:$M$95,$M$97:$M$108,$M$110:$M$121,$M$123:$M$134))*$V$5 -> 49.208401 | R35: =P35-Q35 -> -49.208401 | S35: =IF(R35>0,R35/$S$6,R35) -> -49.208401 | X35: Step #2: Assign all Rooms in Rows 8, 29,42, 55,68,81,94,107,120
B36: Knee Wall (Inside Shower Face) | M36: =L36*(1+$M$6) -> 0 | N36: SF | O36: =IF(AND($C36<>"",$D36<>"",$E36<>""),IF(COUNTIFS(TileTable[Section],$C36,TileTable[Level],$D36,TileTable[Item_Name],$E36)>0,SUMIFS(TileTable[Olsen_Cost],TileTable[Section],$C36,TileTable[Level],$D36,TileTable[Item_Name],$E36),""),"0") -> 0 | P36: =O36*M36 -> 0 | Q36: =(M36/SUM($M$8:$M$30,$M$32:$M$43,$M$45:$M$56,$M$58:$M$69,$M$71:$M$82,$M$84:$M$95,$M$97:$M$108,$M$110:$M$121,$M$123:$M$134))*$V$5 -> 0 | R36: =P36-Q36 -> 0 | S36: =IF(R36>0,R36/$S$6,R36) -> 0 | X36: Step #3: Assign all areas receiving tile Column B
B37: Knee Wall (Outside Shower Face) | M37: =L37*(1+$M$6) -> 0 | N37: SF | O37: =IF(AND($C37<>"",$D37<>"",$E37<>""),IF(COUNTIFS(TileTable[Section],$C37,TileTable[Level],$D37,TileTable[Item_Name],$E37)>0,SUMIFS(TileTable[Olsen_Cost],TileTable[Section],$C37,TileTable[Level],$D37,TileTable[Item_Name],$E37),""),"0") -> 0 | P37: =O37*M37 -> 0 | Q37: =(M37/SUM($M$8:$M$30,$M$32:$M$43,$M$45:$M$56,$M$58:$M$69,$M$71:$M$82,$M$84:$M$95,$M$97:$M$108,$M$110:$M$121,$M$123:$M$134))*$V$5 -> 0 | R37: =P37-Q37 -> 0 | S37: =IF(R37>0,R37/$S$6,R37) -> 0
B38: Knee Wall Cap | C38: Knee Wall Cap | D38: Level 1 | M38: =L38*(1+$M$6) -> 0 | N38: SF | O38: =IF(AND($C38<>"",$D38<>"",$E38<>""),IF(COUNTIFS(TileTable[Section],$C38,TileTable[Level],$D38,TileTable[Item_Name],$E38)>0,SUMIFS(TileTable[Olsen_Cost],TileTable[Section],$C38,TileTable[Level],$D38,TileTable[Item_Name],$E38),""),"0") -> 0 | P38: =O38*M38 -> 0 | Q38: =(M38/SUM($M$8:$M$30,$M$32:$M$43,$M$45:$M$56,$M$58:$M$69,$M$71:$M$82,$M$84:$M$95,$M$97:$M$108,$M$110:$M$121,$M$123:$M$134))*$V$5 -> 0 | R38: =P38-Q38 -> 0 | S38: =IF(R38>0,R38/$S$6,R38) -> 0
B39: Sill | C39: Sill | D39: Level 1 | M39: =L39*(1+$M$6) -> 0 | N39: SF | O39: =IF(AND($C39<>"",$D39<>"",$E39<>""),IF(COUNTIFS(TileTable[Section],$C39,TileTable[Level],$D39,TileTable[Item_Name],$E39)>0,SUMIFS(TileTable[Olsen_Cost],TileTable[Section],$C39,TileTable[Level],$D39,TileTable[Item_Name],$E39),""),"0") -> 0 | P39: =O39*M39 -> 0 | Q39: =(M39/SUM($M$8:$M$30,$M$32:$M$43,$M$45:$M$56,$M$58:$M$69,$M$71:$M$82,$M$84:$M$95,$M$97:$M$108,$M$110:$M$121,$M$123:$M$134))*$V$5 -> 0 | R39: =P39-Q39 -> 0 | S39: =IF(R39>0,R39/$S$6,R39) -> 0
B40: Curb | C40: Curb | D40: Level 1 | M40: =L40*(1+$M$6) -> 0 | N40: SF | O40: =IF(AND($C40<>"",$D40<>"",$E40<>""),IF(COUNTIFS(TileTable[Section],$C40,TileTable[Level],$D40,TileTable[Item_Name],$E40)>0,SUMIFS(TileTable[Olsen_Cost],TileTable[Section],$C40,TileTable[Level],$D40,TileTable[Item_Name],$E40),""),"0") -> 0 | P40: =O40*M40 -> 0 | Q40: =(M40/SUM($M$8:$M$30,$M$32:$M$43,$M$45:$M$56,$M$58:$M$69,$M$71:$M$82,$M$84:$M$95,$M$97:$M$108,$M$110:$M$121,$M$123:$M$134))*$V$5 -> 0 | R40: =P40-Q40 -> 0 | S40: =IF(R40>0,R40/$S$6,R40) -> 0
M41: =L41*(1+$M$6) -> 0 | N41: SF | O41: =IF(AND($C41<>"",$D41<>"",$E41<>""),IF(COUNTIFS(TileTable[Section],$C41,TileTable[Level],$D41,TileTable[Item_Name],$E41)>0,SUMIFS(TileTable[Olsen_Cost],TileTable[Section],$C41,TileTable[Level],$D41,TileTable[Item_Name],$E41),""),"0") -> 0 | P41: =O41*M41 -> 0 | Q41: =(M41/SUM($M$8:$M$30,$M$32:$M$43,$M$45:$M$56,$M$58:$M$69,$M$71:$M$82,$M$84:$M$95,$M$97:$M$108,$M$110:$M$121,$M$123:$M$134))*$V$5 -> 0 | R41: =P41-Q41 -> 0 | S41: =IF(R41>0,R41/$S$6,R41) -> 0
B42: Special Instructions: | N42: =IF(AND($C42<>"",$D42<>"",$E42<>""),IF(COUNTIFS(TileTable[Section],$C42,TileTable[Level],$D42,TileTable[Item_Name],$E42)>0,SUMIFS(TileTable[Olsen_Cost],TileTable[Section],$C42,TileTable[Level],$D42,TileTable[Item_Name],$E42),""),"")
B43: Niche Width (in): | C43: 12 | D43: Height (in): | E43: 12 | F43: Total Niche Area | G43: =IF(C43=0,0,((C43+8)*(E43+8))/144) -> 2.7777778 | H43: SF | N43: =IF(AND($C43<>"",$D43<>"",$E43<>""),IF(COUNTIFS(TileTable[Section],$C43,TileTable[Level],$D43,TileTable[Item_Name],$E43)>0,SUMIFS(TileTable[Olsen_Cost],TileTable[Section],$C43,TileTable[Level],$D43,TileTable[Item_Name],$E43),""),"") | P43: *HO Pays: | S43: =SUM(S32:S42) -> -49.208401
B44: Bathroom #2
B45: Shower Floor Pan | C45: Shower Pan Tile | M45: =L45*(1+$M$6) -> 0 | N45: SF | O45: =IF(AND($C45<>"",$D45<>"",$E45<>""),IF(COUNTIFS(TileTable[Section],$C45,TileTable[Level],$D45,TileTable[Item_Name],$E45)>0,SUMIFS(TileTable[Olsen_Cost],TileTable[Section],$C45,TileTable[Level],$D45,TileTable[Item_Name],$E45),""),"0") -> 0 | P45: =O45*M45 -> 0 | Q45: =(M45/SUM($M$8:$M$30,$M$32:$M$43,$M$45:$M$56,$M$58:$M$69,$M$71:$M$82,$M$84:$M$95,$M$97:$M$108,$M$110:$M$121,$M$123:$M$134))*$V$5 -> 0 | R45: =P45-Q45 -> 0 | S45: =IF(R45>0,R45/$S$6,R45) -> 0
B46: Shower Walls (8') | M46: =L46*(1+$M$6) -> 0 | N46: SF | O46: =IF(AND($C46<>"",$D46<>"",$E46<>""),IF(COUNTIFS(TileTable[Section],$C46,TileTable[Level],$D46,TileTable[Item_Name],$E46)>0,SUMIFS(TileTable[Olsen_Cost],TileTable[Section],$C46,TileTable[Level],$D46,TileTable[Item_Name],$E46),""),"0") -> 0 | P46: =O46*M46 -> 0 | Q46: =(M46/SUM($M$8:$M$30,$M$32:$M$43,$M$45:$M$56,$M$58:$M$69,$M$71:$M$82,$M$84:$M$95,$M$97:$M$108,$M$110:$M$121,$M$123:$M$134))*$V$5 -> 0 | R46: =P46-Q46 -> 0 | S46: =IF(R46>0,R46/$S$6,R46) -> 0
B47: (+) Shower Walls to Ceiling | M47: =L47*(1+$M$6) -> 0 | N47: SF | O47: =IF(AND($C47<>"",$D47<>"",$E47<>""),IF(COUNTIFS(TileTable[Section],$C47,TileTable[Level],$D47,TileTable[Item_Name],$E47)>0,SUMIFS(TileTable[Olsen_Cost],TileTable[Section],$C47,TileTable[Level],$D47,TileTable[Item_Name],$E47),""),"0") -> 0 | P47: =O47*M47 -> 0 | Q47: =(M47/SUM($M$8:$M$30,$M$32:$M$43,$M$45:$M$56,$M$58:$M$69,$M$71:$M$82,$M$84:$M$95,$M$97:$M$108,$M$110:$M$121,$M$123:$M$134))*$V$5 -> 0 | R47: =P47-Q47 -> 0 | S47: =IF(R47>0,R47/$S$6,R47) -> 0
B48: Shower Niche | L48: =G56 -> 0 | M48: =L48*(1+$M$6) -> 0 | N48: SF | O48: =IF(AND($C48<>"",$D48<>"",$E48<>""),IF(COUNTIFS(TileTable[Section],$C48,TileTable[Level],$D48,TileTable[Item_Name],$E48)>0,SUMIFS(TileTable[Olsen_Cost],TileTable[Section],$C48,TileTable[Level],$D48,TileTable[Item_Name],$E48),""),"0") -> 0 | P48: =O48*M48 -> 0 | Q48: =(M48/SUM($M$8:$M$30,$M$32:$M$43,$M$45:$M$56,$M$58:$M$69,$M$71:$M$82,$M$84:$M$95,$M$97:$M$108,$M$110:$M$121,$M$123:$M$134))*$V$5 -> 0 | R48: =P48-Q48 -> 0 | S48: =IF(R48>0,R48/$S$6,R48) -> 0
B49: Knee Wall (Inside Shower Face) | M49: =L49*(1+$M$6) -> 0 | N49: SF | O49: =IF(AND($C49<>"",$D49<>"",$E49<>""),IF(COUNTIFS(TileTable[Section],$C49,TileTable[Level],$D49,TileTable[Item_Name],$E49)>0,SUMIFS(TileTable[Olsen_Cost],TileTable[Section],$C49,TileTable[Level],$D49,TileTable[Item_Name],$E49),""),"0") -> 0 | P49: =O49*M49 -> 0 | Q49: =(M49/SUM($M$8:$M$30,$M$32:$M$43,$M$45:$M$56,$M$58:$M$69,$M$71:$M$82,$M$84:$M$95,$M$97:$M$108,$M$110:$M$121,$M$123:$M$134))*$V$5 -> 0 | R49: =P49-Q49 -> 0 | S49: =IF(R49>0,R49/$S$6,R49) -> 0
B50: Knee Wall (Outside Shower Face) | M50: =L50*(1+$M$6) -> 0 | N50: SF | O50: =IF(AND($C50<>"",$D50<>"",$E50<>""),IF(COUNTIFS(TileTable[Section],$C50,TileTable[Level],$D50,TileTable[Item_Name],$E50)>0,SUMIFS(TileTable[Olsen_Cost],TileTable[Section],$C50,TileTable[Level],$D50,TileTable[Item_Name],$E50),""),"0") -> 0 | P50: =O50*M50 -> 0 | Q50: =(M50/SUM($M$8:$M$30,$M$32:$M$43,$M$45:$M$56,$M$58:$M$69,$M$71:$M$82,$M$84:$M$95,$M$97:$M$108,$M$110:$M$121,$M$123:$M$134))*$V$5 -> 0 | R50: =P50-Q50 -> 0 | S50: =IF(R50>0,R50/$S$6,R50) -> 0
B51: Knee Wall Cap | C51: Knee Wall Cap | D51: Level 1 | M51: =L51*(1+$M$6) -> 0 | N51: SF | O51: =IF(AND($C51<>"",$D51<>"",$E51<>""),IF(COUNTIFS(TileTable[Section],$C51,TileTable[Level],$D51,TileTable[Item_Name],$E51)>0,SUMIFS(TileTable[Olsen_Cost],TileTable[Section],$C51,TileTable[Level],$D51,TileTable[Item_Name],$E51),""),"0") -> 0 | P51: =O51*M51 -> 0 | Q51: =(M51/SUM($M$8:$M$30,$M$32:$M$43,$M$45:$M$56,$M$58:$M$69,$M$71:$M$82,$M$84:$M$95,$M$97:$M$108,$M$110:$M$121,$M$123:$M$134))*$V$5 -> 0 | R51: =P51-Q51 -> 0 | S51: =IF(R51>0,R51/$S$6,R51) -> 0
B52: Sill | C52: Sill | D52: Level 1 | M52: =L52*(1+$M$6) -> 0 | N52: SF | O52: =IF(AND($C52<>"",$D52<>"",$E52<>""),IF(COUNTIFS(TileTable[Section],$C52,TileTable[Level],$D52,TileTable[Item_Name],$E52)>0,SUMIFS(TileTable[Olsen_Cost],TileTable[Section],$C52,TileTable[Level],$D52,TileTable[Item_Name],$E52),""),"0") -> 0 | P52: =O52*M52 -> 0 | Q52: =(M52/SUM($M$8:$M$30,$M$32:$M$43,$M$45:$M$56,$M$58:$M$69,$M$71:$M$82,$M$84:$M$95,$M$97:$M$108,$M$110:$M$121,$M$123:$M$134))*$V$5 -> 0 | R52: =P52-Q52 -> 0 | S52: =IF(R52>0,R52/$S$6,R52) -> 0
B53: Curb | C53: Curb | D53: Level 1 | M53: =L53*(1+$M$6) -> 0 | N53: SF | O53: =IF(AND($C53<>"",$D53<>"",$E53<>""),IF(COUNTIFS(TileTable[Section],$C53,TileTable[Level],$D53,TileTable[Item_Name],$E53)>0,SUMIFS(TileTable[Olsen_Cost],TileTable[Section],$C53,TileTable[Level],$D53,TileTable[Item_Name],$E53),""),"0") -> 0 | P53: =O53*M53 -> 0 | Q53: =(M53/SUM($M$8:$M$30,$M$32:$M$43,$M$45:$M$56,$M$58:$M$69,$M$71:$M$82,$M$84:$M$95,$M$97:$M$108,$M$110:$M$121,$M$123:$M$134))*$V$5 -> 0 | R53: =P53-Q53 -> 0 | S53: =IF(R53>0,R53/$S$6,R53) -> 0
M54: =L54*(1+$M$6) -> 0 | N54: SF | O54: =IF(AND($C54<>"",$D54<>"",$E54<>""),IF(COUNTIFS(TileTable[Section],$C54,TileTable[Level],$D54,TileTable[Item_Name],$E54)>0,SUMIFS(TileTable[Olsen_Cost],TileTable[Section],$C54,TileTable[Level],$D54,TileTable[Item_Name],$E54),""),"0") -> 0 | P54: =O54*M54 -> 0 | Q54: =(M54/SUM($M$8:$M$30,$M$32:$M$43,$M$45:$M$56,$M$58:$M$69,$M$71:$M$82,$M$84:$M$95,$M$97:$M$108,$M$110:$M$121,$M$123:$M$134))*$V$5 -> 0 | R54: =P54-Q54 -> 0 | S54: =IF(R54>0,R54/$S$6,R54) -> 0
B55: Special Instructions: | N55: =IF(AND($B55<>"",$D55<>"",$E55<>""),IF(COUNTIFS(TileTable[Section],$B55,TileTable[Level],$D55,TileTable[Item_Name],$E55)>0,SUMIFS(TileTable[Olsen_Cost],TileTable[Section],$B55,TileTable[Level],$D55,TileTable[Item_Name],$E55),""),"")
B56: Niche Width (in): | C56: 0 | D56: Height (in): | E56: 0 | F56: Total Niche Area | G56: =IF(C56=0,0,((C56+8)*(E56+8))/144) -> 0 | H56: SF | N56: =IF(AND($C56<>"",$D56<>"",$E56<>""),IF(COUNTIFS(TileTable[Section],$C56,TileTable[Level],$D56,TileTable[Item_Name],$E56)>0,SUMIFS(TileTable[Olsen_Cost],TileTable[Section],$C56,TileTable[Level],$D56,TileTable[Item_Name],$E56),""),"") | P56: *HO Pays: | S56: =SUM(S45:S55) -> 0
B57: Bathroom #3
B58: Shower Floor Pan | C58: Floor Tile | M58: =L58*(1+$M$6) -> 0 | N58: SF | O58: =IF(AND($C58<>"",$D58<>"",$E58<>""),IF(COUNTIFS(TileTable[Section],$C58,TileTable[Level],$D58,TileTable[Item_Name],$E58)>0,SUMIFS(TileTable[Olsen_Cost],TileTable[Section],$C58,TileTable[Level],$D58,TileTable[Item_Name],$E58),""),"0") -> 0 | P58: =O58*M58 -> 0 | Q58: =(M58/SUM($M$8:$M$30,$M$32:$M$43,$M$45:$M$56,$M$58:$M$69,$M$71:$M$82,$M$84:$M$95,$M$97:$M$108,$M$110:$M$121,$M$123:$M$134))*$V$5 -> 0 | R58: =P58-Q58 -> 0 | S58: =IF(R58>0,R58/$S$6,R58) -> 0
B59: Shower Walls (8') | M59: =L59*(1+$M$6) -> 0 | N59: SF | O59: =IF(AND($C59<>"",$D59<>"",$E59<>""),IF(COUNTIFS(TileTable[Section],$C59,TileTable[Level],$D59,TileTable[Item_Name],$E59)>0,SUMIFS(TileTable[Olsen_Cost],TileTable[Section],$C59,TileTable[Level],$D59,TileTable[Item_Name],$E59),""),"0") -> 0 | P59: =O59*M59 -> 0 | Q59: =(M59/SUM($M$8:$M$30,$M$32:$M$43,$M$45:$M$56,$M$58:$M$69,$M$71:$M$82,$M$84:$M$95,$M$97:$M$108,$M$110:$M$121,$M$123:$M$134))*$V$5 -> 0 | R59: =P59-Q59 -> 0 | S59: =IF(R59>0,R59/$S$6,R59) -> 0
B60: (+) Shower Walls to Ceiling | M60: =L60*(1+$M$6) -> 0 | N60: SF | O60: =IF(AND($C60<>"",$D60<>"",$E60<>""),IF(COUNTIFS(TileTable[Section],$C60,TileTable[Level],$D60,TileTable[Item_Name],$E60)>0,SUMIFS(TileTable[Olsen_Cost],TileTable[Section],$C60,TileTable[Level],$D60,TileTable[Item_Name],$E60),""),"0") -> 0 | P60: =O60*M60 -> 0 | Q60: =(M60/SUM($M$8:$M$30,$M$32:$M$43,$M$45:$M$56,$M$58:$M$69,$M$71:$M$82,$M$84:$M$95,$M$97:$M$108,$M$110:$M$121,$M$123:$M$134))*$V$5 -> 0 | R60: =P60-Q60 -> 0 | S60: =IF(R60>0,R60/$S$6,R60) -> 0
B61: Shower Niche | L61: =G69 -> 0 | M61: =L61*(1+$M$6) -> 0 | N61: SF | O61: =IF(AND($C61<>"",$D61<>"",$E61<>""),IF(COUNTIFS(TileTable[Section],$C61,TileTable[Level],$D61,TileTable[Item_Name],$E61)>0,SUMIFS(TileTable[Olsen_Cost],TileTable[Section],$C61,TileTable[Level],$D61,TileTable[Item_Name],$E61),""),"0") -> 0 | P61: =O61*M61 -> 0 | Q61: =(M61/SUM($M$8:$M$30,$M$32:$M$43,$M$45:$M$56,$M$58:$M$69,$M$71:$M$82,$M$84:$M$95,$M$97:$M$108,$M$110:$M$121,$M$123:$M$134))*$V$5 -> 0 | R61: =P61-Q61 -> 0 | S61: =IF(R61>0,R61/$S$6,R61) -> 0
B62: Knee Wall (Inside Shower Face) | M62: =L62*(1+$M$6) -> 0 | N62: SF | O62: =IF(AND($C62<>"",$D62<>"",$E62<>""),IF(COUNTIFS(TileTable[Section],$C62,TileTable[Level],$D62,TileTable[Item_Name],$E62)>0,SUMIFS(TileTable[Olsen_Cost],TileTable[Section],$C62,TileTable[Level],$D62,TileTable[Item_Name],$E62),""),"0") -> 0 | P62: =O62*M62 -> 0 | Q62: =(M62/SUM($M$8:$M$30,$M$32:$M$43,$M$45:$M$56,$M$58:$M$69,$M$71:$M$82,$M$84:$M$95,$M$97:$M$108,$M$110:$M$121,$M$123:$M$134))*$V$5 -> 0 | R62: =P62-Q62 -> 0 | S62: =IF(R62>0,R62/$S$6,R62) -> 0
B63: Knee Wall (Outside Shower Face) | M63: =L63*(1+$M$6) -> 0 | N63: SF | O63: =IF(AND($C63<>"",$D63<>"",$E63<>""),IF(COUNTIFS(TileTable[Section],$C63,TileTable[Level],$D63,TileTable[Item_Name],$E63)>0,SUMIFS(TileTable[Olsen_Cost],TileTable[Section],$C63,TileTable[Level],$D63,TileTable[Item_Name],$E63),""),"0") -> 0 | P63: =O63*M63 -> 0 | Q63: =(M63/SUM($M$8:$M$30,$M$32:$M$43,$M$45:$M$56,$M$58:$M$69,$M$71:$M$82,$M$84:$M$95,$M$97:$M$108,$M$110:$M$121,$M$123:$M$134))*$V$5 -> 0 | R63: =P63-Q63 -> 0 | S63: =IF(R63>0,R63/$S$6,R63) -> 0
B64: Knee Wall Cap | C64: Knee Wall Cap | D64: Level 1 | M64: =L64*(1+$M$6) -> 0 | N64: SF | O64: =IF(AND($C64<>"",$D64<>"",$E64<>""),IF(COUNTIFS(TileTable[Section],$C64,TileTable[Level],$D64,TileTable[Item_Name],$E64)>0,SUMIFS(TileTable[Olsen_Cost],TileTable[Section],$C64,TileTable[Level],$D64,TileTable[Item_Name],$E64),""),"0") -> 0 | P64: =O64*M64 -> 0 | Q64: =(M64/SUM($M$8:$M$30,$M$32:$M$43,$M$45:$M$56,$M$58:$M$69,$M$71:$M$82,$M$84:$M$95,$M$97:$M$108,$M$110:$M$121,$M$123:$M$134))*$V$5 -> 0 | R64: =P64-Q64 -> 0 | S64: =IF(R64>0,R64/$S$6,R64) -> 0
B65: Sill | C65: Sill | D65: Level 1 | M65: =L65*(1+$M$6) -> 0 | N65: SF | O65: =IF(AND($C65<>"",$D65<>"",$E65<>""),IF(COUNTIFS(TileTable[Section],$C65,TileTable[Level],$D65,TileTable[Item_Name],$E65)>0,SUMIFS(TileTable[Olsen_Cost],TileTable[Section],$C65,TileTable[Level],$D65,TileTable[Item_Name],$E65),""),"0") -> 0 | P65: =O65*M65 -> 0 | Q65: =(M65/SUM($M$8:$M$30,$M$32:$M$43,$M$45:$M$56,$M$58:$M$69,$M$71:$M$82,$M$84:$M$95,$M$97:$M$108,$M$110:$M$121,$M$123:$M$134))*$V$5 -> 0 | R65: =P65-Q65 -> 0 | S65: =IF(R65>0,R65/$S$6,R65) -> 0
B66: Curb | C66: Curb | D66: Level 1 | M66: =L66*(1+$M$6) -> 0 | N66: SF | O66: =IF(AND($C66<>"",$D66<>"",$E66<>""),IF(COUNTIFS(TileTable[Section],$C66,TileTable[Level],$D66,TileTable[Item_Name],$E66)>0,SUMIFS(TileTable[Olsen_Cost],TileTable[Section],$C66,TileTable[Level],$D66,TileTable[Item_Name],$E66),""),"0") -> 0 | P66: =O66*M66 -> 0 | Q66: =(M66/SUM($M$8:$M$30,$M$32:$M$43,$M$45:$M$56,$M$58:$M$69,$M$71:$M$82,$M$84:$M$95,$M$97:$M$108,$M$110:$M$121,$M$123:$M$134))*$V$5 -> 0 | R66: =P66-Q66 -> 0 | S66: =IF(R66>0,R66/$S$6,R66) -> 0
M67: =L67*(1+$M$6) -> 0 | N67: SF | O67: =IF(AND($C67<>"",$D67<>"",$E67<>""),IF(COUNTIFS(TileTable[Section],$C67,TileTable[Level],$D67,TileTable[Item_Name],$E67)>0,SUMIFS(TileTable[Olsen_Cost],TileTable[Section],$C67,TileTable[Level],$D67,TileTable[Item_Name],$E67),""),"0") -> 0 | P67: =O67*M67 -> 0 | Q67: =(M67/SUM($M$8:$M$30,$M$32:$M$43,$M$45:$M$56,$M$58:$M$69,$M$71:$M$82,$M$84:$M$95,$M$97:$M$108,$M$110:$M$121,$M$123:$M$134))*$V$5 -> 0 | R67: =P67-Q67 -> 0 | S67: =IF(R67>0,R67/$S$6,R67) -> 0
B68: Special Instructions: | N68: =IF(AND($C68<>"",$D68<>"",$E68<>""),IF(COUNTIFS(TileTable[Section],$C68,TileTable[Level],$D68,TileTable[Item_Name],$E68)>0,SUMIFS(TileTable[Olsen_Cost],TileTable[Section],$C68,TileTable[Level],$D68,TileTable[Item_Name],$E68),""),"")
B69: Niche Width (in): | C69: 0 | D69: Height (in): | E69: 0 | F69: Total Niche Area | G69: =IF(C69=0,0,((C69+8)*(E69+8))/144) -> 0 | H69: SF | N69: =IF(AND($C69<>"",$D69<>"",$E69<>""),IF(COUNTIFS(TileTable[Section],$C69,TileTable[Level],$D69,TileTable[Item_Name],$E69)>0,SUMIFS(TileTable[Olsen_Cost],TileTable[Section],$C69,TileTable[Level],$D69,TileTable[Item_Name],$E69),""),"") | P69: *HO Pays: | S69: =SUM(S58:S68) -> 0
B70: Bathroom #4
B71: Shower Floor Pan | C71: Floor Tile | M71: =L71*(1+$M$6) -> 0 | N71: SF | O71: =IF(AND($C71<>"",$D71<>"",$E71<>""),IF(COUNTIFS(TileTable[Section],$C71,TileTable[Level],$D71,TileTable[Item_Name],$E71)>0,SUMIFS(TileTable[Olsen_Cost],TileTable[Section],$C71,TileTable[Level],$D71,TileTable[Item_Name],$E71),""),"0") -> 0 | P71: =O71*M71 -> 0 | Q71: =(M71/SUM($M$8:$M$30,$M$32:$M$43,$M$45:$M$56,$M$58:$M$69,$M$71:$M$82,$M$84:$M$95,$M$97:$M$108,$M$110:$M$121,$M$123:$M$134))*$V$5 -> 0 | R71: =P71-Q71 -> 0 | S71: =IF(R71>0,R71/$S$6,R71) -> 0
B72: Shower Walls (8') | M72: =L72*(1+$M$6) -> 0 | N72: SF | O72: =IF(AND($C72<>"",$D72<>"",$E72<>""),IF(COUNTIFS(TileTable[Section],$C72,TileTable[Level],$D72,TileTable[Item_Name],$E72)>0,SUMIFS(TileTable[Olsen_Cost],TileTable[Section],$C72,TileTable[Level],$D72,TileTable[Item_Name],$E72),""),"0") -> 0 | P72: =O72*M72 -> 0 | Q72: =(M72/SUM($M$8:$M$30,$M$32:$M$43,$M$45:$M$56,$M$58:$M$69,$M$71:$M$82,$M$84:$M$95,$M$97:$M$108,$M$110:$M$121,$M$123:$M$134))*$V$5 -> 0 | R72: =P72-Q72 -> 0 | S72: =IF(R72>0,R72/$S$6,R72) -> 0
B73: (+) Shower Walls to Ceiling | M73: =L73*(1+$M$6) -> 0 | N73: SF | O73: =IF(AND($C73<>"",$D73<>"",$E73<>""),IF(COUNTIFS(TileTable[Section],$C73,TileTable[Level],$D73,TileTable[Item_Name],$E73)>0,SUMIFS(TileTable[Olsen_Cost],TileTable[Section],$C73,TileTable[Level],$D73,TileTable[Item_Name],$E73),""),"0") -> 0 | P73: =O73*M73 -> 0 | Q73: =(M73/SUM($M$8:$M$30,$M$32:$M$43,$M$45:$M$56,$M$58:$M$69,$M$71:$M$82,$M$84:$M$95,$M$97:$M$108,$M$110:$M$121,$M$123:$M$134))*$V$5 -> 0 | R73: =P73-Q73 -> 0 | S73: =IF(R73>0,R73/$S$6,R73) -> 0
B74: Shower Niche | L74: =G82 -> 0 | M74: =L74*(1+$M$6) -> 0 | N74: SF | O74: =IF(AND($C74<>"",$D74<>"",$E74<>""),IF(COUNTIFS(TileTable[Section],$C74,TileTable[Level],$D74,TileTable[Item_Name],$E74)>0,SUMIFS(TileTable[Olsen_Cost],TileTable[Section],$C74,TileTable[Level],$D74,TileTable[Item_Name],$E74),""),"0") -> 0 | P74: =O74*M74 -> 0 | Q74: =(M74/SUM($M$8:$M$30,$M$32:$M$43,$M$45:$M$56,$M$58:$M$69,$M$71:$M$82,$M$84:$M$95,$M$97:$M$108,$M$110:$M$121,$M$123:$M$134))*$V$5 -> 0 | R74: =P74-Q74 -> 0 | S74: =IF(R74>0,R74/$S$6,R74) -> 0
B75: Knee Wall (Inside Shower Face) | M75: =L75*(1+$M$6) -> 0 | N75: SF | O75: =IF(AND($C75<>"",$D75<>"",$E75<>""),IF(COUNTIFS(TileTable[Section],$C75,TileTable[Level],$D75,TileTable[Item_Name],$E75)>0,SUMIFS(TileTable[Olsen_Cost],TileTable[Section],$C75,TileTable[Level],$D75,TileTable[Item_Name],$E75),""),"0") -> 0 | P75: =O75*M75 -> 0 | Q75: =(M75/SUM($M$8:$M$30,$M$32:$M$43,$M$45:$M$56,$M$58:$M$69,$M$71:$M$82,$M$84:$M$95,$M$97:$M$108,$M$110:$M$121,$M$123:$M$134))*$V$5 -> 0 | R75: =P75-Q75 -> 0 | S75: =IF(R75>0,R75/$S$6,R75) -> 0
B76: Knee Wall (Outside Shower Face) | M76: =L76*(1+$M$6) -> 0 | N76: SF | O76: =IF(AND($C76<>"",$D76<>"",$E76<>""),IF(COUNTIFS(TileTable[Section],$C76,TileTable[Level],$D76,TileTable[Item_Name],$E76)>0,SUMIFS(TileTable[Olsen_Cost],TileTable[Section],$C76,TileTable[Level],$D76,TileTable[Item_Name],$E76),""),"0") -> 0 | P76: =O76*M76 -> 0 | Q76: =(M76/SUM($M$8:$M$30,$M$32:$M$43,$M$45:$M$56,$M$58:$M$69,$M$71:$M$82,$M$84:$M$95,$M$97:$M$108,$M$110:$M$121,$M$123:$M$134))*$V$5 -> 0 | R76: =P76-Q76 -> 0 | S76: =IF(R76>0,R76/$S$6,R76) -> 0
B77: Knee Wall Cap | C77: Knee Wall Cap | D77: Level 1 | M77: =L77*(1+$M$6) -> 0 | N77: SF | O77: =IF(AND($C77<>"",$D77<>"",$E77<>""),IF(COUNTIFS(TileTable[Section],$C77,TileTable[Level],$D77,TileTable[Item_Name],$E77)>0,SUMIFS(TileTable[Olsen_Cost],TileTable[Section],$C77,TileTable[Level],$D77,TileTable[Item_Name],$E77),""),"0") -> 0 | P77: =O77*M77 -> 0 | Q77: =(M77/SUM($M$8:$M$30,$M$32:$M$43,$M$45:$M$56,$M$58:$M$69,$M$71:$M$82,$M$84:$M$95,$M$97:$M$108,$M$110:$M$121,$M$123:$M$134))*$V$5 -> 0 | R77: =P77-Q77 -> 0 | S77: =IF(R77>0,R77/$S$6,R77) -> 0
B78: Sill | C78: Sill | D78: Level 1 | M78: =L78*(1+$M$6) -> 0 | N78: SF | O78: =IF(AND($C78<>"",$D78<>"",$E78<>""),IF(COUNTIFS(TileTable[Section],$C78,TileTable[Level],$D78,TileTable[Item_Name],$E78)>0,SUMIFS(TileTable[Olsen_Cost],TileTable[Section],$C78,TileTable[Level],$D78,TileTable[Item_Name],$E78),""),"0") -> 0 | P78: =O78*M78 -> 0 | Q78: =(M78/SUM($M$8:$M$30,$M$32:$M$43,$M$45:$M$56,$M$58:$M$69,$M$71:$M$82,$M$84:$M$95,$M$97:$M$108,$M$110:$M$121,$M$123:$M$134))*$V$5 -> 0 | R78: =P78-Q78 -> 0 | S78: =IF(R78>0,R78/$S$6,R78) -> 0
B79: Curb | C79: Curb | D79: Level 1 | M79: =L79*(1+$M$6) -> 0 | N79: SF | O79: =IF(AND($C79<>"",$D79<>"",$E79<>""),IF(COUNTIFS(TileTable[Section],$C79,TileTable[Level],$D79,TileTable[Item_Name],$E79)>0,SUMIFS(TileTable[Olsen_Cost],TileTable[Section],$C79,TileTable[Level],$D79,TileTable[Item_Name],$E79),""),"0") -> 0 | P79: =O79*M79 -> 0 | Q79: =(M79/SUM($M$8:$M$30,$M$32:$M$43,$M$45:$M$56,$M$58:$M$69,$M$71:$M$82,$M$84:$M$95,$M$97:$M$108,$M$110:$M$121,$M$123:$M$134))*$V$5 -> 0 | R79: =P79-Q79 -> 0 | S79: =IF(R79>0,R79/$S$6,R79) -> 0
M80: =L80*(1+$M$6) -> 0 | N80: SF | O80: =IF(AND($C80<>"",$D80<>"",$E80<>""),IF(COUNTIFS(TileTable[Section],$C80,TileTable[Level],$D80,TileTable[Item_Name],$E80)>0,SUMIFS(TileTable[Olsen_Cost],TileTable[Section],$C80,TileTable[Level],$D80,TileTable[Item_Name],$E80),""),"0") -> 0 | P80: =O80*M80 -> 0 | Q80: =(M80/SUM($M$8:$M$30,$M$32:$M$43,$M$45:$M$56,$M$58:$M$69,$M$71:$M$82,$M$84:$M$95,$M$97:$M$108,$M$110:$M$121,$M$123:$M$134))*$V$5 -> 0 | R80: =P80-Q80 -> 0 | S80: =IF(R80>0,R80/$S$6,R80) -> 0
B81: Special Instructions: | N81: =IF(AND($C81<>"",$D81<>"",$E81<>""),IF(COUNTIFS(TileTable[Section],$C81,TileTable[Level],$D81,TileTable[Item_Name],$E81)>0,SUMIFS(TileTable[Olsen_Cost],TileTable[Section],$C81,TileTable[Level],$D81,TileTable[Item_Name],$E81),""),"")
B82: Niche Width (in): | C82: 0 | D82: Height (in): | E82: 0 | F82: Total Niche Area | G82: =IF(C82=0,0,((C82+8)*(E82+8))/144) -> 0 | H82: SF | N82: =IF(AND($C82<>"",$D82<>"",$E82<>""),IF(COUNTIFS(TileTable[Section],$C82,TileTable[Level],$D82,TileTable[Item_Name],$E82)>0,SUMIFS(TileTable[Olsen_Cost],TileTable[Section],$C82,TileTable[Level],$D82,TileTable[Item_Name],$E82),""),"") | P82: *HO Pays: | S82: =SUM(S71:S81) -> 0
B83: Bathroom #5
B84: Shower Floor Pan | C84: Floor Tile | M84: =L84*(1+$M$6) -> 0 | N84: SF | O84: =IF(AND($C84<>"",$D84<>"",$E84<>""),IF(COUNTIFS(TileTable[Section],$C84,TileTable[Level],$D84,TileTable[Item_Name],$E84)>0,SUMIFS(TileTable[Olsen_Cost],TileTable[Section],$C84,TileTable[Level],$D84,TileTable[Item_Name],$E84),""),"0") -> 0 | P84: =O84*M84 -> 0 | Q84: =(M84/SUM($M$8:$M$30,$M$32:$M$43,$M$45:$M$56,$M$58:$M$69,$M$71:$M$82,$M$84:$M$95,$M$97:$M$108,$M$110:$M$121,$M$123:$M$134))*$V$5 -> 0 | R84: =P84-Q84 -> 0 | S84: =IF(R84>0,R84/$S$6,R84) -> 0
B85: Shower Walls (8') | M85: =L85*(1+$M$6) -> 0 | N85: SF | O85: =IF(AND($C85<>"",$D85<>"",$E85<>""),IF(COUNTIFS(TileTable[Section],$C85,TileTable[Level],$D85,TileTable[Item_Name],$E85)>0,SUMIFS(TileTable[Olsen_Cost],TileTable[Section],$C85,TileTable[Level],$D85,TileTable[Item_Name],$E85),""),"0") -> 0 | P85: =O85*M85 -> 0 | Q85: =(M85/SUM($M$8:$M$30,$M$32:$M$43,$M$45:$M$56,$M$58:$M$69,$M$71:$M$82,$M$84:$M$95,$M$97:$M$108,$M$110:$M$121,$M$123:$M$134))*$V$5 -> 0 | R85: =P85-Q85 -> 0 | S85: =IF(R85>0,R85/$S$6,R85) -> 0
B86: (+) Shower Walls to Ceiling | M86: =L86*(1+$M$6) -> 0 | N86: SF | O86: =IF(AND($C86<>"",$D86<>"",$E86<>""),IF(COUNTIFS(TileTable[Section],$C86,TileTable[Level],$D86,TileTable[Item_Name],$E86)>0,SUMIFS(TileTable[Olsen_Cost],TileTable[Section],$C86,TileTable[Level],$D86,TileTable[Item_Name],$E86),""),"0") -> 0 | P86: =O86*M86 -> 0 | Q86: =(M86/SUM($M$8:$M$30,$M$32:$M$43,$M$45:$M$56,$M$58:$M$69,$M$71:$M$82,$M$84:$M$95,$M$97:$M$108,$M$110:$M$121,$M$123:$M$134))*$V$5 -> 0 | R86: =P86-Q86 -> 0 | S86: =IF(R86>0,R86/$S$6,R86) -> 0
B87: Shower Niche | L87: =G95 -> 0 | M87: =L87*(1+$M$6) -> 0 | N87: SF | O87: =IF(AND($C87<>"",$D87<>"",$E87<>""),IF(COUNTIFS(TileTable[Section],$C87,TileTable[Level],$D87,TileTable[Item_Name],$E87)>0,SUMIFS(TileTable[Olsen_Cost],TileTable[Section],$C87,TileTable[Level],$D87,TileTable[Item_Name],$E87),""),"0") -> 0 | P87: =O87*M87 -> 0 | Q87: =(M87/SUM($M$8:$M$30,$M$32:$M$43,$M$45:$M$56,$M$58:$M$69,$M$71:$M$82,$M$84:$M$95,$M$97:$M$108,$M$110:$M$121,$M$123:$M$134))*$V$5 -> 0 | R87: =P87-Q87 -> 0 | S87: =IF(R87>0,R87/$S$6,R87) -> 0
B88: Knee Wall (Inside Shower Face) | M88: =L88*(1+$M$6) -> 0 | N88: SF | O88: =IF(AND($C88<>"",$D88<>"",$E88<>""),IF(COUNTIFS(TileTable[Section],$C88,TileTable[Level],$D88,TileTable[Item_Name],$E88)>0,SUMIFS(TileTable[Olsen_Cost],TileTable[Section],$C88,TileTable[Level],$D88,TileTable[Item_Name],$E88),""),"0") -> 0 | P88: =O88*M88 -> 0 | Q88: =(M88/SUM($M$8:$M$30,$M$32:$M$43,$M$45:$M$56,$M$58:$M$69,$M$71:$M$82,$M$84:$M$95,$M$97:$M$108,$M$110:$M$121,$M$123:$M$134))*$V$5 -> 0 | R88: =P88-Q88 -> 0 | S88: =IF(R88>0,R88/$S$6,R88) -> 0
B89: Knee Wall (Outside Shower Face) | M89: =L89*(1+$M$6) -> 0 | N89: SF | O89: =IF(AND($C89<>"",$D89<>"",$E89<>""),IF(COUNTIFS(TileTable[Section],$C89,TileTable[Level],$D89,TileTable[Item_Name],$E89)>0,SUMIFS(TileTable[Olsen_Cost],TileTable[Section],$C89,TileTable[Level],$D89,TileTable[Item_Name],$E89),""),"0") -> 0 | P89: =O89*M89 -> 0 | Q89: =(M89/SUM($M$8:$M$30,$M$32:$M$43,$M$45:$M$56,$M$58:$M$69,$M$71:$M$82,$M$84:$M$95,$M$97:$M$108,$M$110:$M$121,$M$123:$M$134))*$V$5 -> 0 | R89: =P89-Q89 -> 0 | S89: =IF(R89>0,R89/$S$6,R89) -> 0
B90: Knee Wall Cap | C90: Knee Wall Cap | D90: Level 1 | M90: =L90*(1+$M$6) -> 0 | N90: SF | O90: =IF(AND($C90<>"",$D90<>"",$E90<>""),IF(COUNTIFS(TileTable[Section],$C90,TileTable[Level],$D90,TileTable[Item_Name],$E90)>0,SUMIFS(TileTable[Olsen_Cost],TileTable[Section],$C90,TileTable[Level],$D90,TileTable[Item_Name],$E90),""),"0") -> 0 | P90: =O90*M90 -> 0 | Q90: =(M90/SUM($M$8:$M$30,$M$32:$M$43,$M$45:$M$56,$M$58:$M$69,$M$71:$M$82,$M$84:$M$95,$M$97:$M$108,$M$110:$M$121,$M$123:$M$134))*$V$5 -> 0 | R90: =P90-Q90 -> 0 | S90: =IF(R90>0,R90/$S$6,R90) -> 0
B91: Sill | C91: Sill | D91: Level 1 | M91: =L91*(1+$M$6) -> 0 | N91: SF | O91: =IF(AND($C91<>"",$D91<>"",$E91<>""),IF(COUNTIFS(TileTable[Section],$C91,TileTable[Level],$D91,TileTable[Item_Name],$E91)>0,SUMIFS(TileTable[Olsen_Cost],TileTable[Section],$C91,TileTable[Level],$D91,TileTable[Item_Name],$E91),""),"0") -> 0 | P91: =O91*M91 -> 0 | Q91: =(M91/SUM($M$8:$M$30,$M$32:$M$43,$M$45:$M$56,$M$58:$M$69,$M$71:$M$82,$M$84:$M$95,$M$97:$M$108,$M$110:$M$121,$M$123:$M$134))*$V$5 -> 0 | R91: =P91-Q91 -> 0 | S91: =IF(R91>0,R91/$S$6,R91) -> 0
B92: Curb | C92: Curb | D92: Level 1 | M92: =L92*(1+$M$6) -> 0 | N92: SF | O92: =IF(AND($C92<>"",$D92<>"",$E92<>""),IF(COUNTIFS(TileTable[Section],$C92,TileTable[Level],$D92,TileTable[Item_Name],$E92)>0,SUMIFS(TileTable[Olsen_Cost],TileTable[Section],$C92,TileTable[Level],$D92,TileTable[Item_Name],$E92),""),"0") -> 0 | P92: =O92*M92 -> 0 | Q92: =(M92/SUM($M$8:$M$30,$M$32:$M$43,$M$45:$M$56,$M$58:$M$69,$M$71:$M$82,$M$84:$M$95,$M$97:$M$108,$M$110:$M$121,$M$123:$M$134))*$V$5 -> 0 | R92: =P92-Q92 -> 0 | S92: =IF(R92>0,R92/$S$6,R92) -> 0
M93: =L93*(1+$M$6) -> 0 | N93: SF | O93: =IF(AND($C93<>"",$D93<>"",$E93<>""),IF(COUNTIFS(TileTable[Section],$C93,TileTable[Level],$D93,TileTable[Item_Name],$E93)>0,SUMIFS(TileTable[Olsen_Cost],TileTable[Section],$C93,TileTable[Level],$D93,TileTable[Item_Name],$E93),""),"0") -> 0 | P93: =O93*M93 -> 0 | Q93: =(M93/SUM($M$8:$M$30,$M$32:$M$43,$M$45:$M$56,$M$58:$M$69,$M$71:$M$82,$M$84:$M$95,$M$97:$M$108,$M$110:$M$121,$M$123:$M$134))*$V$5 -> 0 | R93: =P93-Q93 -> 0 | S93: =IF(R93>0,R93/$S$6,R93) -> 0
B94: Special Instructions: | N94: =IF(AND($C94<>"",$D94<>"",$E94<>""),IF(COUNTIFS(TileTable[Section],$C94,TileTable[Level],$D94,TileTable[Item_Name],$E94)>0,SUMIFS(TileTable[Olsen_Cost],TileTable[Section],$C94,TileTable[Level],$D94,TileTable[Item_Name],$E94),""),"")
B95: Niche Width (in): | C95: 0 | D95: Height (in): | E95: 0 | F95: Total Niche Area | G95: =IF(C95=0,0,((C95+8)*(E95+8))/144) -> 0 | H95: SF | N95: =IF(AND($C95<>"",$D95<>"",$E95<>""),IF(COUNTIFS(TileTable[Section],$C95,TileTable[Level],$D95,TileTable[Item_Name],$E95)>0,SUMIFS(TileTable[Olsen_Cost],TileTable[Section],$C95,TileTable[Level],$D95,TileTable[Item_Name],$E95),""),"") | P95: *HO Pays: | S95: =SUM(S84:S94) -> 0
B96: Bathroom #6
B97: Shower Floor Pan | C97: Floor Tile | M97: =L97*(1+$M$6) -> 0 | N97: SF | O97: =IF(AND($C97<>"",$D97<>"",$E97<>""),IF(COUNTIFS(TileTable[Section],$C97,TileTable[Level],$D97,TileTable[Item_Name],$E97)>0,SUMIFS(TileTable[Olsen_Cost],TileTable[Section],$C97,TileTable[Level],$D97,TileTable[Item_Name],$E97),""),"0") -> 0 | P97: =O97*M97 -> 0 | Q97: =(M97/SUM($M$8:$M$30,$M$32:$M$43,$M$45:$M$56,$M$58:$M$69,$M$71:$M$82,$M$84:$M$95,$M$97:$M$108,$M$110:$M$121,$M$123:$M$134))*$V$5 -> 0 | R97: =P97-Q97 -> 0 | S97: =IF(R97>0,R97/$S$6,R97) -> 0
B98: Shower Walls (8') | M98: =L98*(1+$M$6) -> 0 | N98: SF | O98: =IF(AND($C98<>"",$D98<>"",$E98<>""),IF(COUNTIFS(TileTable[Section],$C98,TileTable[Level],$D98,TileTable[Item_Name],$E98)>0,SUMIFS(TileTable[Olsen_Cost],TileTable[Section],$C98,TileTable[Level],$D98,TileTable[Item_Name],$E98),""),"0") -> 0 | P98: =O98*M98 -> 0 | Q98: =(M98/SUM($M$8:$M$30,$M$32:$M$43,$M$45:$M$56,$M$58:$M$69,$M$71:$M$82,$M$84:$M$95,$M$97:$M$108,$M$110:$M$121,$M$123:$M$134))*$V$5 -> 0 | R98: =P98-Q98 -> 0 | S98: =IF(R98>0,R98/$S$6,R98) -> 0
B99: (+) Shower Walls to Ceiling | M99: =L99*(1+$M$6) -> 0 | N99: SF | O99: =IF(AND($C99<>"",$D99<>"",$E99<>""),IF(COUNTIFS(TileTable[Section],$C99,TileTable[Level],$D99,TileTable[Item_Name],$E99)>0,SUMIFS(TileTable[Olsen_Cost],TileTable[Section],$C99,TileTable[Level],$D99,TileTable[Item_Name],$E99),""),"0") -> 0 | P99: =O99*M99 -> 0 | Q99: =(M99/SUM($M$8:$M$30,$M$32:$M$43,$M$45:$M$56,$M$58:$M$69,$M$71:$M$82,$M$84:$M$95,$M$97:$M$108,$M$110:$M$121,$M$123:$M$134))*$V$5 -> 0 | R99: =P99-Q99 -> 0 | S99: =IF(R99>0,R99/$S$6,R99) -> 0
B100: Shower Niche | L100: =G108 -> 0 | M100: =L100*(1+$M$6) -> 0 | N100: SF | O100: =IF(AND($C100<>"",$D100<>"",$E100<>""),IF(COUNTIFS(TileTable[Section],$C100,TileTable[Level],$D100,TileTable[Item_Name],$E100)>0,SUMIFS(TileTable[Olsen_Cost],TileTable[Section],$C100,TileTable[Level],$D100,TileTable[Item_Name],$E100),""),"0") -> 0 | P100: =O100*M100 -> 0 | Q100: =(M100/SUM($M$8:$M$30,$M$32:$M$43,$M$45:$M$56,$M$58:$M$69,$M$71:$M$82,$M$84:$M$95,$M$97:$M$108,$M$110:$M$121,$M$123:$M$134))*$V$5 -> 0 | R100: =P100-Q100 -> 0 | S100: =IF(R100>0,R100/$S$6,R100) -> 0
B101: Knee Wall (Inside Shower Face) | M101: =L101*(1+$M$6) -> 0 | N101: SF | O101: =IF(AND($C101<>"",$D101<>"",$E101<>""),IF(COUNTIFS(TileTable[Section],$C101,TileTable[Level],$D101,TileTable[Item_Name],$E101)>0,SUMIFS(TileTable[Olsen_Cost],TileTable[Section],$C101,TileTable[Level],$D101,TileTable[Item_Name],$E101),""),"0") -> 0 | P101: =O101*M101 -> 0 | Q101: =(M101/SUM($M$8:$M$30,$M$32:$M$43,$M$45:$M$56,$M$58:$M$69,$M$71:$M$82,$M$84:$M$95,$M$97:$M$108,$M$110:$M$121,$M$123:$M$134))*$V$5 -> 0 | R101: =P101-Q101 -> 0 | S101: =IF(R101>0,R101/$S$6,R101) -> 0
...

Sheet Tile Product Lists
A1: Tile Section List | C1: Tile_Level_Kitchen_Backsplash | D1: Tile_Level_Floor_Tile | E1: Tile_Level_Listel | F1: Tile_Level_Shower_Pan_Tile | G1: Tile_Level_Shower_Tub_Wall_Tile | H1: Tile_Level_Sill | I1: Tile_Level_Knee_Wall_Cap | J1: Tile_Level_Curb | K1: Tile_Level_Carpet | L1: Tile_Level_LVP | M1: Tile_Level_Wood | P1: Tile_Product_Kitchen_Backsplash_Level_1 | Q1: Tile_Product_Kitchen_Backsplash_Level_2 | R1: Tile_Product_Kitchen_Backsplash_Level_3 | S1: Tile_Product_Kitchen_Backsplash_Level_4 | T1: Tile_Product_Kitchen_Backsplash_Level_5 | U1: Tile_Product_Kitchen_Backsplash_Level_6 | V1: Tile_Product_Kitchen_Backsplash_Level_7 | W1: Tile_Product_Kitchen_Backsplash_Level_8 | X1: Tile_Product_Kitchen_Backsplash_Level_9 | Y1: Tile_Product_Floor_Tile_Level_1 | Z1: Tile_Product_Floor_Tile_Level_2 | AA1: Tile_Product_Floor_Tile_Level_3 | AB1: Tile_Product_Floor_Tile_Level_4 | AC1: Tile_Product_Floor_Tile_Level_5 | AD1: Tile_Product_Floor_Tile_Level_6 | AE1: Tile_Product_Floor_Tile_Level_7 | AF1: Tile_Product_Floor_Tile_Level_8 | AG1: Tile_Product_Floor_Tile_Level_9 | AH1: Tile_Product_Listel_Level_1 | AI1: Tile_Product_Listel_Level_2 | AJ1: Tile_Product_Listel_Level_3 | AK1: Tile_Product_Listel_Level_4 | AL1: Tile_Product_Listel_Level_5 | AM1: Tile_Product_Shower_Pan_Tile_Level_1 | AN1: Tile_Product_Shower_Pan_Tile_Level_2 | AO1: Tile_Product_Shower_Pan_Tile_Level_3 | AP1: Tile_Product_Shower_Pan_Tile_Level_4 | AQ1: Tile_Product_Shower_Pan_Tile_Level_5 | AR1: Tile_Product_Shower_Tub_Wall_Tile_Level_1 | AS1: Tile_Product_Shower_Tub_Wall_Tile_Level_2 | AT1: Tile_Product_Shower_Tub_Wall_Tile_Level_3 | AU1: Tile_Product_Shower_Tub_Wall_Tile_Level_4 | AV1: Tile_Product_Shower_Tub_Wall_Tile_Level_5 | AW1: Tile_Product_Shower_Tub_Wall_Tile_Level_6 | AX1: Tile_Product_Shower_Tub_Wall_Tile_Level_7 | AY1: Tile_Product_Shower_Tub_Wall_Tile_Level_8 | AZ1: Tile_Product_Shower_Tub_Wall_Tile_Level_9 | BA1: Tile_Product_Sill_Level_1 | BB1: Tile_Product_Knee_Wall_Cap_Level_1 | BC1: Tile_Product_Curb_Level_1 | BD1: Tile_Product_Carpet_Level_1 | BE1: Tile_Product_LVP_Level_1 | BF1: Tile_Product_Wood_Level_1
A2: Kitchen Backsplash | C2: Level 1 | D2: Level 1 | E2: Level 1 | F2: Level 1 | G2: Level 1 | H2: Level 1 | I2: Level 1 | J2: Level 1 | K2: Level 1 | L2: Level 1 | M2: Level 1 | P2: Ceramic Subway BG 3" x 6" - Running Bond (1/2 offset) | Q2: Ceramic Subway 4" x 16" - 1/3 offest or stack bond- w/ 3x10 BN | R2: Ceramic Subway BG Beveled 4" x 10" - 1/3 offset or stack bond - w/ 3x10 BN | S2: Broadway 3" x 12" - Running Bond (1/2 offset) or Stack Bond w/Jolly | T2: Beveled Brick 2" x 4" Mosaic Horizontal straight w/ Jolly | U2: Aran 5/8" glass/stone stack mosaic - 12" x12" sheet | V2: 3D Hex Recycled Glass - Mosaic - 12" x 12" Sheet Straight w/Jolly | W2: Marble Slide - Diana Royal Polished -11" x 17" - Straight w/Jolly | X2: Arabesque BV/Ice/Wht polished marble 12" x 14" Mosaic Straight w/Jolly | Y2: Boston 18" x 18" - Straight (no offset) | Z2: Cambridge 12" x 24" - Stack Bond or 1/3 Offset | AA2: Emilia 12" x 24" - Stack Bond or 1/3 Offset | AB2: Alliance- 12" x 24" - Stack Bond or 1/3 Offset | AC2: Annora 12" x 24" - Stack Bond or 1/3 Offset | AD2: Absolute Slate 12" x 24" - Stack Bond or 1/3 Offset | AE2: Casblanca Hex 8" x 9" - Straight (no offset) | AF2: Masterstone Polished or Matte- 32"x32" Straight (no offset) | AG2: Carenza 24" X 48" Stack Bond or 1/3 Offset | AH2: Comet Stratos - White Marble/ Glass Blend - 4" x 12" listel - (1/3 sheet) | AI2: Aran - 5/8" glass/stone stack mosaic - 4" x 12" listel - (1/3 sheet) | AJ2: Glossy Glass 2" x 4" Offset Mosaic 4" x 12" - (1/3 Sheet) | AK2: Gemstone Mosaic 4" x 12" Listel | AL2: LH Stairs 2"x10" Stacked or Offset 4"x10" | AM2: Boston 2" x 2"- Straight | AN2: Cambridge 2" x 2" - Stack Bond or 1/3 Offset | AO2: Alliance - 2" x 2" Mosaic 12" x 12" sheet - straight | AP2: Absolute Slate - 2" x 2" Mosaic - Straight | AQ2: 3D Hex Recycled Glass Mosaic 11" x 13" sheet | AR2: Boston 12" x 12" - Straight (no offset) | AS2: Cambridge 12" x 24" - Stack Bond or 1/3 Offset | AT2: Ceramic Bright 3" x 6" - Running Bond | AU2: Alliance- 12" x 24" - Stack Bond or 1/3 Offset | AV2: Annora 12" x 24" - Stack Bond or 1/3 Offset | AW2: Absolute Slate 12" x 24" - Stack Bond or 1/3 Offset | AX2: Arctic White Polished- 24" x 24" - Straight (no offset) | AY2: Masterstone Polished or Matte- 32"x32" Straight (no offset) | AZ2: Carenza 24" X 48" Stack Bond or 1/3 Offset | BA2: Elustra White | BB2: Elustra White | BC2: Elustra White | BD2: Carpet Product 1 | BE2: LVP Product 1 | BF2: Campbell Creek
A3: Floor Tile | C3: Level 2 | D3: Level 2 | E3: Level 2 | F3: Level 2 | G3: Level 2 | Q3: Ceramic Subway BG Beveled 3" x 6" - Running Bond (1/2 offset) - w/2x6 BN | R3: Maiolica 3" x 6" - Stack Bond or Running Bond w/ 3x6 BN | S3: Casablanca 8" x 8" - Straight w/Jolly | T3: Diamond Herringbone BG Mosaic 12" x 12" sheet - w/Jolly | U3: Autumn Mist - Random - Linear Glass Blend Mosaic - 12" x 12" Sheet | V3: Arrow Gold - Mosaic - 11.75" x 12" Sheet Straight w/Jolly | W3: Marble Slide - Veonra polished 11" x 17" Straight w/Jolly | X3: Arabesque Bianco Venato Dol. pol marble 12" x 14" Mosaic Straight w/Jolly | Y3: Ferrara 18" X 18" - Straight (no offset) | Z3: Carrara 12" x 24" Stack Bond or 1/3 Offset | AA3: Madreas Nogal 6" x 24" - 1/3 Offset | AB3: Bartons Creek 8" x 33" - Stack Bond or 1/3 Offset | AC3: Carenza Matte - 24" x 24" - Straight (no offset) | AD3: Apini Hex- 9"x10.5" Straight (no offset) | AE3: Cottage 9" x 40" - Stack Bond or 1/3 Offset | AF3: Stauaro Polish or Matte- 32"x32" Straight (no offset) | AG3: Era 24" X 48" Stack Bond or 1/3 Offset | AH3: Crackle Glass Slate - 1" x 2" Brick Mosaic - 3x12 listel - (1/4 sheet) | AI3: Autumn Mist Random Linear Glass Mosaic - 4x12" listel - (1/3 sheet) | AJ3: Midpark Random Rainstorm 2" Mosaic - 4" x 12" listel (1/3 Sheet) | AK3: Lighthouse 2"x10" stacked or offset 4"x10" | AM3: Ferrara 2" X 2" - Straight | AN3: Carrara 2" x 2" Stack Bond or 1/3 Offset | AO3: Beach 2" x 2" Mosaic 12" x 12" sheet - straight | AP3: Carenza -Statuary unpolished - 2" x 2" Mosaic - Straight | AQ3: Aran 5/8" glass/stone stack mosaic - 12" x12" sheet | AR3: Ferrara 12" X 12" Straight (no offset) | AS3: Carrara 12" x 24" Stack Bond or 1/3 Offset | AT3: Ceramic Bright 6" x 6" - Straight (no offset) | AU3: Beach 11" x 22" - Stack Bond or 1/3 Offset | AV3: Aura Dolce Wave 6" x 18" - Stack Bond or 1/3 Offset | AW3: Acrtic White 12" x 24" - Stack Bond or 1/3 offset | AX3: Broadway 3" x 12" - Running Bond (1/2 offset) or Stack Bond | AY3: Stauaro Polish or Matte- 32"x32" Straight (no offset) | AZ3: Era 24" X 48" Stack Bond or 1/3 Offset | BA3: Elustra Bisque | BB3: Elustra Bisque | BC3: Elustra Bisque | BF3: Essence
A4: Listel | C4: Level 3 | D4: Level 3 | E4: Level 3 | F4: Level 3 | G4: Level 3 | S4: Eden 3" x 11" - Stack Bond or Running Bond w/ Jolly | T4: Herringbone BG Mosaic -Antique White 12" x 12" sheet - w/Jolly | U4: Comet White Stone/Glass Blend Mosaic - 12" x 12" Sheet | V4: Baltia Mini-brick white - Mosaic - 12" x 12" Sheet Straight w/Jolly | W4: Midpark Random 2" Mosaic - Rainstorm - 12" x 12" sheet Straight w/Jolly | X4: Chevron polished marble 13" x 12" Mosaic Straight w/Jolly | Y4: Travertino 18" x 18" - Straight (no offset) | Z4: Skyline 18" x 18" - Straight | AA4: Palma 12" x 24" - Stack Bond or 1/3 Offset | AB4: Beach 22" x 22" - Straight (no offset) | AC4: Carenza Matte- 12 x 24" - Stack Bond or 1/3 Offset | AD4: Arctic White Matte- 24" x 24" - Straight (no offset) | AE4: Marble Folio 24" x 24" Straight (no offset) | AG4: Pro Matte 24" X 48" Stack Bond or 1/3 Offset | AH4: Crackle Glass White Pearl - 1" x 2" Brick Mosaic 3x12 listel - (1/4 sheet) | AI4: Baltia Mini-brick white Mosaic 4x12 Listel - (1/3 sheet) | AJ4: Raine Random Linear Mosaic 6" x 11" listel - (1/2 sheet) | AK4: Shaved pebble 12" x 12" sheet- stock colors | AM4: Travertino 2" x 2" - Straight | AN4: Skyline 2" x 2" - Straight | AO4: Brescia 2" x 2" Mosaic 12" x 12" sheet - straight | AP4: Charisma Naturale 2" x 2" Mosaic 12" x 12" sheet - straight | AQ4: GEMSTONE MOSAIC - 11.25" x 11.87" | AR4: Travertino 12" x 12" - Straight (no offset) | AS4: Skyline 10" x 13" - Stack Bond | AT4: Emilia 12" x 24" - Stack Bond or 1/3 Offset | AU4: Brescia 11" x 22" - Stack Bond (no offset) | AV4: Carenza Matte- 12 x 24" - Stack Bond or 1/3 Offset | AW4: Carenza 12 x 24" - Stack Bond or 1/3 Offset | AX4: Casblanca Hex 8" x 9" - Straight (no offset) | AZ4: Pro Matte 24" X 48" Stack Bond or 1/3 Offset | BA4: Eng. Botticino | BB4: Eng. Botticino | BC4: Eng. Botticino | BF4: Frontier
A5: Shower Pan Tile | C5: Level 4 | D5: Level 4 | E5: Level 4 | F5: Level 4 | G5: Level 4 | S5: Flow Hexagon 8" x 9" - Horizontal Straight w/Jolly | T5: Hexagon MG Mosaic - 12" x 12" sheet - w/Jolly | U5: Crackle Glass Slate - 1" x 2" Brick Mosaic - 12" x 12" sheet | V5: Geohex recycled glass - Mosaic - 11" x 13" Sheet Straight w/Jolly | W5: Safari Stacked- Elephant 12" x 12" Horizontal - Straight w/Jolly | X5: Fish Scale BVD polished marble 12" x 12" (.80) Mosaic Straight w/Jolly | Z5: Vancouver 18" x 18" - Straight | AA5: Skyline 12" x 24" - Stack Bond or 1/3 Offset | AB5: Brescia 22" x 22" - Straight (no offset) | AC5: Harden Valley 8" x 48" - 1/3 Offset or Random | AD5: Arctic White Polished- 24" x 24" - Straight (no offset) | AE5: Masterstone Polished or Matte- 16"x32" Stack Bond or 1/3 offset | AG5: Pro Polished 24" X 48" Stack Bond or 1/3 Offset | AH5: Crackle Glass Wood Vein - 1" x 2" Brick Mosaic 3x12 listel- (1/4 sheet) | AI5: Icicle Stratos - Calcutta & Glass Mosaic - 4x12" listel - (1/3 sheet) | AJ5: Safari Elephant Stacked 4" x 12" (1/3 sheet) | AM5: Vitra Matte 2" X 2" - Straight | AN5: Vancouver 2" x 2" - Straight | AO5: Cavatina - 2" x 2" Brick Mosaic - Straight | AP5: Hexacycle Carrara 11" x 13" sheet | AQ5: Geohex Recycled Glass Mosaic 11" x 13" sheet | AS5: Vancouver 10" x 38" - Stack Bond | AT5: Palma 12" x 24" - Stack Bond or 1/3 Offset | AU5: Ceramic Bright 4" x 16" - Running Bond | AV5: Ceramic Bright Bevel 4" x 10" - Running Bond | AW5: Carenza Matte - 24" x 24" - Straight (no offset) | AX5: Eden 3" x 11" - Stack or 1/3 Offset | AZ5: Pro Polished 24" X 48" Stack Bond or 1/3 Offset | BA5: Eng. Carrara | BB5: Eng. Carrara | BC5: Eng. Carrara
A6: Shower / Tub Wall Tile | C6: Level 5 | D6: Level 5 | E6: Level 5 | F6: Level 5 | G6: Level 5 | S6: Flow I - 3" x 12" - Stack Bond or Running Bond w/ Jolly | T6: Lantern BG Mosaic 12" x 12" sheet - w/ Jolly | U6: Crackle Glass White Pearl - 1" x 2" Brick Mosaic - 12" x 12" sheet | V6: Glossy Glass - 2" x 4" - Offset - Mosaic - 12" x 12" Sheet Straight w/Jolly | W6: Skyline - Staggered Mosaic Polished - 12" x 12" sheet - Straight w/Jolly | X6: Fish Scale Dol/Ice/Van polished marble 12" x 12" (.80) Mosaic Straight w/Jolly | AA6: Vancouver 12"x24" - Stack Bond or 1/3 Offset | AB6: Dublin- 13"x13" Straight (no offset) | AC6: Lariks- 8"x48" 1/3 Offset or Random | AD6: Carenza Polished- 12 x 24" - Stack Bond or 1/3 Offset | AE6: Nolita - 18" x 36" - Stack Bond (no offset) | AH6: Crystal Stone Pearl Linear Mosaic - 4" x 12" Listel (1/3 sheet) | AI6: Meteor Random Mosaic 4" x 12" Listel - (1/3 Sheet) | AJ6: Silver Star White Random Blend Linear Mosaic - 6" x 12" (1/2 sheet) | AO6: Empire 2" x 2" Mosaic 12" x 12" sheet - straight | AP6: Hexacycle Crema 11" x 13" sheet | AQ6: Linker White Wood Mosaic 10.8" x 10.8" sheet | AS6: Villa 10" x 13" - Stack Bond | AT6: Skyline 12" x 24" - Stack Bond or 1/3 Offset | AU6: Ceramic Bright Beveled 3" x 6" - Running Bond | AV6: Ceramic Bright Wavy 10" x 28" - Stack Bond or 1/3 Offset | AW6: Casablanca 8" x 8" - Straight (no offset) | AX6: Flow 3" x 12" Special Colors - Stack Bond or 1/3 Offset
A7: Sill | C7: Level 6 | D7: Level 6 | G7: Level 6 | S7: Flow II - 3" x 12" - Stack Bond or Running Bond w/ Jolly | T7: Penny Round BG Black Mosaic 12" x 12" sheet - w/ Jolly 5/16" | U7: Crackle Glass Wood Vein - 1" x 2" Brick Mosaic - 12" x 12" sheet | V7: Lamplight recycled glass - Mosaic - 13" x 13" Sheet Straight w/Jolly | W7: Time Grey glass/stone Mosaic 12 x 12 Straight w/Jolly | X7: Linker Mosaic - 10.8" x 10.8" sheet Straight w/Jolly | AB7: Empire 12" x 24" - Stack Bond or 1/3 Offset | AC7: Linen 12" x 24" - Stack Bond or 1/3 Offset | AD7: Carenza Polished- 24" x 24" - Straight (no offset) | AE7: Rever- 8"x48" 1/3 Offset or Random | AH7: Glass Blend Brick Mosaic 1" x 3" - Alpine - 3" x 12" Listel (1/4 sheet) | AI7: Stone/Glass Mosaic 5/8" x 5/8" - 3" X 12" Listel - Carrera (1/4 sheet) | AJ7: Skyline - Staggered Mosaic Polished - 4" x 12" listel - (1/3 sheet) | AO7: Gotham 2" x 2" Mosaic 12" x 12" sheet - straight | AP7: Hexacycle Grey 11" x 13" sheet | AQ7: Shaved pebble 12" x 12" sheet- stock colors | AT7: Vancouver 12"x24" - Stack Bond or 1/3 Offset | AU7: Crayon 4" x 12" - Running Bond | AV7: Linen 12" x 24" - Stack Bond or 1/3 Offset | AW7: Contro Iconica- 12"x24" Stack Bond or 1/3 offset | AX7: Flow Hex 8" x 9" - Straight (no offset)
A8: Knee Wall Cap | C8: Level 7 | D8: Level 7 | G8: Level 7 | S8: Flow Picket 3" x 12" - Horizontal Straight w/Jolly | T8: Penny Round BG Grey Mosaic 12" x 12" sheet -w/ Jolly 5/16" | U8: Crystal Stone Linear Mosaic Pearl - 12" x 12" - Straight | V8: Pinwheel Quartzite 12" x 12" Horizontal - Straight w/Jolly | W8: Verona Staggered Pol 5/8" x 1 1/4" Mosaic - 12" x 12" sht Straight w/Jolly | AB8: Gotham - 12" x 24" - Stack Bond or 1/3 Offset | AC8: Marmo Matte- 12"x24" Stack Bond or 1/3 offset | AD8: Casablanca 8" x 8" - Straight (no offset) | AE8: Stauaro Polish or Matte- 16"x32" Stack Bond or 1/3 offset | AH8: Kolda - 1" x 1" Stone Mosaic 3" x 12" listel - (1/4 sheet) | AI8: Time Grey Glass/Stone Mosaic 3x12 (1/4 Sheet) | AJ8: Squarecycle Grey 2x2 Mosaic - 4" x 12" listel - (1/3 sheet) | AO8: Hexagon 2" x 2" Matte Glaze Black - 12" Mosaic | AP8: Historia - 2" x 2" Mosaic 12" x 12" sheet - straight | AQ8: Verona Staggered Polished 5/8" x 1 1/4" Mosaic - 12" x 12" sheet | AU8: Dublin- 13"x13" Straight (no offset) | AV8: Marmo Matte- 12"x24" Stack Bond or 1/3 offset | AW8: Contro Iconica- 24"x24" Straight (no offset) | AX8: Flow Picket 3" x 12" - Straight (no offset)
A9: Curb | C9: Level 8 | D9: Level 8 | G9: Level 8 | S9: Maiolica Crackled 3" x 12" -Stack Bond or Running Bond w/ Jolly | T9: Penny Round BG White Mosaic 12" x 12" sheet - w/ Jolly 5/16" | U9: Elongate Hex Carrara Mosaic 12" x 13"sheet w/Jolly straight | V9: Shaved Pebbles - 12" x 12" Mosaic - Straight w/Jolly | AB9: Ibiza 12" x24" - Stack Bond or 1/3 Offset | AC9: Marmo Matte- 24"x24" Straight (no offset) | AD9: Contro Iconica- 12"x24" Stack Bond or 1/3 offset | AE9: Terra - 8" x 8" Square - straight | AH9: Pinwheel Mosaic Quartzite - 12x12 Brick Mosaic 3x12 listel - (1/4 sheet) | AJ9: Verona Staggered Polished 5/8" x 1 1/4" Mosaic - 4 x 12" (1/3 sheet) | AO9: Hexagon 2" x 2" Matte Glaze Tender Gray - 12" Mosaic | AP9: Legend II - 2" x 2" Mosaic 12" x 12" sheet - straight | AU9: Empire 12" x 24" - Stack Bond or 1/3 Offset | AV9: Masterstone Matte- 12"x24" Stack Bond or 1/3 | AW9: Flow 3" x 12" Standard Colors - Stack Bond or 1/3 Offset | AX9: Maiolica Crackled 3" x 12" - Stack Bond or 1/3 Offset
A10: Carpet | C10: Level 9 | D10: Level 9 | G10: Level 9 | S10: Maiolica Hexagon 7" x 8" - Horizontal Straight w/Jolly | T10: Tumbled Marble - 3" x 6" - Running Bond (1/2 offset) - Ivory | U10: Glass Blend Brick Mosaic 1" x 3" Alpine- - 12" x 12" Sheet | V10: Squarecycle Grey 12" x 12" sheet Straight w/Jolly | AB10: Immerse Carrara 12"x24" Stack Bond or 1/3 Offset | AC10: Masterstone Matte- 12"x24" Stack Bond or 1/3 | AD10: Contro Iconica- 24"x24" Straight (no offset) | AE10: Yukon 9" x 40" - Stack Bond or 1/3 Offset | AH10: Stone/Glass Mosaic 5/8" x 5/8" - 3" x 12" Listel -Safari (1/4 sheet) | AO10: Hexagon 2" x 2" Matte Glaze White - 12" Mosaic | AP10: Linen White - 2" x 2" Mosaic 12" x 12" sheet - straight | AU10: Gotham - 12" x 24" - Stack Bond or 1/3 Offset | AV10: Pro Matte 12" x 24" - Stack Bond or 1/3 Offset | AW10: Historia 12" x 24" - Stack Bond or 1/3 Offset | AX10: Maiolica Hex 7" x 8" - Straight (no offset)
A11: Tile | S11: Middleton Square 4" x 12" - Running (1/2 offset)or stack bond- w/ BN | T11: Tumbled Marble - 3" x 6" - Running Bond (1/2 offset) - Silver | U11: Icicle Stratos Random Linear Calcutta & Glass Mosaic - 12" x 12" Sheet | V11: Stratos Glass & Stone Mosaic - 11.65 x 11.65" sheet Straight w/Jolly | AB11: Leeds- 13"x13" Straight (no offset) | AC11: Masterstone Matte- 24"x24" Straight (no offset) | AD11: Historia -12" x 24" - Stack Bond or 1/3 Offset | AH11: Stratos Glass & Stone Mosaic 11.65"x11.65" - 3"x12" listel (1/4 sheet) | AO11: Ibiza 2" x 2" Mosaic 12" x 12" sheet - straight | AP11: Nolita - 2" x 2" Mosaic 12" x 12" sheet - straight | AU11: Ibiza 12" x24" - Stack Bond or 1/3 Offset | AV11: Pro Polished 12" x 24" - Stack Bond or 1/3 Offset | AW11: Historia 12" x 24" - Stack Bond or 1/3 Offset | AX11: Marble Folio 12" x 24" - Stack Bond or 1/3 Offset
A12: LVP | S12: Suite - 4" x 12" Running Bond (1/2 offset) or stack bond w/3x12 BN | T12: Tumbled Marble - 3" x 6" - Running Bond (1/2 offset) - Milas White | U12: Kolda 1" x 1" Stone Mosaic - Straight only | AB12: Legend II 12" x 24" - Stack Bond or 1/3 Offset | AC12: Pro Matte 12 x 24" - Stack Bond or 1/3 Offset | AD12: Laser Hex- 9.5"x10.5" Straight (no offset) | AH12: Striped Random Mosaic - 3" x 12" listel - (1/4 sheet) | AO12: Milano 2" x 2" Mosaic 12" x 12" sheet - straight | AP12: Pebblecycle Glass Mosaic 12" x 12" sheet | AU12: Immerse Carrara 12"x24" Stack Bond or 1/3 Offset | AV12: Salvador Polished or Matte- 12"x24" Stack Bond or 1/3 offset | AW12: Marmo Matte- 24"x24" Straight (no offset) | AX12: Marmo Polished- 24"x24" Straight (no offset)
A13: Vinyl | S13: Terra 8" x 8" - Straight w/ Jolly | T13: Tumbled Marble - 3" x 6" - Running Bond (1/2 offset)- Diana Royal | U13: Meteor Random Blend Mosaic - 12" x 12" sheet Straight | AB13: Lumber 6" x 24" - Stack Bond or 1/3 Offset | AC13: Pro Matte 24" x 24" - Straight (no offset) | AD13: Marble Folio- 12"x24" Stack Bond or 1/3 offset | AO13: Moscato 2" x 2" Mosaic 12" x 12" sheet - straight | AP13: Penny Round BG Black Mosaic 12" x 12" sheet - straight | AU13: Leeds- 13"x13" Straight (no offset) | AV13: Santiago Polished or Matte- 12"x24" Stack Bond or 1/3 offset | AW13: Marmo Polished- 12"x24" Stack Bond or 1/3 offset | AX13: Masterstone Polished or Matte- 16"x32" Stack Bond or 1/3 offset
A14: Cabinets | S14: Tumbled Marble 4" x 4" - Straight - Dark Walnut | U14: Pebblecycle 12" x 12" sheet w/Jolly | AB14: Madera- 9"x36" 1/3 offset or Random | AC14: Pro Polished 12" x 24" - Stack Bond or 1/3 Offset | AD14: Marmo Polished- 12"x24" Stack Bond or 1/3 offset | AO14: Octagon & Dot White 2" x 2" Matte Glaze - 12" Mosaic | AP14: Penny Round BG Grey Mosaic 12" x 12" sheet - straight | AU14: Mailoica Subway 3" x 6" - Running Bond | AV14: Stonemood Matte- 12"x24" Stack Bond or 1/3 offset | AW14: Masterstone Matte- 24"x24" Straight (no offset) | AX14: Masterstone Polished- 24"x24" Straight (no offset)
A15: Countertops | S15: Tumbled Marble 4" x 4" - Straight - Diana Royal | U15: Pennycycle 12" x 12" sheet Straight w/Jolly | AB15: Moscato 12" x 24" - Stack Bond or 1/3 Offset | AC15: Pro Polished 24" x 24" - Straight (no offset) | AD15: Marmo Polished- 24"x24" Straight (no offset) | AO15: Palma 2" x 2" Mosaic 12" x 12" sheet - straight | AP15: Penny Round BG White Mosaic 12" x 12" sheet - straight | AU15: Moscato 12" x 24" - Stack Bond or 1/3 Offset | AV15: Suite- 12" x 24" - Stack Bond or 1/3 Offset | AW15: Masterstone Polished- 12"x24" Stack Bond or 1/3 | AX15: Nolita 18" x 36" - Stack Bond (no offset)
A16: Hardware | S16: Tumbled Marble 4" x 4" - Straight - Ivory | U16: Petal Gems Gray 13X13 Mosaic sheet Straight w/Jolly | AB16: Ocean- 13"x13" Straight (no offset) | AC16: Pro max 12" x 24" - Stack Bond or 1/3 Offset | AD16: Masterstone Polished- 12"x24" Stack Bond or 1/3 | AO16: Sandstone 2" x 2" Mosaic 12" x 12" sheet - straight | AP16: Pennycycle Glass Mosaic 12" x 12" sheet | AU16: Ocean- 13"x13" Straight (no offset) | AV16: Trevi 12" x 24" - Stack Bond or 1/3 Offset | AW16: Nolita 12" x 24" - Stack Bond or 1/3 Offset | AX16: Stauaro Polish or Matte- 16"x32" Stack Bond or 1/3 offset
A17: Wood | S17: Zellige 2.5" x 16" -Stack Bond or Running Bond w/ Jolly | U17: Picket Cycle Wood Vein 14X10 Mosaic Straight w/Jolly | AB17: Sandstone 12" x 24" - Stack Bond or 1/3 Offset | AC17: Salvador Polished or Matte- 12"x24" Stack Bond or 1/3 offset | AD17: Masterstone Polished- 24"x24" Straight (no offset) | AP17: Pro Matte - 2" x 2" - Mosaic 12" x 12" sheet - straight | AU17: Sandstone 12" x 24" - Stack Bond or 1/3 Offset | AW17: Pro Matte 24" x 24" - Straight (no offset) | AX17: Stonemood Polished- 24"x24" Straight (no offset)
U18: Picket Mosaic 1" x 4" - 12" x 12" sheet Straight w/Jolly | AB18: Suite 12" x 24" - Stack Bond or 1/3 Offset | AC18: Salvador Polished or Matte- 24"x24" Straight (no offset) | AD18: Nolita 12" x 24" - Stack Bond or 1/3 Offset | AP18: Squarecycle Grey 2" x 2" Mosaic - 12" x 12" sheet | AU18: Vintage- 13"x13" Straight (no offset) | AW18: Pro Polished 24" x 24" - Straight (no offset) | AX18: Terra - 8" x 8" - Square - straight
U19: Raine Random Linear Mosaic 11.25" x 11.25" sheet - Straight w/Jolly | AB19: Valor- 6"x36" 1/3 offset or Random | AC19: Santiago Polished or Matte- 12"x24" Stack Bond or 1/3 offset | AD19: Statuaro Polished or Matte- 12"x24" Stack Bond or 1/3 offset | AP19: Stone/Glass Mosaic 5/8" x 5/8" - Carrera | AU19: Winter 8" x 24" - Running or Stack Bond | AW19: Salvador Polished or Matte- 24"x24" Straight (no offset) | AX19: Zellige 2.5" x 16" - Stack or 1/3 Offset
U20: Ripple 2" x 8" - Stack Bond or Running Bond w/Jolly | AB20: Vintage- 13"x13" Straight (no offset) | AC20: Santiago Polished or Matte- 24"x24" Straight | AD20: Stonemood Polished- 12"x24" Stack Bond or 1/3 offset | AP20: Suite - 2" x 2" Mosaic 12" x 12" sheet - straight | AW20: Santiago Polished or Matte- 24"x24" Straight
U21: Silver Star White Random Blend Linear Mosaic - 12" x 12" sh Straight w/Jolly | AB21: Voyage 8" x 33" - Stack Bond or 1/3 Offset | AC21: Stonemood Matte- 12"x24" Stack Bond or 1/3 offset | AD21: Stonemood Polished- 24"x24" Straight (no offset) | AP21: Trevi - 2" x 2" Mosaic 12" x 12" sheet - straight | AW21: Statuaro Polished or Matte- 12"x24" Stack Bond or 1/3 offset
U22: Stone/Glass Mosaic 5/8" x 5/8" - 12" x 12" sheet Straight - Safari Straight w/Jolly | AB22: Yuka 6.5" x 20" - 1/3 Offset | AC22: Stonemood Matte- 24"x24" Straight (no offset) | AD22: Suite 24" x 24" - Straight (no offset) | AP22: Tumbled Marble 4" x 4" - Diagonal - Ivory | AW22: Stonemood Matte- 24"x24" Straight (no offset)
U23: Stone/Glass Mosaic 5/8" x 5/8" - Straight only - Carrera Straight w/Jolly | AC23: Terrazzo- 24"x24" Straight (no offset) | AD23: Toledo Hex- 9.5"x10.5" Straight (no offset) | AP23: Tumbled Marble 4" x 4" - Diagonal - Diana Royal | AW23: Stonemood Polished- 12"x24" Stack Bond or 1/3 offset
U24: Striped Random Mosaic - 12" x 12" sheet Straight w/Jolly | AC24: Trevi 12" x 24" - Stack Bond or 1/3 Offset | AD24: Verso Iconica- 12"x24" Stack Bond or 1/3 Offset | AP24: Tumbled Marble 4" x 4" - Diagonal- Dark Walnut | AW24: Toledo Hex- 9.5"x10.5" Straight (no offset)
U25: Veneer Ledger Panel 6" x 24" - 1/3 offset w/Jolly or Corner | AD25: Verso Iconica- 24"x24" Straight (no offset) | AP25: Winter Stone - 2" x 2" Mosaic 12" x 12" sheet - straight | AW25: Verso Iconica- 12"x24" Stack Bond or 1/3 Offset
AD26: Waves-12"x24" Stack Bond or 1/3 offset | AW26: Verso Iconica- 24"x24" Straight (no offset)
AD27: Waves-24"x24" Straight (no offset) | AW27: Waves-12"x24" Stack Bond or 1/3 offset
AD28: Whisper 8" x 40" - Stack Bond or 1/3 Offset | AW28: Waves-24"x24" Straight (no offset)

Sheet Cabinets
A1: ='Customer Option Cover Page'!C6 -> John Doe
A2: ='Customer Option Cover Page'!C7 -> 123 avenue
A3: Budget
A11: Total | B11: =SUM(B4:B10) -> 0

Sheet Pavers
A1: ='Customer Option Cover Page'!C6 -> John Doe
A2: ='Customer Option Cover Page'!C7 -> 123 avenue
A3: Budget
A11: Total | B11: =SUM(B4:B10) -> 0

Sheet Stone
A1: ='Customer Option Cover Page'!C6 -> John Doe
A2: ='Customer Option Cover Page'!C7 -> 123 avenue
A3: Budget
A11: Total | B11: =SUM(B4:B10) -> 0

Sheet Summer Kitchen
A1: ='Customer Option Cover Page'!C6 -> John Doe
A2: ='Customer Option Cover Page'!C7 -> 123 avenue
A3: Budget
A11: Total | B11: =SUM(B4:B10) -> 0

Sheet Sheet8
A1: ='Customer Option Cover Page'!C6 -> John Doe
A2: ='Customer Option Cover Page'!C7 -> 123 avenue
A3: Budget
A11: Total | B11: =SUM(B4:B10) -> 0

Sheet Sheet9
A1: ='Customer Option Cover Page'!C6 -> John Doe
A2: ='Customer Option Cover Page'!C7 -> 123 avenue
A3: Budget
A11: Total | B11: =SUM(B4:B10) -> 0

Sheet Sheet10
A1: ='Customer Option Cover Page'!C6 -> John Doe
A2: ='Customer Option Cover Page'!C7 -> 123 avenue
A3: Budget
A11: Total | B11: =SUM(B4:B10) -> 0

Sheet Sheet11
A1: ='Customer Option Cover Page'!C6 -> John Doe
A2: ='Customer Option Cover Page'!C7 -> 123 avenue
A3: Budget
A11: Total | B11: =SUM(B4:B10) -> 0
