Workbook

Sheet Cover Page
A1: Veranda Bay Olsen Model
A2: 183 Stillwater Drive
A3: =TODAY() -> 46157
A5: Estimate | C5: Estimate File 183 Stillwater Drive
A7: Contract | C7: NA
B9: Living SF. | D9: 2961 | E9: SF
B10: Total perimiter | E10: LF
B11: Driveway sf | D11: 1925 | E11: SF
B13: Total Slab SF. | D13: =2961+957+602+178 -> 4698 | E13: SF
B14: Total all areas | D14: 4698 | E14: SF
B15: Wall heights | D15: 11 | E15: LF
B16: Tile sf floors | D16: 2961 | E16: SF
B18: Garage floor | D18: 957 | E18: SF
B19: Appx Block | D19: 6596 | E19: EA
B20: Roof Pitch | D20: 1.6

Sheet Slab
A1: =('Cover Page'!A1) -> Veranda Bay Olsen Model
A2: =('Cover Page'!A2) -> 183 Stillwater Drive
A5: Slab Material | F5: Order Date:
A6: Item | B6: Qty | C6: Unit $ | D6: Ext $
A7: D541 | B7: 160 | C7: 3.5 | D7: =C7*B7 -> 560
A8: RE540 | B8: =7+3+45+12 -> 67 | C8: 13.95 | D8: =C8*B8 -> 934.65
A9: RCE2 | B9: 100 | C9: 0.41 | D9: =C9*B9 -> 41
A10: RCE3 | B10: 50 | C10: 0.42 | D10: =C10*B10 -> 21
A11: 620-VQ | B11: 3 | C11: 72 | D11: =C11*B11 -> 216
A12: Rtape | B12: 6 | C12: 6.55 | D12: =C12*B12 -> 39.3
A13: BT6 | B13: 1 | C13: 15.7 | D13: =C13*B13 -> 15.7
C14: 7% Tax | D14: =SUM(D7:D13)*0.07 -> 127.9355
C15: Slab Material Total | D15: =SUM(D7:D14) -> 1955.5855 | E15: PO# 42
C16: Budget | D16: 2114.1
C17: Under | D17: =D16-D15 -> 158.5145
A19: Slab Concrete
A20: Location | B20: QTY | C20: Unit $ | D20: Ext $
A21: A Footers | B21: 13 | C21: 148 | D21: =C21*B21 -> 1924
A22: C Footers | B22: 3.2 | C22: 148 | D22: =C22*B22 -> 473.6
A23: F Footers | B23: 1 | C23: 148 | D23: =C23*B23 -> 148
A24: G Footers | B24: 4 | C24: 148 | D24: =C24*B24 -> 592
A25: H Footers | B25: 14 | C25: 148 | D25: =C25*B25 -> 2072
A26: J Footers | B26: 1 | C26: 148 | D26: =C26*B26 -> 148
A27: K Footers | B27: 5.3 | C27: 148 | D27: =C27*B27 -> 784.4
A28: L Footers | B28: 8.5 | C28: 148 | D28: =C28*B28 -> 1258
A29: Column Footers | B29: 3 | C29: 148 | D29: =C29*B29 -> 444
A30: Monolith | B30: 57 | C30: 148 | D30: =C30*B30 -> 8436
A31: Master Fiber | B31: =SUM(B21:B30) -> 110 | C31: 7 | D31: =C31*B31 -> 770
A32: Enviro Surcharge | B32: 11 | C32: 20 | D32: =C32*B32 -> 220
A33: Fuel Surcharge | B33: 11 | C33: 26 | D33: =C33*B33 -> 286
C34: Sales Tax 6.5% | D34: =SUM(D21:D33)*0.065 -> 1141.14
C35: Concrete Total | D35: =SUM(D21:D34) -> 18697.14 | E35: PO# 42
C36: Budget | D36: 19966.5
C37: Under | D37: =D36-D35 -> 1269.36
A39: Slab Labor
A40: Location | B40: QTY | C40: Unit $ | D40: Unit | E40: Ext $
A41: Slab | B41: 4698 | C41: 1.65 | D41: sf | E41: =C41*B41 -> 7751.7
A42: Interior Footers | B42: 37 | C42: 7.5 | D42: lf | E42: =C42*B42 -> 277.5
A43: Small Pad Column | C43: 50 | D43: ea | E43: =C43*B43 -> 0
A44: Large Pad Column | B44: 7 | C44: 75 | D44: ea | E44: =C44*B44 -> 525
A45: Xlg Pad Column | C45: 150 | D45: ea | E45: =C45*B45 -> 0
A46: AC Wall Footer | C46: 200 | D46: ea | E46: =C46*B46 -> 0
A47: Stem Wall Footer | C47: 13.5 | D47: lf | E47: =C47*B47 -> 0
A48: 2 Story stem wall footger | C48: 17.5 | D48: lf | E48: =C48*B48 -> 0
D49: Labor Total | E49: =SUM(E41:E48) -> 8554.2 | F49: PO# 10
D50: Budget | E50: 9396
D51: Under | E51: =E50-E49 -> 841.8
A53: Slab Pump
B54: QTY | C54: Unit $ | D54: Ext $
A55: 38 Meter Boom Pump 4 Hr Min | B55: 1 | C55: 700 | D55: =C55*B55 -> 700
A56: Boom Pump Time per Hour | B56: 4 | C56: 175 | D56: =C56*B56 -> 700
A57: Per Cubic Yard Pump | B57: 110 | C57: 3 | D57: =C57*B57 -> 330
A58: 8% Fuel Charge | D58: =SUM(D55:D57)*0.08 -> 138.4
C59: Pump Total | D59: =SUM(D55:D58) -> 1868.4 | E59: PO# 11
C60: Budget | D60: 1800
C61: Over | D61: =D60-D59 -> -68.4

Sheet Lintels & Sills
A1: =('Cover Page'!A1) -> Veranda Bay Olsen Model
A2: =('Cover Page'!A2) -> 183 Stillwater Drive
A4: Lintels
A5: Item | B5: Location | C5: Qty | D5: Unit $ | E5: Ext $
A7: P3-6 | B7: Bath 2, Bath 3, SK Opening | C7: 4 | D7: 29.84 | E7: =D7*C7 -> 119.36 | F7: 14
B8: Master Toilet
A9: P4-0 | B9: Garage Door, SK Hall | C9: 2 | D9: 35 | E9: =D9*C9 -> 70 | F9: 8
A11: P4-6 | B11: Laundry, Hallway, Bed 2 | C11: 10 | D11: 38.36 | E11: =D11*C11 -> 383.6 | F11: 45
B12: Bed 3, Lanai Opening
A13: P7-6 | B13: Master Bath (x2) | C13: 3 | D13: 61 | E13: =D13*C13 -> 183 | F13: 22.5
B14: Front Door
A15: P8-4 | B15: Entry Middle | C15: 1 | D15: 69 | E15: =D15*C15 -> 69 | F15: 8.333
A17: P9-4 | B17: Study | C17: 1 | D17: 79.55 | E17: =D17*C17 -> 79.55 | F17: 9.333
A19: P10-6 | B19: Entry Left/Right | C19: 3 | D19: 89.51 | E19: =D19*C19 -> 268.53 | F19: 31.5
B20: Garage Door 2
A22: P12-0 | B22: Garage Window, SK | C22: 4 | D22: 102.3 | E22: =D22*C22 -> 409.2 | F22: 48
B23: Nook, Master Window
A25: P13-4 | B25: SK Opening | C25: 1 | D25: 115 | E25: =D25*C25 -> 115 | F25: 13.33
A27: P14-0 | B27: SK Opening | C27: 1 | D27: 120 | E27: =D27*C27 -> 120 | F27: 14
A29: P17-4 | B29: Garage Door 2, SGD 1 | C29: 2 | D29: 221 | E29: =D29*C29 -> 442 | F29: 34.67
A31: P21-4 | B31: Lanai Opening | C31: 1 | D31: 280 | E31: =D31*C31 -> 280 | F31: 21.33
A32: 2x6x12 Spruce | C32: 20 | D32: 16.04 | E32: =D32*C32 -> 320.8
G33: =SUM(F7:F32) -> 269.996 | H33: 451.6
A34: Recessed Door Headers | G34: =G33/20 -> 13.4998 | H34: =451.6/20 -> 22.58 | I34: =G34+H34 -> 36.0798
A35: Item | B35: Location | C35: Qty | D35: Unit $ | E35: Ext $
A36: 6P4-0 (2680 & 2880) | B36: Garage, SK, Master | C36: 3 | D36: 35 | E36: =D36*C36 -> 105
A38: Sills
A39: Item | B39: Location | C39: Qty | D39: Unit $ | E39: Ext $
A40: WR26 1/2 | C40: 3 | D40: 21.03 | E40: =D40*C40 -> 63.09
A41: WR37 | C41: 20 | D41: 30.68 | E41: =D41*C41 -> 613.6
A42: WR74 | C42: 1 | D42: 78 | E42: =D42*C42 -> 78
A44: Miscellaneous
A45: Item | B45: Location | C45: Qty | D45: Unit $ | E45: Ext $
A46: DR98 | B46: 10' wall | C46: 104 | D46: 7.47 | E46: =D46*C46 -> 776.88
A47: DR118 | B47: 12' wall | C47: 40 | D47: 8.87 | E47: =D47*C47 -> 354.8
A48: RE540 | B48: lintels & bondbeam | C48: 37 | D48: 13.95 | E48: =D48*C48 -> 516.15 | F48: Lintel Box in feet then / 20
A49: LS | B49: Lintel | C49: 2 | D49: 14.55 | E49: =D49*C49 -> 29.1 | F49: Perimeter / 20 *1.05 | H49: Sq ft / 2000 | I49: > 2
A50: BT6 | C50: 1 | D50: 15.7 | E50: =D50*C50 -> 15.7
A51: AB8E | C51: 22 | D51: 0.87 | E51: =D51*C51 -> 19.14 | F51: Garage gets 12
A52: SQ1802 | C52: 22 | D52: 0.73 | E52: =D52*C52 -> 16.06 | F52: Same as AB8E
A53: HETA20-0 | C53: 300 | D53: 2.05 | E53: =D53*C53 -> 615 | F53: Ties truss to block | G53: Count beams
D54: 7% tax | E54: =SUM(E28:E53)*0.07 -> 297.1724
D56: Total | E56: =SUM(E7:E54) -> 6359.7324

Sheet Block
A1: =('Cover Page'!A1) -> Veranda Bay Olsen Model
A2: =('Cover Page'!A2) -> 183 Stillwater Drive
A4: Block Material
A6: Wall Height | B6: LF
A7: 8' CMU Wall
A8: 10' CMU Wall
A9: 12' CMU Wall
A10: 13'4" CMU Wall
A15: Item | B15: Qty | C15: Unit $ | D15: Ext $ | I15: Item | J15: lbs
A16: 8816 | B16: 3396 | C16: 1.75 | D16: =C16*B16 -> 5943 | E16: =B16*28 -> 95088 | I16: Sand Bag | J16: 2204
A17: 8814 | B17: 90 | C17: 2 | D17: =C17*B17 -> 180 | E17: =B17*25 -> 2250 | I17: HS Masonry Bag | J17: 40
A18: 8812 | B18: 250 | C18: 2.35 | D18: =C18*B18 -> 587.5 | E18: =B18*22 -> 5500 | I18: 8816 | J18: 28
A19: 888 | B19: 325 | C19: 1.85 | D19: =C19*B19 -> 601.25 | E19: =B19*14 -> 4550 | I19: 888 | J19: 14
A20: 8416 | B20: 72 | C20: 1.9 | D20: =C20*B20 -> 136.8 | E20: =B20*14 -> 1008
A21: 8816 bonbeam | B21: 350 | C21: 1.95 | D21: =C21*B21 -> 682.5 | E21: =B21*30 -> 10500
A22: 12" Sq Column Block | B22: 24 | C22: 2 | D22: =C22*B22 -> 48 | E22: =B22*28 -> 672
A23: 16" Sq Column Block | B23: 90 | C23: 2 | D23: =C23*B23 -> 180 | E23: =B23*30 -> 2700
A24: Sand 1 CY | B24: 6 | C24: 60 | D24: =C24*B24 -> 360 | E24: =B24*2204 -> 13224 | I24: 1 CY Sand | J24: 800 | K24: block
A25: HS Masonry Bag 70 Lb | B25: 43 | C25: 9.6 | D25: =C25*B25 -> 412.8 | E25: =B25*70 -> 3010 | I25: 1 40 lb bag HS Msonry | J25: 100 | K25: block
A26: Freigth Free Zone 6 (38,304 lbs) | B26: 4 | C26: 384.18 | D26: =C26*B26 -> 1536.72
A27: Fuel Surcharge | B27: 4 | C27: 25 | D27: =C27*B27 -> 100
A28: ED. ACT FU | B28: 4 | C28: 12 | D28: =C28*B28 -> 48
C29: 7% Tax | D29: =SUM(D16:D28)*0.07 -> 757.1599
C30: Total | D30: =SUM(D16:D29) -> 11573.73
C31: Budget
A34: Block Labor
E35: Santana | G35: Masonry Concepts
A36: Wall Height | B36: Block | C36: Courses | D36: Total | E36: Unit $ | F36: Ext $ | G36: Unit $ | H36: Ext $
A37: 56" | E37: 1.75 | F37: =E37*D37 -> 0 | G37: 2 | H37: =G37*D37 -> 0
A38: 10' | E38: 1.75 | F38: =E38*D38 -> 0 | G38: 2 | H38: =G38*D38 -> 0
A39: 12' | E39: 1.95 | F39: =E39*D39 -> 0 | G39: 2.25 | H39: =G39*D39 -> 0
A40: Drills | E40: 15 | F40: =E40*D40 -> 0
E41: Total Block Labor | F41: =SUM(F37:F40) -> 0 | H41: =SUM(H37:H40) -> 0
E42: Budget
E43: Under | F43: =F42-F41 -> 0 | H43: =H42-H41 -> 0
A46: Lintel Concrete | O46: multiplier
B47: Fill Cells | C47: Block/down | D47: Qty
A48: 6' Wall Course | C48: 9 | D48: =C48*B48 -> 0
A49: 10' wall Course | C49: 15 | D49: =C49*B49 -> 0
A50: 12' Wall Course | C50: 18 | D50: =C50*B50 -> 0
A51: 13' 4" Wall Course | C51: 20 | D51: =C51*B51 -> 0
A52: Lania 12 sq column | C52: 15 | D52: =C52*B52 -> 0 | J52: CY | L52: CF
J53: 1 | K53: = | L53: 27 | N53: =J53/L53 -> 0.037037037
A54: Lintel | B54: SF | C54: LF | D54: CY
A55: 7.625 X 7.625 | B55: 0.403 | D55: =C55*B55*0.03704 -> 0 | J55: CI | L55: CF
A56: 8x20 | B56: 1.111 | D56: =C56*B56*0.03704 -> 0
A57: 8x24 | B57: 1.333 | D57: =C57*B57*0.03704 -> 0 | J57: 1728 | K57: = | L57: 1
A58: Block | B58: CY Fill | C58: Qty | D58: CY
A59: 888 | B59: 0.006 | C59: =SUM(D48:D51) -> 0 | D59: =C59*B59 -> 0
A60: 8816 Bondbeam | B60: 0.014 | D60: =C60*B60 -> 0
A61: 12812 Column block | B61: 0.015 | D61: =C61*B61 -> 0
C62: Total CY | D62: =SUM(D55:D61) -> 0
A64: Titan Order | B64: QTY | C64: Unit $ | D64: Ext $
A65: BAGX8PXY 3000 #8 PM | B65: =D62/10 -> 0 | C65: 158 | D65: =C65*B65 -> 0
A66: Fuel Surcharge | B66: =D62/10 -> 0 | C66: 26 | D66: =C66*B66 -> 0
A67: Enviro Surcharge | B67: =D62/10 -> 0 | C67: 20 | D67: =C67*B67 -> 0
C68: 7% Tax | D68: =SUM(D65:D67)*0.07 -> 0
C69: Concrete Total | D69: =SUM(D65:D68) -> 0
A71: Pump Lintel
B72: Qty | C72: Unit $ | D72: Ext $
A73: 1st 10 Yards | B73: 1 | C73: 450 | D73: =C73*B73 -> 450
A74: $25/yd after 10 yards | C74: 25 | D74: =C74*B74 -> 0
A75: Boards = D541 | C75: 3 | D75: =C75*B75 -> 0
C77: Pump Lintel Labor Total | D77: =SUM(D73:D76) -> 450

Sheet Framing Material
A1: =('Cover Page'!A1) -> Veranda Bay Olsen Model
A2: =('Cover Page'!A2) -> 183 Stillwater Drive

Sheet Windows
A1: =('Cover Page'!A1) -> Veranda Bay Olsen Model
A2: =('Cover Page'!A2) -> 183 Stillwater Drive

Sheet Ext. Doors
A1: =('Cover Page'!A1) -> Veranda Bay Olsen Model
A2: =('Cover Page'!A2) -> 183 Stillwater Drive

Sheet Insulation
A1: =('Cover Page'!A1) -> Veranda Bay Olsen Model
A2: =('Cover Page'!A2) -> 183 Stillwater Drive

Sheet Drywall
A1: =('Cover Page'!A1) -> Veranda Bay Olsen Model
A2: =('Cover Page'!A2) -> 183 Stillwater Drive
A4: Material | B4: Quantity | C4: L&W
A5: 1/2 Regular 4'x12' | B5: 310 | C5: 0.415 | D5: sf | E5: =310*48*C5 -> 6175.2
A6: 5/8" Fire Rate 4' x 12' | C6: 0.495 | D6: sf
A7: Densglass 4'x8' | B7: 27 | C7: 1.225 | D7: sf | E7: =32*27*C7 -> 1058.4
A8: 1/2 Cement-Duro 4'x8' | B8: 28 | C8: 1.165 | D8: sf | E8: =32*B8*C8 -> 1043.84
A9: Ready Mix Joint Compound 4 g | B9: 45 | C9: 11.45 | D9: ea | E9: =B9*C9 -> 515.25
A10: 250 Tape | B10: 24 | C10: 2.75 | D10: ea | E10: =B10*C10 -> 66
A11: 90 minute | B11: 1 | C11: 11.9 | D11: ea | E11: =B11*C11 -> 11.9
A12: 1 1/8" Screws 10M/CTN | B12: 2 | C12: 85 | D12: ea | E12: =B12*C12 -> 170
A13: 1 1/4" Cement Sharp Wafer | C13: 35 | D13: ea
A14: 8' Metal Cornerbead - 63 per box | B14: 63 | C14: 0.285 | D14: lf | E14: =63*8*C14 -> 143.64
A15: 10' Metal Cornerbead - 50 per box | B15: 50 | C15: 0.285 | D15: lf | E15: =10*B15*C15 -> 142.5
A16: Bullnose Archway bead 3/4" x 10' 35/box | C16: 0.25 | D16: lf
A17: Plastic Bullnose bead 3/4" x 10' 35/box | C17: 0.225 | D17: lf
A18: Plastic Arch Bead 1 1/4" x 10' | C18: 0.22 | D18: lf
A19: 10' PVC Bullnose Corner - 35 per box | C19: 0.23 | D19: lf
A20: 10' Splayed PVC Bullnose Outside Corner | C20: 0.25 | D20: lf
C21: 7% Tax | E21: =SUM(E5:E20)*0.07 -> 652.8711
C22: Total | E22: =SUM(E5:E21) -> 9979.6011
C23: Budget | E23: 11000

Sheet Interior Doors & Trim
A1: =('Cover Page'!A1) -> Veranda Bay Olsen Model
A2: =('Cover Page'!A2) -> 183 Stillwater Drive
A15: Interior Doors/Trim material
A16: Interior trim
A17: CROWN MATL
A18: Attic stairs
A19: Barn door items
A20: extras trim
A21: Attic door
A22: Door Hardware
A23: Cedar shelving
A24: Beam material
A27: Trim Labor
A28: Pocket door
... A38: Beams install

Sheet Pavers
A1: =('Cover Page'!A1) -> Veranda Bay Olsen Model
A2: =('Cover Page'!A2) -> 183 Stillwater Drive

Sheet Stone
A1: =('Cover Page'!A1) -> Veranda Bay Olsen Model
A2: =('Cover Page'!A2) -> 183 Stillwater Drive

Sheet Paint
A1: =('Cover Page'!A1) -> Veranda Bay Olsen Model
A2: =('Cover Page'!A2) -> 183 Stillwater Drive
A4: N & L Painting Pricing Sheet | B4: Unit @ | C4: Unit | D4: Quanity | E4: Cost
A5: Acrylic Deck Labor | B5: 2 | C5: SF
A6: Garage Floor Epoxy | B6: 2.85 | C6: SF
A7: Paint Tinted walls & Ceilings, Trim Std color | B7: 195 | C7: ea
A8: Accent Paint all int doors over 2500 sf | B8: 775 | C8: Lot
A9: Accent Paint all Int doors under 2500 SF | B9: 550 | C9: Lot
A10: Accent Paint Recess per ceiling | B10: 50 | C10: ea
A11: Add for 2 story model | B11: 0.2 | C11: sf
A12: Additional Ext Door | B12: 50 | C12: Ea
A13: Add over 2500 sf, includes volume high ceilings | B13: 0.25 | C13: sf
A14: Add Barn door | B14: 60 | C14: ea
A15: Paint ceilings other color than walls - up to 2 story | B15: 500 | C15: ea
A16: Paint columns | B16: 65 | C16: ea
... A34: Paint Prep Ext. Siding for painting | B34: 200 | C34: ea
A35: Paint Stair Pulldown | B35: 25
A36: Paint Satin Walls | B36: 0.3 | C36: sf
A37: Scrubbable Paint | B37: 0.35 | C37: sf
A38: Paint Shutters per pair | B38: 50 | C38: ea
A39: Paint window sills only | B39: 10 | C39: ea
A40: Paint Ship Lap | B40: 2 | C40: TSF
A41: Paint Summer Kitchen | B41: 50 | C41: ea
A42: Painting | B42: 3.15 | C42: sf
A43: Paint/Stain Handrail/Stair (Stained Treads, risers, handrail) | B43: 7 | C43: lf
A44: Paint Stair painted spindles with stain treads | B44: 10 | C44: ea
A45: Paint Stair primed spindles with stain treads | B45: 325 | C45: ea
A46: Paint Stucco Bands Sides and rear of home | B46: 0
A47: Paint Stucco Columns | B47: 65 | C47: ea
A48: Paint stop n drop | B48: 150 | C48: ea
A49: Paint stair skirt board and handrail | B49: 150 | C49: ea
A50: Paint stair treads & Risers | B50: 70 | C50: ea
A51: Paitn stair spindles and stain handrail | B51: 7 | C51: ea
A52: Paint Transom Glass | B52: 5 | C52: ea
A53: Paint Window Seat | B53: 175 | C53: ea
A54: Paint Window Wrap & Sill | B54: 2.2 | C54: ea
A55: Paint Wood Wall Cap any size | B55: 15 | C55: ea
A56: paint wood columns 8' and over | B56: 25 | C56: ea
A57: Stain/Paint Box out | B57: 75 | C57: ea
A58: Stain Chair Rail | B58: 3 | C58: LF
... A67: Interior Tongue & Groove Stain | B67: 2 | C67: LF

Sheet Flooring
A1: =('Cover Page'!A1) -> Veranda Bay Olsen Model
A2: =('Cover Page'!A2) -> 183 Stillwater Drive
A6: Tile Floors matl
A7: Tile floor labor
A8: Woodfloors
A9: Carpet Install
A10: Master bathroom
A11: Shower flor
A12: Sills
A13: Seat
A14: Bath 2 tile walls
A15: Bath 2 shower floor
A16: Bath 2 sills
A17: Bath 3 tiel walls
... A22: Cermaic fixt

Sheet Plumbing
A1: Model - 183 Stillwater
A3: Plumbing Selection Form
O4: Base
A5: Pipe material: | B5: CPVC all areas
A6: Water Heater: | B6: 1 -Tankless heater RUR 199EP Rinnai | O6: 2600
A7: Hot water heater system: | B7: Gas
A8: Reciruit system: | B8: built in recirculating pump with transfer valve
A9: Water meter notes: | B9: 1" from water meter
A11: Utilities
A12: Washing machine: | B12: 1 | C12: recessed box with hammer arrestors
A13: Sewer lines: | C13: 4" 3034 sewer pipe
A14: Water lines: | C14: CPVC
A15: A/C chase: | C15: Include
A16: Fridge: | B16: 1
A17: Dishwasher: | B17: 1
A18: Hose bibs: | B18: 4
A21: Plumbing Fixtures | O21: Builder Cost
A22: Kitchen Island | O22: Brantford
B23: Qty
A24: Sink: | B24: 1 | C24: GSM-3218 Dakota-supplied by granite company-single bowl sink
A25: sink faucet: | B25: 1 | C25: Moen Brantford 7185ORB | O25: =459*1.07 -> 491.13
A26: Disposal: | B26: 1 | C26: 1/2 HP Insinkerator badger 5 | O26: =154.23*1.07 -> 165.0261
A27: Air switch: | C27: None
A28: Pot filler: | C28: None
A30: Laundry room
B31: Qty
A32: sink: | B32: 1 | C32: GSM-2318 Dakota-supplied by granite company
A33: sink faucet: | B33: 1 | C33: Moen Brantford 7185ORB | O33: =459*1.07 -> 491.13
A35: Pantry
B36: Qty
A37: sink: | B37: 1 | C37: GSM-2318 Dakota-supplied by granite company
A38: sink faucet: | B38: 1 | C38: Moen Brantford 7185ORB | O38: =459*1.07 -> 491.13
A40: Bar
B41: Qty
A42: sink: | B42: 1 | C42: GSM-2318 Dakota-supplied by granite company
A43: sink faucet: | B43: 1 | C43: Moen Brantford 7185ORB | O43: =459*1.07 -> 491.13
A45: Master bathroom
B46: Qty
A47: sink: | B47: 2 | C47: sinks undermount-supplied by granite company
A48: sink faucet: | B48: 2 | C48: Moen Brantford TV6620ORB with corresponding valve | O48: =600*1.07 -> 642
A49: Shower fixture: | B49: 1 | C49: Moen Brantford T2152ORB with corresponding valve | O49: =225.72*1.07 -> 241.5204
A50: Roman Tub faucet: | B50: 1 | C50: Moen Brantford T933ORB with corresponding valve | O50: =494*1.07 -> 528.58
A51: Toilet: | B51: 1 | C51: Highline comfort 2 piece elongated chair height model# K-4636 seat model# K-3999 | O51: 412
C52: match handle to fuacet colors
A53: Tub: | B53: 1 | C53: Freestanding-Paloma from Royal bath | I53: 1200 | O53: 1500
A54: Notes: | C54: 3/4 inch to the master bathroom
A56: Bath #2
B57: Qty
A58: sink: | B58: 1 | C58: sinks undermount-supplied by granite company
A59: sink faucet: | B59: 1 | C59: Moen Brantford TV6620ORB with corresponding valve | O59: =300*1.07 -> 321
A60: Shower fixture: | B60: 1 | C60: Moen Brantford T2153ORB with corresponding valve | O60: =270*1.07 -> 288.9
A61: Toilet: | B61: 1 | C61: Highline comfort 2 piece elongated chair height model# K-4636 seat model# K-3999 | O61: 412
C62: match handle to fuacet colors
A63: Tub: | B63: 1 | C63: American standard #2393 Princeton 60" shite porcelian enameled steel tub | O63: 700
C64: right hand drain alcove bathtub-olor White
A66: Bath #3
B67: Qty
A68: sink: | B68: 1 | C68: sinks undermount-supplied by granite company
A69: sink faucet: | B69: 1 | C69: Moen Brantford TV6620ORB with corresponding valve | O69: 321
A70: Shower fixture: | B70: 1 | C70: Moen Brantford T2152ORB with corresponding valve | O70: 288.9
A71: Toilet: | B71: 1 | C71: Highline comfort 2 piece elongated chair height model# K-4636 seat model# K-3999 | O71: 412
C72: match handle to fuacet colors
A74: Summer kitchen
A75: Preplumb only: | B75: 1 | C75: yes
A76: sink faucet: | B76: 1 | C76: 5965SRS Align Spot Resist Stainless One-Handle Arce Pulldown Bar Faucet (Deck Plate or Sink Hole?) | L76: 440.66 | O76: 510
N78: Base Total | O78: =SUM(O6:O77) -> 11307.447
M80: Leading Edge Labor Only | O80: 16500
N82: Total Base Plumbing | O82: =SUM(O78:O80) -> 27807.446

Sheet Electric
A1: =('Cover Page'!A1) -> Veranda Bay Olsen Model
A2: =('Cover Page'!A2) -> 183 Stillwater Drive

Sheet Cabinets
A1: =('Cover Page'!A1) -> Veranda Bay Olsen Model
A2: =('Cover Page'!A2) -> 183 Stillwater Drive

Sheet Granite
A1: =('Cover Page'!A1) -> Veranda Bay Olsen Model
A2: =('Cover Page'!A2) -> 183 Stillwater Drive

Sheet Summer Kitchen
A1: =('Cover Page'!A1) -> Veranda Bay Olsen Model
A2: =('Cover Page'!A2) -> 183 Stillwater Drive
A5: Appliances
A6: Cabinet
A7: Granite
A8: Electric
A9: Faucet

Sheet Specialty
A1: =('Cover Page'!A1) -> Veranda Bay Olsen Model
A2: =('Cover Page'!A2) -> 183 Stillwater Drive
